Workbook

Sheet Raw_Data_Collection
A1: Ranking | B1: Name | C1: Net worth | D1: Net Worth Expanded | E1: Residence | F1: Moving? (Y/N) | G1: House Price | H1: House Price Source | I1: House Price (Assessed) Year | J1: Total Residential Real Estate | K1: TRRE Price (Assessed) Year(s) | L1: TRRE Source | M1: Notes | N1: Moving Source
A2: 1 | B2: Larry Page | C2: $256.2B | D2: 256200000000 | E2: Palo Alto | F2: Y | G2: 101500000 | H2: https://elmundomiami.com/economy/larry-page-invests-173-4-million-in-the-miami-real-estate-market/ | I2: 2024 | M2: Page's primary residence is now a Florida mansion. | N2: https://www.businessinsider.com/larry-page-leave-california-wealth-billionaire-tax-koop-google-2026-1
A3: 2 | B3: Larry Ellison | C3: $246.1B | D3: 246100000000 | E3: Woodside | F3: Y | G3: 45000000 | H3: https://sfstandard.com/2026/01/05/larry-ellison-san-francisco-home-sale/ | I3: 2025 | M3: Sold property in late 2025. | N3: https://www.sfchronicle.com/california/article/larry-page-larry-ellison-california-wealth-tax-21281843.php
A4: 3 | B4: Sergey Brin | C4: $236.4B | D4: 236400000000 | E4: Los Altos | F4: Y | G4: 35000000 | I4: 2025 | N4: https://www.aol.com/news/google-cofounders-sergey-brin-larry-195211174.html
A5: 4 | B5: Mark Zuckerberg | C5: $225.1B | D5: 225100000000 | E5: Palo Alto | F5: N | G5: 112000000 | H5: https://www.realtor.com/news/celebrity-real-estate/mark-zuckerberg-palo-alto-home-fury-neighbors/ | I5: 2025 | J5: 300000000 | K5: 2011-2025 | L5: https://robbreport.com/shelter/celebrity-homes/mark-zuckerberg-property-portfolio-1236712447/ | M5: Zuckerberg's compund consists of 11 different properties ranging from $5 million to $15 million.
A6: 5 | B6: Jensen Huang | C6: $162.6B | D6: 162600000000 | E6: Los Altos | F6: N | G6: 6900000 | H6: https://www.yahoo.com/lifestyle/articles/3-most-expensive-properties-nvidia-115457861.html | I6: 2025 | J6: 52400000 | K6: 2004 | L6: https://www.foxbusiness.com/lifestyle/nvidias-ceo-extensive-rich-real-estate-portfolio | M6: Huang also has a $38 million San Francisco Mansion. | N6: https://uk.finance.yahoo.com/news/nvidia-jensen-huang-perfectly-fine-170800688.html
A7: 6 | B7: Eric Schmidt | C7: $35.6B | D7: 35600000000 | E7: Los Angeles | F7: N | G7: 110000000 | I7: 2025 | J7: 600000000 | K7: 2025 | L7: https://robbreport.com/shelter/celebrity-homes/lists/eric-schmidt-property-portfolio-1236832435/ | M7: Schmidt also bought a $30.8 million estate in Montecito in 2020.
A8: 7 | B8: Henry Samueli | C8: $32B | D8: 32000000000 | E8: Newport Beach | F8: N | G8: 20150000 | H8: https://www.urbansplatter.com/2024/06/henry-samueli-house-the-california-dwelling/ | I8: 2024 | J8: 20150000 | K8: 2024 | L8: https://www.urbansplatter.com/2024/06/henry-samueli-house-the-california-dwelling/ | M8: Samueli only seems to have one residence.
A9: 8 | B9: Peter Thiel | C9: $26.7B | D9: 26700000000 | E9: Los Angeles | F9: Y | G9: 11500000 | H9: https://labusinessjournal.com/technology/billionaire-peter-thiel-moving-los-angeles/ | I9: 2018 | J9: 77200000 | K9: 2012-2024 | L9: https://www.loveproperty.com/gallerylist/73268/billionaire-boltholes-to-survive-the-end-of-the-world; https://shopoahuproperties.com/paypal-co-founder-peter-thiel-buys-maui-home-for-27m/; https://press.farm/inside-peter-thiels-lifestyle/; https://www.aol.com/news/fords-former-ceo-just-sold-164442537.html; https://press.farm/inside-peter-thiels-lifestyle/ | N9: https://www.forbes.com/sites/tylerroush/2025/12/27/possible-california-wealth-tax-causes-billionaire-freakout-page-thiel-threaten-to-leave/
A10: 9 | B10: Robert Pera | C10: $25.5B | D10: 25500000000 | E10: San Jose | F10: N | G10: 21550000 | H10: https://www.dailymail.co.uk/sport/nba/article-12947653/Memphis-Grizzlies-billionaire-owner-Robert-Pena-Star-Island-arena.html | I10: 2024 | M10: Pera's primary residence is in San Jose, but no sources confirm its value. One of Pera's other residences is a $21.5 million NYC penthouse.
A11: 10 | B11: Adam Foroughi | C11: $25B | D11: 25000000000 | E11: Truckee | F11: N | M11: Homes.com shows Foroughi sold his Truckee home in 2021: https://www.homes.com/property/2413-newhall-ct-truckee-ca/1egj3t32qvw4h/
A12: 11 | B12: Henry Nicholas III | C12: $21.9B | D12: 21900000000 | E12: Newport Coast | F12: N | G12: 19777777 | H12: https://hauteliving.com/2010/01/haute-estate-19-8-million-newport-coast-mansion/18762/ | I12: 2010 | J12: 19777777 | K12: 2010 | L12: https://hauteliving.com/2010/01/haute-estate-19-8-million-newport-coast-mansion/18762/
A13: 12 | B13: John Doerr | C13: $20B | D13: 20000000000 | E13: Woodside | F13: N
A14: 13 | B14: Donald Bren | C14: $19.2B | D14: 19200000000 | E14: Newport Beach | F14: N
A15: 14 | B15: Eric Smidt | C15: $17.9B | D15: 17900000000 | E15: Beverly Hills | F15: N | G15: 54000000 | H15: https://labusinessjournal.com/special-editions/wealthiest-angelenos/wealthiest-2023/10-eric-smidt/ | I15: 2023
A16: 15 | B16: John Tu | C16: $17.5B | D16: 17500000000 | E16: Rolling Hills | F16: N | G16: 7250000 | H16: https://blockshopper.com/ca/los-angeles-county/rolling-hills/property/7567015025/6-east-crest-road | I16: 2011
A17: 16 | B17: David Sun | C17: $17.5B | D17: 17500000000 | E17: Irvine | F17: N
A18: 17 | B18: Jan Koum | C18: $17.1B | D18: 17100000000 | E18: Atherton | F18: Y | G18: 187000000 | H18: https://www.celebritynetworth.com/articles/celebrity-homes/two-years-after-paying-100-million-for-a-malibu-mansion-whatsapp-founder-buys-the-house-next-door-for-87-million/ | I18: 2021 | J18: 400000000 | K18: 2021 | L18: https://www.celebritynetworth.com/articles/billionaire-news/jan-koum-grew-up-on-food-stamps-and-now-owns-more-than-400-million-worth-of-california-real-estate/ | M18: Koum's $187 million compound consists of two houses. | N18: https://nypost.com/2026/01/08/real-estate/tech-titans-leaving-california-for-florida-over-billionaire-tax/
A19: 18 | B19: George Roberts | C19: $15.9B | D19: 15900000000 | E19: Atherton | F19: N | G19: 29084160 | H19: https://blockshopper.com/ca/san-mateo-county/atherton/property/070032440/260-atherton-avenue | I19: 2020
A20: 19 | B20: Laurene Powell Jobs | C20: $14B | D20: 14000000000 | E20: San Francisco | F20: N | G20: 70000000 | H20: https://fortune.com/2024/07/13/laurene-powell-jobs-buys-mansion-san-francisco-billionaires-row-70-million-record-high/ | I20: 2024 | J20: 242000000 | K20: 2015-2024 | L20: https://fortune.com/2024/06/17/laurene-powell-jobs-94-million-malibu-mansion-apple-steve-jobs-widow/; https://www.architecturaldigest.com/story/laurene-powell-jobs-buys-record-breaking-san-francisco-home
A21: 20 | B21: Jack Dangermond | C21: $13.8B | D21: 13800000000 | E21: Redlands | F21: N
A22: 21 | B22: Antony Ressler | C22: $13.1B | D22: 13100000000 | E22: Los Angeles | F22: N | G22: 60000000 | H22: https://www.finance-monthly.com/antony-resslers-net-worth-2025-billionaire-financier-sports-owner-and-philanthropist/ | I22: 2025 | J22: 100000000 | K22: 2025 | L22: https://www.finance-monthly.com/antony-resslers-net-worth-2025-billionaire-financier-sports-owner-and-philanthropist/ | M22: Ressler's various LA properties are estimated to be worth over $100,000,000.
A23: 22 | B23: Vinod Khosla | C23: $12.5B | D23: 12500000000 | E23: Portola Valley | F23: N | G23: 17100579 | H23: https://www.homes.com/property/630-los-trancos-rd-portola-valley-ca/lsj62j03bbdml/ | I23: 2026 | J23: 17100579 | K23: 2026 | L23: https://www.homes.com/property/630-los-trancos-rd-portola-valley-ca/lsj62j03bbdml/ | M23: Estimated value on homes.com is $6,290,000 - $17,100,579, owned by Ltn Trust and Khosla, likely owned by Vinod Khosla secondary source: https://virtualglobetrotting.com/map/vinod-khoslas-house/view/google/
A24: 23 | B24: Riley Bechtel | C24: $11.6B | D24: 11600000000 | E24: Woodside | F24: N | G24: 63300000 | H24: https://www.yahoo.com/entertainment/billionaire-riley-bechtel-pays-record-201404351.html | I24: 2020 | J24: 86100000 | K24: 2011-2020 | L24: https://www.yahoo.com/entertainment/billionaire-riley-bechtel-pays-record-201404351.html
A25: 24 | B25: Dustin Moskovitz | C25: $11.2B | D25: 11200000000 | E25: San Francisco | F25: N | G25: 800000 | H25: https://www.seattletimes.com/business/young-tech-millionaires-keeping-1-bedroom-lifestyle/ | I25: 2011 | M25: Moskovitz' primary residence is an $800,000 San Francisco condo.
A26: 25 | B26: Douglas Leone | C26: $10.7B | D26: 10700000000 | E26: Napa | F26: N | G26: 10000000 | H26: https://www.celebritynetworth.com/richest-businessmen/richest-billionaires/douglas-leone-net-worth/ | I26: 2026 | J26: 80000000 | K26: 2000-2026 | L26: https://www.celebritynetworth.com/richest-businessmen/richest-billionaires/douglas-leone-net-worth/
A27: 26 | B27: Chris Larsen | C27: $10.2B | D27: 10200000000 | E27: San Francisco | F27: N | G27: 13500000 | H27: https://sfstandard.com/2025/09/09/chris-larsen-napa-home/ | I27: 2025 | J27: 13500000 | K27: 2025 | L27: https://docs.google.com/spreadsheets/d/1-d_IAr8tITUy_s8QmIzH-FLYoODzaBxNMWShu9W7IFk/edit?gid=1121030019#gid=1121030019
A28: 27 | B28: Brian Armstrong | C28: $10.1B | D28: 10100000000 | E28: Los Angeles | F28: N | G28: 133000000 | H28: https://www.urbansplatter.com/2022/05/brian-armstrong-house-the-los-angeles-mansion/ | I28: 2022 | J28: 133000000 | K28: 2022 | L28: https://www.urbansplatter.com/2022/05/brian-armstrong-house-the-los-angeles-mansion/
A29: 28 | B29: Marijke Mars | C29: $10B | D29: 10000000000 | E29: Los Angeles | F29: N
A30: 29 | B30: Tom Gores | C30: $10B | D30: 10000000000 | E30: Beverly Hills | F30: N | G30: 100000000 | H30: https://therealdeal.com/la/2016/10/24/platinum-equity-ceo-buys-holmby-hills-spec-home-for-100m/ | I30: 2016 | J30: 138000000 | K30: 2016-2017 | L30: https://therealdeal.com/la/2016/10/24/platinum-equity-ceo-buys-holmby-hills-spec-home-for-100m/; https://therealdeal.com/la/2017/12/04/detroit-pistons-owner-tom-gores-pays-38m-for-his-former-beverly-park-home/
A31: 30 | B31: Andrew Karam | C31: $9.8B | D31: 9800000000 | F31: N
A32: 31 | B32: Brian Chesky | C32: $9.6B | D32: 9600000000 | E32: San Francisco | F32: N | N32: https://www.washingtonpost.com/technology/2026/01/19/california-wealth-tax-exodus/
A33: 32 | B33: Marc Benioff | C33: $9.3B | D33: 9300000000 | E33: San Francisco | F33: N | G33: 18000000 | H33: https://www.yahoo.com/entertainment/twitter-ceo-jack-dorsey-scoops-011751538.html | I33: 2009
A34: 33 | B34: David Geffen | C34: $9.2B | D34: 9200000000 | E34: Beverly Hills | F34: N | G34: 68000000 | H34: https://finance.yahoo.com/news/david-geffen-completes-68-million-192458970.html | I34: 2020 | J34: 132000000 | K34: 2010-2020 | L34: https://www.inman.com/2020/06/11/entertainment-mogul-david-geffen-buys-la-luxury-estate-for-68m/; https://www.forbes.com/sites/erincarlyle/2014/05/07/a-look-at-billionaire-david-geffens-1-1-billion-stash-of-dream-palaces/
A35: 34 | B35: Nathan Blecharczyk | C35: $9.1B | D35: 9100000000 | E35: San Francisco | F35: N
A36: 35 | B36: Lynsi Snyder | C36: $8.6B | D36: 8600000000 | E36: Glendora | F36: Y | M36: Confirmed to be moving, not clear if due to CA Wealth Tax | N36: https://apnews.com/article/innout-ceo-moving-af175b4926847325970b5bcba52276fe
A37: 36 | B37: Steven Rales | C37: $8.6B | D37: 8600000000 | E37: Santa Barbara | F37: N
A38: 37 | B38: Don Hankey | C38: $8.1B | D38: 8100000000 | E38: Malibu | F38: Y | G38: 10659988 | H38: https://www.homes.com/property/27450-pacific-coast-hwy-malibu-ca/gt8keb94hyyzn/ | I38: 2026 | J38: 51300000 | K38: 2021-2026 | L38: https://www.reviewjournal.com/business/housing/l-a-billionaire-buys-summerlin-condo-for-record-high-21m-3609182/; https://therealdeal.com/miami/2021/10/13/billionaire-don-hankey-buys-oceanfront-highland-beach-mansion-for-30m/ | M38: Estimated value on homes.com is $6,882,000 - $19,119,746 | N38: https://www.forbes.com/sites/chasewithorn/2026/01/15/los-angeles-billionaire-moves-to-nevada-after-california-threatens-to-tax-wealth/
A39: 38 | B39: Tench Coxe | C39: $7.8B | D39: 7800000000 | E39: Palo Alto | F39: N | G39: 8683775 | H39: https://www.homes.com/property/1401-emerson-st-palo-alto-ca/znpl6z10qsgvy/ | I39: 2026 | J39: 8683775 | K39: 2026 | L39: https://www.homes.com/property/1401-emerson-st-palo-alto-ca/znpl6z10qsgvy/ | M39: Estimated value on homes.com is $5,573,000 $8,683,775
A40: 39 | B40: Michael Moritz | C40: $7.7B | D40: 7700000000 | E40: San Francisco | F40: N | G40: 10600000 | H40: https://blockshopper.com/ca/san-francisco-county/san-francisco/property/0953006/2626-vallejo-street | I40: 2002 | J40: 10600000 | K40: 2002 | L40: https://blockshopper.com/ca/san-francisco-county/san-francisco/property/0953006/2626-vallejo-street | N40: https://www.bloomberg.com/news/articles/2026-01-08/california-wealth-tax-threat-pushes-billionaires-to-texas-florida
A41: 40 | B41: Edward Roski Jr | C41: $7.6B | D41: 7600000000 | E41: Los Angeles | F41: N | G41: 8107000 | H41: https://www.homes.com/property/10051-valley-spring-ln-toluca-lake-ca/kd8ylmg68cld1/ | I41: 2026 | J41: 8107000 | K41: 2026 | L41: https://www.homes.com/property/10051-valley-spring-ln-toluca-lake-ca/kd8ylmg68cld1/ | M41: Estimated value on homes.com is $6,522,000 - $8,107,000.
A42: 41 | B42: Michael Milken | C42: $7.4B | D42: 7400000000 | E42: Los Angeles | F42: N | G42: 102000000 | H42: https://www.forbes.com/sites/trulia/2014/04/04/las-super-mansion-fleur-de-lys-sells-for-a-record-breaking-102-million/ | I42: 2014 | J42: 179750000 | K42: 2011-2026 | L42: https://palisadesnews.com/michael-milkens-pacific-palisades-estate-goes-on-sale-for-64-million/; https://virtualglobetrotting.com/map/michael-milkens-house-4/view/google/; https://www.forbes.com/sites/trulia/2014/04/04/las-super-mansion-fleur-de-lys-sells-for-a-record-breaking-102-million/
A43: 42 | B43: Steven Spielberg | C43: $7B | D43: 7000000000 | E43: Pacific Palisades | F43: N | G43: 250000000 | H43: https://www.finance-monthly.com/steven-spielbergs-net-worth-9-5-billion-in-2025/ | I43: 2024 | J43: 250000000 | K43: 2024 | L43: https://www.finance-monthly.com/steven-spielbergs-net-worth-9-5-billion-in-2025/ | M43: Spielberg's property is estimated to be between $100 million and $250 million.
A44: 43 | B44: Edythe Broad | C44: $6.9B | D44: 6900000000 | E44: Los Angeles | F44: N | G44: 13283376 | H44: https://www.homes.com/property/75-oakmont-dr-los-angeles-ca/tcbdp4fxzjekc/ | I44: 2026 | J44: 13283376 | K44: 2026 | L44: https://www.homes.com/property/75-oakmont-dr-los-angeles-ca/tcbdp4fxzjekc/ | M44: Owned by Broad Revocable Trust: Estimated value on homes.com is $7,420,000 - $13,283,376
A45: 44 | B45: Scott Cook | C45: $6.9B | D45: 6900000000 | E45: Woodside | F45: N | G45: 15830193 | H45: https://www.homes.com/property/376-mountain-home-rd-woodside-ca/p6sh3hp6plvk6/ | I45: 2026 | J45: 15830193 | K45: 2026 | L45: https://www.homes.com/property/376-mountain-home-rd-woodside-ca/p6sh3hp6plvk6/ | M45: Estimated value on homes.com is 6,309,000-15,830,193
A46: 45 | B46: Baiju Bhatt | C46: $6.7B | D46: 6700000000 | E46: Palo Alto | F46: N
A47: 46 | B47: Vlad Tenev | C47: $6.4B | D47: 6400000000 | E47: Palo Alto | F47: N
A48: 47 | B48: John A. Sobrato | C48: $6.4B | D48: 6400000000 | E48: Atherton | F48: N | N48: https://www.bloomberg.com/news/articles/2026-01-08/california-wealth-tax-threat-pushes-billionaires-to-texas-florida
A49: 48 | B49: Stephen Cohen | C49: $6.3B | D49: 6300000000 | E49: Palo Alto | F49: N | G49: 1031715 | H49: https://www.homes.com/property/20-willow-rd-menlo-park-ca-unit-8/hbwec8jc2rsrg/ | I49: 2026 | M49: Estimated value on homes.com is $916,859 - $1,131,000
A50: 49 | B50: Rick Caruso | C50: $5.9B | D50: 5900000000 | E50: Los Angeles | F50: N | G50: 80000000 | H50: https://xabisinc.com/blog/rick-carusos-net-worth-the-secrets-behind-his-real-estate-success/ | I50: 2025 | J50: 86500000 | K50: 2015-2025 | L50: https://www.celebritynetworth.com/richest-businessmen/richest-billionaires/rick-caruso-net-worth/ | M50: Caruso's primary estate is estimated to be worth $60-80 million.
A51: 50 | B51: Ken Xie | C51: $5.7B | D51: 5700000000 | E51: Los Altos Hills | F51: N | G51: 18104324 | H51: https://www.homes.com/property/352-atherton-ave-atherton-ca/x8c1bf64k72nl/ | I51: 2026 | J51: 14340561 | K51: 2004-2024 | L51: https://www.celebritynetworth.com/richest-businessmen/richest-billionaires/ken-xie-net-worth/; https://blockshopper.com/ca/san-mateo-county/atherton/property/070120060/9-tuscaloosa-avenue
A52: 51 | B52: Jayshree Ullal | C52: $5.6B | D52: 5600000000 | E52: Saratoga | F52: N | G52: 877000 | H52: https://www.homes.com/property/190-n-lafayette-st-tracy-ca/x6xzt2lw9j9cx/ | I52: 2026 | J52: 7862000 | K52: 2026 | L52: https://www.homes.com/property/19384-chablis-ct-saratoga-ca/e3n5y70n6ed3h/; https://www.homes.com/property/190-n-lafayette-st-tracy-ca/x6xzt2lw9j9cx/ | M52: Estimated values on homes.com is $803,000 - $877,000 and $6,190,389 - $6,985,000.
A53: 52 | B53: Archie Aldis Emmerson | C53: $5.6B | D53: 5600000000 | E53: Redding | F53: N | G53: 4101800 | H53: https://www.zillow.com/homedetails/18988-Smith-Rd-Redding-CA-96002/15212777_zpid/ | I53: 2026 | J53: 4101800 | K53: 2026 | L53: https://www.zillow.com/homedetails/18988-Smith-Rd-Redding-CA-96002/15212777_zpid/ | M53: Used this source to find initial address: https://virtualglobetrotting.com/map/red-emmersons-house/view/google/ , then confirmed with deed lookup: https://recorderselfservice.shastacounty.gov/web/document/DOCCOR-2501886?search=DOCSEARCH344S5
A54: 53 | B54: Romesh T. Wadhwani | C54: $5.5B | D54: 5500000000 | E54: Palo Alto | F54: N | G54: 13169940 | H54: https://www.homes.com/property/26170-w-fremont-rd-los-altos-hills-ca/b1fflmh2yhezd/ | I54: 2026 | J54: 13169940 | K54: 2026 | L54: https://www.homes.com/property/26170-w-fremont-rd-los-altos-hills-ca/b1fflmh2yhezd/ | M54: Estimated value on homes.com is $9,313,000 - $13,169,940
A55: 54 | B55: Neal Blue | C55: $5.4B | D55: 5400000000 | E55: San Diego | F55: N
A56: 55 | B56: Gordon Getty | C56: $5.4B | D56: 5400000000 | E56: San Francisco | F56: N | G56: 29608760 | H56: https://blockshopper.com/ca/san-francisco-county/san-francisco/property/0958030/2870-broadway-street; https://www.redfin.com/CA/San-Francisco/2870-Broadway-St-94115/home/1811887#property-details | I56: 2026 | J56: 29608760 | K56: 2026 | L56: https://blockshopper.com/ca/san-francisco-county/san-francisco/property/0958030/2870-broadway-street; https://www.redfin.com/CA/San-Francisco/2870-Broadway-St-94115/home/1811887#property-details | M56: Estimated value on redfin.com is $29,608,760.
A57: 56 | B57: Patrick Soon-Shiong | C57: $5.4B | D57: 5400000000 | E57: Los Angeles | F57: N | G57: 30000000 | H57: https://www.celebritynetworth.com/articles/celebrity-homes/patrick-soon-shiongs-house-brentwood-billionaire-doctor-demolished-seven-houses-build-one-insane-mega-property/ | I57: 2014 | J57: 162500000 | K57: 2005-2016 | L57: https://www.ocregister.com/2016/02/04/oceanfront-laguna-beach-estate-twin-points-sells-for-record-shattering-45-million/; https://virtualglobetrotting.com/map/patrick-soon-shiongs-house-2/view/google/; https://www.ocbj.com/special-report/ocs-wealthiest-2024/ocs-wealthiest-2024-patrick-soon-shiong/; https://www.celebritynetworth.com/articles/celebrity-homes/patrick-soon-shiongs-house-brentwood-billionaire-doctor-demolished-seven-houses-build-one-insane-mega-property/ | M57: Main estate consists of 7 properties combined for $30 million dollars according to celebritynetworth.com
A58: 57 | B58: Jean (Gigi) Pritzker | C58: $5.4B | D58: 5400000000 | E58: Los Angeles | F58: N
A59: 58 | B59: Stewart Resnick | C59: $5.3B | D59: 5300000000 | E59: Beverly Hills | F59: N | G59: 17115689 | H59: https://www.homes.com/property/9491-sunset-blvd-beverly-hills-ca/sw2h7klpb942m/ | I59: 2026 | J59: 17115689 | K59: 2026 | L59: https://www.homes.com/property/9491-sunset-blvd-beverly-hills-ca/sw2h7klpb942m/ | M59: Estimated value on homes.com is $8,902,000 - $17,115,689.
A60: 59 | B60: Lynda Resnick | C60: $5.3B | D60: 5300000000 | E60: Beverly Hills | F60: N | G60: 17115689 | H60: https://www.homes.com/property/9491-sunset-blvd-beverly-hills-ca/sw2h7klpb942m/ | I60: 2026 | J60: 17115689 | K60: 2026 | L60: https://www.homes.com/property/9491-sunset-blvd-beverly-hills-ca/sw2h7klpb942m/ | M60: Estimated value on homes.com is $8,902,000 - $17,115,689.
A61: 60 | B61: Eduardo Vivas | C61: $5.3B | D61: 5300000000 | E61: Palo Alto | F61: N
A62: 61 | B62: George Lucas | C62: $5.3B | D62: 5300000000 | E62: San Anselmo | F62: N | G62: 41600000 | H62: https://www.marinij.com/2023/07/29/george-lucas-sues-to-secure-san-anselmo-parcel-ownership/ | I62: 2026 | J62: 123000000 | K62: 2010-2023 | L62: https://robbreport.com/shelter/celebrity-homes/lists/george-lucas-property-portfolio-1237348814/; https://www.sfgate.com/realestate/article/George-Lucas-Carpinteria-houses-owned-property-14885154.php; https://www.marinij.com/2023/07/29/george-lucas-sues-to-secure-san-anselmo-parcel-ownership/ | M62: Lucas also owns "Skywalker Ranch", but this is not a residential property and is instead used for business.
A63: 62 | B63: Reed Hastings | C63: $5.1B | D63: 5100000000 | E63: Santa Cruz | F63: Y | G63: 1750000 | H63: https://www.celebritynetworth.com/richest-businessmen/ceos/reed-hastings-net-worth/ | I63: 2016 | J63: 3250000 | K63: 2013-2016 | L63: https://www.celebritynetworth.com/richest-businessmen/ceos/reed-hastings-net-worth/ | M63: Hastings also owns property in Hollywood. | N63: https://nypost.com/2026/01/08/real-estate/tech-titans-leaving-california-for-florida-over-billionaire-tax/
A64: 63 | B64: Eric Yuan | C64: $5.1B | D64: 5100000000 | E64: Santa Clara | F64: N
A65: 64 | B65: Gwendolyn Sontheim Meyer | C65: $5B | D65: 5000000000 | E65: Rancho Santa Fe | F65: N
A66: 65 | B66: Jim Coulter | C66: $5B | D66: 5000000000 | E66: San Francisco | F66: N
A67: 66 | B67: Jack Dorsey | C67: $4.9B | D67: 4900000000 | E67: San Francisco | F67: N | G67: 31900000 | H67: https://www.yahoo.com/entertainment/twitter-ceo-jack-dorsey-scoops-011751538.html | I67: 2018 | J67: 31900000 | K67: 2012-2018 | L67: https://www.yahoo.com/entertainment/twitter-ceo-jack-dorsey-scoops-011751538.html; https://www.yahoo.com/entertainment/jack-dorsey-hollywood-hills-hideaway-015224916.html | M67: Compound consists of two residences, one bought in 2012 for $10 million and one bought in 2019 for $21.9 million. His Hollywood Hills residence was later sold.
A68: 67 | B68: David Baszucki | C68: $4.9B | D68: 4900000000 | E68: San Francisco | F68: N
A69: 68 | B69: Scott Crabill | C69: $4.8B | D69: 4800000000 | E69: San Francisco | F69: N | G69: 22222762 | H69: https://www.homes.com/property/34-maple-st-san-francisco-ca/83sknmj9zbck7/ | I69: 2026 | J69: 59322762 | K69: 2017-2026 | L69: https://www.homes.com/property/34-maple-st-san-francisco-ca/83sknmj9zbck7/; https://www.compass.com/homedetails/1710-Cabernet-Ln-St-Helena-CA-94574/7885975409678385_lid/; https://www.compass.com/homedetails/12-Upper-Ames-Ave-Ross-CA-94957/1018950796530693897_lid/; https://www.compass.com/homedetails/3712-Jackson-St-San-Francisco-CA-94118/778822386949832337_lid/ | M69: Estimated value on homes.com is $7,527,000 - $22,222,762.
A70: 69 | B70: Holden Spaht | C70: $4.8B | D70: 4800000000 | E70: San Francisco | F70: N | G70: 6849000 | H70: https://www.homes.com/property/2324-pacific-ave-san-francisco-ca/qpzresp8fbygw/ | I70: 2026 | J70: 6849000 | K70: 2026 | L70: https://www.homes.com/property/2324-pacific-ave-san-francisco-ca/qpzresp8fbygw/ | M70: Estimated value on homes.com is $6,849,000.
A71: 70 | B71: Seth Boro | C71: $4.8B | D71: 4800000000 | E71: San Anselmo | F71: N | G71: 5884000 | H71: https://www.homes.com/property/429-elizabeth-st-san-francisco-ca/xpxfwnhw0x4kw/ | I71: 2026 | J71: 5884000 | K71: 2026 | L71: https://www.homes.com/property/429-elizabeth-st-san-francisco-ca/xpxfwnhw0x4kw/ | M71: Estimated value on homes.com is $2,842,000 - $5,884,000.
A72: 71 | B72: Michael Xie | C72: $4.8B | D72: 4800000000 | E72: Los Altos Hills | F72: N | G72: 13269963 | H72: https://www.homes.com/property/27161-w-fremont-rd-los-altos-hills-ca/yneqges0z8j44/ | I72: 2026 | J72: 25671792 | K72: 2026 | L72: https://www.homes.com/property/27161-w-fremont-rd-los-altos-hills-ca/yneqges0z8j44/; https://www.homes.com/property/1218-portola-rd-pebble-beach-ca/pyl3bhymmvf5d/ | M72: Estimated value on homes.com is $8,136,000 - $13,269,963
A73: 72 | B73: Dagmar Dolby | C73: $4.8B | D73: 4800000000 | E73: San Francisco | F73: N | G73: 7809894 | H73: https://www.homes.com/property/3340-jackson-st-san-francisco-ca/lemwwpgc5tfrh/ | I73: 2026 | J73: 90000000 | K73: 2023 | L73: https://www.forbes.com/sites/forbeswealthteam/2023/08/26/when-10-homes-isnt-enough-which-billionaires-own-the-most-properties-larry-ellison-jeff-bezos-oprah-winfrey/ | M73: Estimated value on homes.com is $5,631,000 - $7,809,894.
A74: 73 | B74: David Filo | C74: $4.5B | D74: 4500000000 | E74: Palo Alto | F74: N
A75: 74 | B75: Rupert Johnson Jr | C75: $4.4B | D75: 4400000000 | E75: Burlingame | F75: N
A76: 75 | B76: Anthony Pritzker | C76: $4.4B | D76: 4400000000 | E76: Los Angeles | F76: N | G76: 195000000 | H76: https://kanebridgenews.com/one-of-americas-biggest-homes-hits-the-market-for-195-million/ | I76: 2024 | J76: 195000000 | K76: 2024 | L76: https://kanebridgenews.com/one-of-americas-biggest-homes-hits-the-market-for-195-million/
A77: 76 | B77: Rodney Sacks | C77: $4.3B | D77: 4300000000 | E77: Laguna Beach | F77: N
A78: 77 | B78: Donald Sterling | C78: $4.3B | D78: 4300000000 | E78: Beverly Hills | F78: N | G78: 11443465 | H78: https://www.homes.com/property/808-n-beverly-dr-beverly-hills-ca/lgnr8czbm0szq/ | I78: 2026 | J78: 29825465 | K78: 2015-2026 | L78: https://www.homes.com/property/808-n-beverly-dr-beverly-hills-ca/lgnr8czbm0szq/; https://www.realtytoday.com/articles/36434/20150918/former-la-clipper-owner-donald-sterling-buys-beverly-hills-home-for-18m.htm | M78: Estimated value on homes.com is $5,584,000 - $11,443,465.
A79: 78 | B79: Sanjit Biswas | C79: $4.1B | D79: 4100000000 | E79: San Francisco | F79: N
A80: 79 | B80: Thomas Siebel | C80: $4B | D80: 4000000000 | E80: Woodside | F80: N | M80: Siebel potentially owns this Lake Tahoe estate, but not confirmed: https://www.sacbee.com/news/business/real-estate-news/article141950429.html
A81: 80 | B81: John Bicket | C81: $4B | D81: 4000000000 | E81: San Francisco | F81: N
A82: 81 | B82: José E. Feliciano | C82: $3.8B | D82: 3800000000 | E82: Los Angeles | F82: N | G82: 50000000 | H82: https://palisadesnews.com/private-equity-billionaire-jose-e-feliciano-buys-50-palisades-million-mansion-narrowly-avoids-new-mansion-tax/ | I82: 2023 | J82: 50000000 | K82: 2023 | L82: https://palisadesnews.com/private-equity-billionaire-jose-e-feliciano-buys-50-palisades-million-mansion-narrowly-avoids-new-mansion-tax/
A83: 82 | B83: Meg Whitman | C83: $3.8B | D83: 3800000000 | E83: Los Angeles | F83: N | G83: 6500000 | H83: https://www.latimes.com/business/real-estate/story/2020-08-10/quibi-chief-meg-whitman-lists-west-hollywood-condo-for-6-5-million | I83: 2020 | J83: 6500000 | K83: 2020 | L83: https://www.latimes.com/business/real-estate/story/2020-08-10/quibi-chief-meg-whitman-lists-west-hollywood-condo-for-6-5-million | M83: While listed for sale, Whitman still seems to have not sold the residence yet.
A84: 83 | B84: Behdad Eghbali | C84: $3.8B | D84: 3800000000 | E84: Los Angeles | F84: N | G84: 21000000 | H84: https://www.yahoo.com/entertainment/billionaire-behdad-eghbali-buys-21-224623408.html | I84: 2020
A85: 84 | B85: Peter Gassner | C85: $3.8B | D85: 3800000000 | E85: Pleasanton | F85: N | G85: 1977425 | H85: https://www.homes.com/property/4512-lin-gate-st-pleasanton-ca/jfjbyjdmsmcgx/ | I85: 2026 | M85: Estimated value on homes.com is $1,887,000 - $2,072,000
A86: 85 | B86: John Fisher | C86: $3.7B | D86: 3700000000 | E86: San Francisco | F86: N | G86: 29250000 | H86: https://www.casino.org/news/as-owner-buys-3rd-most-expensive-vegas-home-ever-sold/ | I86: 2025 | M86: Fisher owns other residential property besides his $29.25 million Las Vegas home, but there are no reports indicating valuations of these properties.
A87: 86 | B87: Danny Harris | C87: $3.7B | D87: 3700000000 | E87: Los Angeles | F87: N | G87: 30000000 | H87: https://therealdeal.com/la/2017/02/21/alo-yoga-founder-buys-beverly-hills-house-from-bebe-founder-for-30m/ | I87: 2017
A88: 87 | B88: Jared Kaplan | C88: $3.7B | D88: 3700000000 | E88: Pacifica | F88: N
A89: 88 | B89: Dario Amodei | C89: $3.7B | D89: 3700000000 | E89: San Francisco | F89: N
A90: 89 | B90: Tom Brown | C90: $3.7B | D90: 3700000000 | E90: San Francisco | F90: N | G90: 2572000 | H90: https://www.homes.com/property/34-bothin-rd-fairfax-ca-unit-a/trh18zhv4y4gc/ | I90: 2026 | M90: Estimated value on homes.com is $2,230,000 - $2,572,000
A91: 90 | B91: Jack Clark | C91: $3.7B | D91: 3700000000 | F91: N
A92: 91 | B92: Sam McCandlish | C92: $3.7B | D92: 3700000000 | E92: San Francisco | F92: N | G92: 4831145 | H92: https://www.homes.com/property/347-precita-ave-san-francisco-ca/48ds9edzhcj41/ | I92: 2026 | M92: Estimated value on homes.com is $2,317,000 - $4,831,145
A93: 92 | B93: Daniela Amodei | C93: $3.7B | D93: 3700000000 | E93: San Francisco | F93: N
A94: 93 | B94: Marco DeGeorge | C94: $3.6B | D94: 3600000000 | E94: Los Angeles | F94: N | G94: 12982483 | H94: https://www.homes.com/property/517-alta-ave-santa-monica-ca/vq4nqr9enjgpr/ | I94: 2026 | M94: Estimated value on homes.com is $4,142,000 - $12,982,483.
A95: 94 | B95: Kavitark Ram Shriram | C95: $3.6B | D95: 3600000000 | E95: Menlo Park | F95: N
A96: 95 | B96: Hemant Taneja | C96: $3.6B | D96: 3600000000 | E96: Palo Alto | F96: N | G96: 13784748 | H96: https://www.homes.com/property/13685-la-paloma-rd-los-altos-hills-ca/fmywnqbsb44wd/ | I96: 2026 | M96: Estimated value on homes.com is $9,271,000 - $13,784,748.
A97: 96 | B97: Richard Peery | C97: $3.5B | D97: 3500000000 | E97: Palo Alto | F97: N
A98: 97 | B98: Brian Acton | C98: $3.5B | D98: 3500000000 | E98: Palo Alto | F98: N | G98: 86000000 | H98: https://www.yahoo.com/entertainment/whatsapp-co-founder-brian-acton-174840726.html | I98: 2019 | M98: Acton's compound consists of 7 Palo Alto houses.
A99: 98 | B99: Travis Kalanick | C99: $3.5B | D99: 3500000000 | E99: Los Angeles | F99: N | G99: 43300000 | H99: https://therealdeal.com/la/2020/05/09/uber-buy-travis-kalanick-behind-43m-bel-air-purchase/ | I99: 2020 | N99: https://www.forbes.com/sites/chasewithorn/2026/01/15/los-angeles-billionaire-moves-to-nevada-after-california-threatens-to-tax-wealth/
A100: 99 | B100: Palmer Luckey | C100: $3.5B | D100: 3500000000 | E100: Newport Beach | F100: N | G100: 12500000 | H100: https://www.forbes.com/sites/iainmartin/2024/07/22/billionaire-palmer-luckey-sues-contractor-after-being-trapped-in-his-mansions-car-elevator/ | I100: 2024 | M100: Unclear if Luckey is moving, but he is a vocal critic of tax. | N100: https://www.foxbusiness.com/politics/tech-billionaires-threaten-flee-california-over-proposed-5-wealth-tax
...

Sheet Descriptive_Statistics
D1: Billionaires | E1: Aggregate Wealth | F1: Share of Total
D2: Top 20 | E2: =SUM(Raw_Data_Collection!$D$2:$D$21) -> 1446000000000 | F2: =E2 / SUM(Raw_Data_Collection!$D$2:$D$215) -> 0.67268329
D3: Top 10 | E3: =SUM(Raw_Data_Collection!$D$2:$D$11) -> 1271200000000 | F3: =E3 / SUM(Raw_Data_Collection!$D$2:$D$215) -> 0.59136584
D4: Top 5 | E4: =SUM(Raw_Data_Collection!$D$2:$D$6) -> 1126400000000 | F4: =E4 / SUM(Raw_Data_Collection!$D$2:$D$215) -> 0.52400447
D5: Descriptive Statistics (Billionaire Wealth)
D6: Mean | E6: =AVERAGE(Raw_Data_Collection!$D$2:$D$215) -> 10044859813
D7: Median | E7: =MEDIAN(Raw_Data_Collection!$D$2:$D$215) -> 3150000000
D8: Mode | E8: =MODE(Raw_Data_Collection!$D$2:$D$215) -> 1300000000
D9: Std. Deviation | E9: =Raw_Data_Collection!$D$2:$D$215 -> 26700000000
D10: Max | E10: =MAX(Raw_Data_Collection!$D$2:$D$215) -> 256200000000
D11: Min | E11: =MIN(Raw_Data_Collection!$D$2:$D$215) -> 1000000000
D12: Sum | E12: =SUM(Raw_Data_Collection!$D$2:$D$215) -> 2149600000000
D13: Count | E13: 214
D14: Moving? | E14: Moving Count | F14: Moving Net Worth | G14: Share of Total
D15: Yes | E15: =COUNTIF(Raw_Data_Collection!$F$2:$F$215, "Y") -> 9 | F15: =SUMIF(Raw_Data_Collection!$F$2:$F$215, "Y", Raw_Data_Collection!$D$2:$D$215) -> 806400000000 | G15: =F15 / SUM(Raw_Data_Collection!$D$2:$D$215) -> 0.37513956
D16: No | E16: =COUNTIF(Raw_Data_Collection!$F$2:$F$215, "N") -> 205 | F16: =SUMIF(Raw_Data_Collection!$F$2:$F$215, "N", Raw_Data_Collection!$D$2:$D$215) -> 1343200000000 | G16: =F16 / SUM(Raw_Data_Collection!$D$2:$D$215) -> 0.62486044
D17: Descriptive Statistics (House Price)
D18: Mean | E18: =AVERAGE(Raw_Data_Collection!$G$2:$G$215) -> 33388602
D19: Median | E19: =MEDIAN(Raw_Data_Collection!$G$2:$G$215) -> 15939028
D20: Mode | E20: =MODE(Raw_Data_Collection!$G$2:$G$215) -> 30000000
D21: Std. Deviation | E21: =STDEV(Raw_Data_Collection!$G$2:$G$215) -> 42566696
D22: Max | E22: =MAX(Raw_Data_Collection!$G$2:$G$215) -> 250000000
D23: Min | E23: =MIN(Raw_Data_Collection!$G$2:$G$215) -> 800000
D24: Sum | E24: =SUM(Raw_Data_Collection!$G$2:$G$215) -> 4407295432
D25: Count | E25: =COUNTIF(Raw_Data_Collection!$G$2:$G$215, ">0") -> 132
D26: Descriptive Statistics (Total Res. Real Estate)
D27: Mean | E27: =AVERAGE(Raw_Data_Collection!$J$2:$J$215) -> 64026431
D28: Median | E28: =MEDIAN(Raw_Data_Collection!$J$2:$J$215) -> 19963888
D29: Mode | E29: =MODE(Raw_Data_Collection!$J$2:$J$215) -> 17115689
D30: Std. Deviation | E30: =STDEV(Raw_Data_Collection!$J$2:$J$215) -> 98671832
D31: Max | E31: =MAX(Raw_Data_Collection!$J$2:$J$215) -> 600000000
D32: Min | E32: =MIN(Raw_Data_Collection!$J$2:$J$215) -> 3250000
D33: Sum | E33: =SUM(Raw_Data_Collection!$J$2:$J$215) -> 4737955880
D34: Count | E34: =COUNTIF(Raw_Data_Collection!$J$2:$J$215, ">0") -> 74

Sheet Calculations
O1: 5% One-Time Tax Scenario | R1: 1% One-Time Tax Scenario
A2: Ranking | B2: Name | C2: Net Worth | D2: Net Worth Expanded | E2: Residence | F2: Moving? (Y/N) | G2: House Price | H2: House Price Source | I2: House Price (Assessed) Year | J2: Total Residential Real Estate | K2: Total Residential Real Estate* | L2: Net Worth - TRRE | M2: Capital Gains Rate | N2: Wealth Tax Rate | O2: 5% Wealth Tax Revenues | P2: Cap Gain Initial Calc (5%) | Q2: 5% Capital Gains Revenues | R2: Interest Rate | S2: 1% Wealth Tax Revenues | T2: Cap Gain Initial Calc (1%) | U2: 1% Capital Gains Revenues | V2: TRRE Price (Assessed) Year(s) | W2: TRRE Source | X2: Notes | Y2: Moving Source
A3: 1 | B3: Larry Page | C3: $256.2B | D3: 256200000000 | E3: Palo Alto | F3: =VLOOKUP(B3,Raw_Data_Collection!$B$2:$F$215,5,FALSE) -> Y | G3: =VLOOKUP(B3,Raw_Data_Collection!$B$2:$J$215,6,FALSE) -> 101500000 | H3: https://elmundomiami.com/economy/larry-page-invests-173-4-million-in-the-miami-real-estate-market/ | I3: 2024 | J3: =VLOOKUP(B3,Raw_Data_Collection!$B$2:$J$215,9,FALSE) | K3: =VLOOKUP(B3,Real_Estate_Stats!$A$2:$G$215,7,FALSE) -> 101500000 | L3: =D3-K3 -> 256098500000 | M3: 0.37 | N3: 0.05 | O3: =L3*N3 -> 12804925000 | P3: =O3/(1-M3) -> 20325277778 | Q3: =P3*M3 -> 7520352778 | R3: 0.075 | S3: =L3*N3 + (L3*N3*R3*(4+3+2+1+0)/5) -> 14725663750 | T3: =S3/(1-M3) -> 23374069444 | U3: =T3*M3 -> 8648405694 | X3: Page's primary residence is now a Florida mansion. | Y3: https://www.businessinsider.com/larry-page-leave-california-wealth-billionaire-tax-koop-google-2026-1
A4: 2 | B4: Larry Ellison | C4: $246.1B | D4: 246100000000 | E4: Woodside | F4: =VLOOKUP(B4,Raw_Data_Collection!$B$2:$F$215,5,FALSE) -> Y | G4: =VLOOKUP(B4,Raw_Data_Collection!$B$2:$J$215,6,FALSE) -> 45000000 | H4: https://sfstandard.com/2026/01/05/larry-ellison-san-francisco-home-sale/ | I4: 2025 | J4: =VLOOKUP(B4,Raw_Data_Collection!$B$2:$J$215,9,FALSE) | K4: =VLOOKUP(B4,Real_Estate_Stats!$A$2:$G$215,7,FALSE) -> 45000000 | L4: =D4-K4 -> 246055000000 | M4: 0.37 | N4: 0.05 | O4: =L4*N4 -> 12302750000 | P4: =O4/(1-M4) -> 19528174603 | Q4: =P4*M4 -> 7225424603 | R4: 0.075 | S4: =L4*N4 + (L4*N4*R4*(4+3+2+1+0)/5) -> 14148162500 | T4: =S4/(1-M4) -> 22457400794 | U4: =T4*M4 -> 8309238294 | X4: Sold property in late 2025. | Y4: https://www.sfchronicle.com/california/article/larry-page-larry-ellison-california-wealth-tax-21281843.php
A5: 3 | B5: Sergey Brin | C5: $236.4B | D5: 236400000000 | E5: Los Altos | F5: =VLOOKUP(B5,Raw_Data_Collection!$B$2:$F$215,5,FALSE) -> Y | G5: =VLOOKUP(B5,Raw_Data_Collection!$B$2:$J$215,6,FALSE) -> 35000000 | I5: 2025 | J5: =VLOOKUP(B5,Raw_Data_Collection!$B$2:$J$215,9,FALSE) | K5: =VLOOKUP(B5,Real_Estate_Stats!$A$2:$G$215,7,FALSE) -> 35000000 | L5: =D5-K5 -> 236365000000 | M5: 0.37 | N5: 0.05 | O5: =L5*N5 -> 11818250000 | P5: =O5/(1-M5) -> 18759126984 | Q5: =P5*M5 -> 6940876984 | R5: 0.075 | S5: =L5*N5 + (L5*N5*R5*(4+3+2+1+0)/5) -> 13590987500 | T5: =S5/(1-M5) -> 21572996032 | U5: =T5*M5 -> 7982008532 | Y5: https://www.aol.com/news/google-cofounders-sergey-brin-larry-195211174.html
A6: 4 | B6: Mark Zuckerberg | C6: $225.1B | D6: 225100000000 | E6: Palo Alto | F6: =VLOOKUP(B6,Raw_Data_Collection!$B$2:$F$215,5,FALSE) -> N | G6: =VLOOKUP(B6,Raw_Data_Collection!$B$2:$J$215,6,FALSE) -> 112000000 | H6: https://www.realtor.com/news/celebrity-real-estate/mark-zuckerberg-palo-alto-home-fury-neighbors/ | I6: 2025 | J6: =VLOOKUP(B6,Raw_Data_Collection!$B$2:$J$215,9,FALSE) -> 300000000 | K6: =VLOOKUP(B6,Real_Estate_Stats!$A$2:$G$215,7,FALSE) -> 300000000 | L6: =D6-K6 -> 224800000000 | M6: 0.37 | N6: 0.05 | O6: =L6*N6 -> 11240000000 | P6: =O6/(1-M6) -> 17841269841 | Q6: =P6*M6 -> 6601269841 | R6: 0.075 | S6: =L6*N6 + (L6*N6*R6*(4+3+2+1+0)/5) -> 12926000000 | T6: =S6/(1-M6) -> 20517460317 | U6: =T6*M6 -> 7591460317 | V6: 2011-2025 | W6: https://robbreport.com/shelter/celebrity-homes/mark-zuckerberg-property-portfolio-1236712447/ | X6: Zuckerberg's compund consists of 11 different properties ranging from $5 million to $15 million.
A7: 5 | B7: Jensen Huang | C7: $162.6B | D7: 162600000000 | E7: Los Altos | F7: =VLOOKUP(B7,Raw_Data_Collection!$B$2:$F$215,5,FALSE) -> N | G7: =VLOOKUP(B7,Raw_Data_Collection!$B$2:$J$215,6,FALSE) -> 6900000 | H7: https://www.yahoo.com/lifestyle/articles/3-most-expensive-properties-nvidia-115457861.html | I7: 2025 | J7: =VLOOKUP(B7,Raw_Data_Collection!$B$2:$J$215,9,FALSE) -> 52400000 | K7: =VLOOKUP(B7,Real_Estate_Stats!$A$2:$G$215,7,FALSE) -> 52400000 | L7: =D7-K7 -> 162547600000 | M7: 0.37 | N7: 0.05 | O7: =L7*N7 -> 8127380000 | P7: =O7/(1-M7) -> 12900603175 | Q7: =P7*M7 -> 4773223175 | R7: 0.075 | S7: =L7*N7 + (L7*N7*R7*(4+3+2+1+0)/5) -> 9346487000 | T7: =S7/(1-M7) -> 14835693651 | U7: =T7*M7 -> 5489206651 | V7: 2004 | W7: https://www.foxbusiness.com/lifestyle/nvidias-ceo-extensive-rich-real-estate-portfolio | X7: Huang also has a $38 million San Francisco Mansion. | Y7: https://uk.finance.yahoo.com/news/nvidia-jensen-huang-perfectly-fine-170800688.html
A8: 6 | B8: Eric Schmidt | C8: $35.6B | D8: 35600000000 | E8: Los Angeles | F8: =VLOOKUP(B8,Raw_Data_Collection!$B$2:$F$215,5,FALSE) -> N | G8: =VLOOKUP(B8,Raw_Data_Collection!$B$2:$J$215,6,FALSE) -> 110000000 | I8: 2025 | J8: =VLOOKUP(B8,Raw_Data_Collection!$B$2:$J$215,9,FALSE) -> 600000000 | K8: =VLOOKUP(B8,Real_Estate_Stats!$A$2:$G$215,7,FALSE) -> 600000000 | L8: =D8-K8 -> 35000000000 | M8: 0.37 | N8: 0.05 | O8: =L8*N8 -> 1750000000 | P8: =O8/(1-M8) -> 2777777778 | Q8: =P8*M8 -> 1027777778 | R8: 0.075 | S8: =L8*N8 + (L8*N8*R8*(4+3+2+1+0)/5) -> 2012500000 | T8: =S8/(1-M8) -> 3194444444 | U8: =T8*M8 -> 1181944444 | V8: 2025 | W8: https://robbreport.com/shelter/celebrity-homes/lists/eric-schmidt-property-portfolio-1236832435/ | X8: Schmidt also bought a $30.8 million estate in Montecito in 2020.
A9: 7 | B9: Henry Samueli | C9: $32B | D9: 32000000000 | E9: Newport Beach | F9: =VLOOKUP(B9,Raw_Data_Collection!$B$2:$F$215,5,FALSE) -> N | G9: =VLOOKUP(B9,Raw_Data_Collection!$B$2:$J$215,6,FALSE) -> 20150000 | H9: https://www.urbansplatter.com/2024/06/henry-samueli-house-the-california-dwelling/ | I9: 2024 | J9: =VLOOKUP(B9,Raw_Data_Collection!$B$2:$J$215,9,FALSE) -> 20150000 | K9: =VLOOKUP(B9,Real_Estate_Stats!$A$2:$G$215,7,FALSE) -> 20150000 | L9: =D9-K9 -> 31979850000 | M9: 0.37 | N9: 0.05 | O9: =L9*N9 -> 1598992500 | P9: =O9/(1-M9) -> 2538083333 | Q9: =P9*M9 -> 9.3909083e+08 | R9: 0.075 | S9: =L9*N9 + (L9*N9*R9*(4+3+2+1+0)/5) -> 1838841375 | T9: =S9/(1-M9) -> 2918795833 | U9: =T9*M9 -> 1079954458 | V9: 2024 | W9: https://www.urbansplatter.com/2024/06/henry-samueli-house-the-california-dwelling/ | X9: Samueli only seems to have one residence.
A10: 8 | B10: Peter Thiel | C10: $26.7B | D10: 26700000000 | E10: Los Angeles | F10: =VLOOKUP(B10,Raw_Data_Collection!$B$2:$F$215,5,FALSE) -> Y | G10: =VLOOKUP(B10,Raw_Data_Collection!$B$2:$J$215,6,FALSE) -> 11500000 | H10: https://labusinessjournal.com/technology/billionaire-peter-thiel-moving-los-angeles/ | I10: 2018 | J10: =VLOOKUP(B10,Raw_Data_Collection!$B$2:$J$215,9,FALSE) -> 77200000 | K10: =VLOOKUP(B10,Real_Estate_Stats!$A$2:$G$215,7,FALSE) -> 77200000 | L10: =D10-K10 -> 26622800000 | M10: 0.37 | N10: 0.05 | O10: =L10*N10 -> 1331140000 | P10: =O10/(1-M10) -> 2112920635 | Q10: =P10*M10 -> 7.8178063e+08 | R10: 0.075 | S10: =L10*N10 + (L10*N10*R10*(4+3+2+1+0)/5) -> 1530811000 | T10: =S10/(1-M10) -> 2429858730 | U10: =T10*M10 -> 8.9904773e+08 | V10: 2012-2024 | W10: https://www.loveproperty.com/gallerylist/73268/billionaire-boltholes-to-survive-the-end-of-the-world; https://shopoahuproperties.com/paypal-co-founder-peter-thiel-buys-maui-home-for-27m/; https://press.farm/inside-peter-thiels-lifestyle/; https://www.aol.com/news/fords-former-ceo-just-sold-164442537.html; https://press.farm/inside-peter-thiels-lifestyle/ | Y10: https://www.forbes.com/sites/tylerroush/2025/12/27/possible-california-wealth-tax-causes-billionaire-freakout-page-thiel-threaten-to-leave/
A11: 9 | B11: Robert Pera | C11: $25.5B | D11: 25500000000 | E11: San Jose | F11: =VLOOKUP(B11,Raw_Data_Collection!$B$2:$F$215,5,FALSE) -> N | G11: =VLOOKUP(B11,Raw_Data_Collection!$B$2:$J$215,6,FALSE) -> 21550000 | H11: https://www.dailymail.co.uk/sport/nba/article-12947653/Memphis-Grizzlies-billionaire-owner-Robert-Pena-Star-Island-arena.html | I11: 2024 | J11: =VLOOKUP(B11,Raw_Data_Collection!$B$2:$J$215,9,FALSE) | K11: =VLOOKUP(B11,Real_Estate_Stats!$A$2:$G$215,7,FALSE) -> 21550000 | L11: =D11-K11 -> 25478450000 | M11: 0.37 | N11: 0.05 | O11: =L11*N11 -> 1273922500 | P11: =O11/(1-M11) -> 2022099206 | Q11: =P11*M11 -> 7.4817671e+08 | R11: 0.075 | S11: =L11*N11 + (L11*N11*R11*(4+3+2+1+0)/5) -> 1465010875 | T11: =S11/(1-M11) -> 2325414087 | U11: =T11*M11 -> 8.6040321e+08 | X11: Pera's primary residence is in San Jose, but no sources confirm its value. One of Pera's other residences is a $21.5 million NYC penthouse.
A12: 10 | B12: Adam Foroughi | C12: $25B | D12: 25000000000 | E12: Truckee | F12: =VLOOKUP(B12,Raw_Data_Collection!$B$2:$F$215,5,FALSE) -> N | G12: =VLOOKUP(B12,Raw_Data_Collection!$B$2:$J$215,6,FALSE) | J12: =VLOOKUP(B12,Raw_Data_Collection!$B$2:$J$215,9,FALSE) | K12: =VLOOKUP(B12,Real_Estate_Stats!$A$2:$G$215,7,FALSE) -> 1.5900893e+08 | L12: =D12-K12 -> 24840991071 | M12: 0.37 | N12: 0.05 | O12: =L12*N12 -> 1242049554 | P12: =O12/(1-M12) -> 1971507228 | Q12: =P12*M12 -> 7.2945767e+08 | R12: 0.075 | S12: =L12*N12 + (L12*N12*R12*(4+3+2+1+0)/5) -> 1428356987 | T12: =S12/(1-M12) -> 2267233312 | U12: =T12*M12 -> 8.3887633e+08
A13: 11 | B13: Henry Nicholas III | C13: $21.9B | D13: 21900000000 | E13: Newport Coast | F13: =VLOOKUP(B13,Raw_Data_Collection!$B$2:$F$215,5,FALSE) -> N | G13: =VLOOKUP(B13,Raw_Data_Collection!$B$2:$J$215,6,FALSE) -> 19777777 | H13: https://hauteliving.com/2010/01/haute-estate-19-8-million-newport-coast-mansion/18762/ | I13: 2010 | J13: =VLOOKUP(B13,Raw_Data_Collection!$B$2:$J$215,9,FALSE) -> 19777777 | K13: =VLOOKUP(B13,Real_Estate_Stats!$A$2:$G$215,7,FALSE) -> 19777777 | L13: =D13-K13 -> 21880222223 | M13: 0.37 | N13: 0.05 | O13: =L13*N13 -> 1094011111 | P13: =O13/(1-M13) -> 1736525573 | Q13: =P13*M13 -> 6.4251446e+08 | R13: 0.075 | S13: =L13*N13 + (L13*N13*R13*(4+3+2+1+0)/5) -> 1258112778 | T13: =S13/(1-M13) -> 1997004409 | U13: =T13*M13 -> 7.3889163e+08 | V13: 2010 | W13: https://hauteliving.com/2010/01/haute-estate-19-8-million-newport-coast-mansion/18762/
A14: 12 | B14: John Doerr | C14: $20B | D14: 20000000000 | E14: Woodside | F14: =VLOOKUP(B14,Raw_Data_Collection!$B$2:$F$215,5,FALSE) -> N | G14: =VLOOKUP(B14,Raw_Data_Collection!$B$2:$J$215,6,FALSE) | J14: =VLOOKUP(B14,Raw_Data_Collection!$B$2:$J$215,9,FALSE) | K14: =VLOOKUP(B14,Real_Estate_Stats!$A$2:$G$215,7,FALSE) -> 1.2720714e+08 | L14: =D14-K14 -> 19872792857 | M14: 0.37 | N14: 0.05 | O14: =L14*N14 -> 9.9363964e+08 | P14: =O14/(1-M14) -> 1577205782 | Q14: =P14*M14 -> 5.8356614e+08 | R14: 0.075 | S14: =L14*N14 + (L14*N14*R14*(4+3+2+1+0)/5) -> 1142685589 | T14: =S14/(1-M14) -> 1813786650 | U14: =T14*M14 -> 6.7110106e+08
A15: 13 | B15: Donald Bren | C15: $19.2B | D15: 19200000000 | E15: Newport Beach | F15: =VLOOKUP(B15,Raw_Data_Collection!$B$2:$F$215,5,FALSE) -> N | G15: =VLOOKUP(B15,Raw_Data_Collection!$B$2:$J$215,6,FALSE) | J15: =VLOOKUP(B15,Raw_Data_Collection!$B$2:$J$215,9,FALSE) | K15: =VLOOKUP(B15,Real_Estate_Stats!$A$2:$G$215,7,FALSE) -> 1.2211886e+08 | L15: =D15-K15 -> 19077881143 | M15: 0.37 | N15: 0.05 | O15: =L15*N15 -> 9.5389406e+08 | P15: =O15/(1-M15) -> 1514117551 | Q15: =P15*M15 -> 5.6022349e+08 | R15: 0.075 | S15: =L15*N15 + (L15*N15*R15*(4+3+2+1+0)/5) -> 1096978166 | T15: =S15/(1-M15) -> 1741235184 | U15: =T15*M15 -> 644257018
A16: 14 | B16: Eric Smidt | C16: $17.9B | D16: 17900000000 | E16: Beverly Hills | F16: =VLOOKUP(B16,Raw_Data_Collection!$B$2:$F$215,5,FALSE) -> N | G16: =VLOOKUP(B16,Raw_Data_Collection!$B$2:$J$215,6,FALSE) -> 54000000 | H16: https://labusinessjournal.com/special-editions/wealthiest-angelenos/wealthiest-2023/10-eric-smidt/ | I16: 2023 | J16: =VLOOKUP(B16,Raw_Data_Collection!$B$2:$J$215,9,FALSE) | K16: =VLOOKUP(B16,Real_Estate_Stats!$A$2:$G$215,7,FALSE) -> 54000000 | L16: =D16-K16 -> 17846000000 | M16: 0.37 | N16: 0.05 | O16: =L16*N16 -> 892300000 | P16: =O16/(1-M16) -> 1416349206 | Q16: =P16*M16 -> 5.2404921e+08 | R16: 0.075 | S16: =L16*N16 + (L16*N16*R16*(4+3+2+1+0)/5) -> 1026145000 | T16: =S16/(1-M16) -> 1628801587 | U16: =T16*M16 -> 6.0265659e+08
A17: 15 | B17: John Tu | C17: $17.5B | D17: 17500000000 | E17: Rolling Hills | F17: =VLOOKUP(B17,Raw_Data_Collection!$B$2:$F$215,5,FALSE) -> N | G17: =VLOOKUP(B17,Raw_Data_Collection!$B$2:$J$215,6,FALSE) -> 7250000 | H17: https://blockshopper.com/ca/los-angeles-county/rolling-hills/property/7567015025/6-east-crest-road | I17: 2011 | J17: =VLOOKUP(B17,Raw_Data_Collection!$B$2:$J$215,9,FALSE) | K17: =VLOOKUP(B17,Real_Estate_Stats!$A$2:$G$215,7,FALSE) -> 7250000 | L17: =D17-K17 -> 17492750000 | M17: 0.37 | N17: 0.05 | O17: =L17*N17 -> 874637500 | P17: =O17/(1-M17) -> 1388313492 | Q17: =P17*M17 -> 5.1367599e+08 | R17: 0.075 | S17: =L17*N17 + (L17*N17*R17*(4+3+2+1+0)/5) -> 1005833125 | T17: =S17/(1-M17) -> 1596560516 | U17: =T17*M17 -> 5.9072739e+08
A18: 16 | B18: David Sun | C18: $17.5B | D18: 17500000000 | E18: Irvine | F18: =VLOOKUP(B18,Raw_Data_Collection!$B$2:$F$215,5,FALSE) -> N | G18: =VLOOKUP(B18,Raw_Data_Collection!$B$2:$J$215,6,FALSE) | J18: =VLOOKUP(B18,Raw_Data_Collection!$B$2:$J$215,9,FALSE) | K18: =VLOOKUP(B18,Real_Estate_Stats!$A$2:$G$215,7,FALSE) -> 111306250 | L18: =D18-K18 -> 17388693750 | M18: 0.37 | N18: 0.05 | O18: =L18*N18 -> 8.6943469e+08 | P18: =O18/(1-M18) -> 1380055060 | Q18: =P18*M18 -> 510620372 | R18: 0.075 | S18: =L18*N18 + (L18*N18*R18*(4+3+2+1+0)/5) -> 9.9984989e+08 | T18: =S18/(1-M18) -> 1587063318 | U18: =T18*M18 -> 5.8721343e+08
A19: 17 | B19: Jan Koum | C19: $17.1B | D19: 17100000000 | E19: Atherton | F19: =VLOOKUP(B19,Raw_Data_Collection!$B$2:$F$215,5,FALSE) -> Y | G19: =VLOOKUP(B19,Raw_Data_Collection!$B$2:$J$215,6,FALSE) -> 187000000 | H19: https://www.celebritynetworth.com/articles/celebrity-homes/two-years-after-paying-100-million-for-a-malibu-mansion-whatsapp-founder-buys-the-house-next-door-for-87-million/ | I19: 2021 | J19: =VLOOKUP(B19,Raw_Data_Collection!$B$2:$J$215,9,FALSE) -> 400000000 | K19: =VLOOKUP(B19,Real_Estate_Stats!$A$2:$G$215,7,FALSE) -> 400000000 | L19: =D19-K19 -> 16700000000 | M19: 0.37 | N19: 0.05 | O19: =L19*N19 -> 835000000 | P19: =O19/(1-M19) -> 1325396825 | Q19: =P19*M19 -> 4.9039683e+08 | R19: 0.075 | S19: =L19*N19 + (L19*N19*R19*(4+3+2+1+0)/5) -> 960250000 | T19: =S19/(1-M19) -> 1524206349 | U19: =T19*M19 -> 5.6395635e+08 | V19: 2021 | W19: https://www.celebritynetworth.com/articles/billionaire-news/jan-koum-grew-up-on-food-stamps-and-now-owns-more-than-400-million-worth-of-california-real-estate/ | X19: Koum's $187 million compound consists of two houses. | Y19: https://nypost.com/2026/01/08/real-estate/tech-titans-leaving-california-for-florida-over-billionaire-tax/
A20: 18 | B20: George Roberts | C20: $15.9B | D20: 15900000000 | E20: Atherton | F20: =VLOOKUP(B20,Raw_Data_Collection!$B$2:$F$215,5,FALSE) -> N | G20: =VLOOKUP(B20,Raw_Data_Collection!$B$2:$J$215,6,FALSE) -> 29084160 | H20: https://blockshopper.com/ca/san-mateo-county/atherton/property/070032440/260-atherton-avenue | I20: 2020 | J20: =VLOOKUP(B20,Raw_Data_Collection!$B$2:$J$215,9,FALSE) | K20: =VLOOKUP(B20,Real_Estate_Stats!$A$2:$G$215,7,FALSE) -> 29084160 | L20: =D20-K20 -> 15870915840 | M20: 0.37 | N20: 0.05 | O20: =L20*N20 -> 793545792 | P20: =O20/(1-M20) -> 1259596495 | Q20: =P20*M20 -> 4.660507e+08 | R20: 0.075 | S20: =L20*N20 + (L20*N20*R20*(4+3+2+1+0)/5) -> 9.1257766e+08 | T20: =S20/(1-M20) -> 1448535970 | U20: =T20*M20 -> 5.3595831e+08
A21: 19 | B21: Laurene Powell Jobs | C21: $14B | D21: 14000000000 | E21: San Francisco | F21: =VLOOKUP(B21,Raw_Data_Collection!$B$2:$F$215,5,FALSE) -> N | G21: =VLOOKUP(B21,Raw_Data_Collection!$B$2:$J$215,6,FALSE) -> 70000000 | H21: https://fortune.com/2024/07/13/laurene-powell-jobs-buys-mansion-san-francisco-billionaires-row-70-million-record-high/ | I21: 2024 | J21: =VLOOKUP(B21,Raw_Data_Collection!$B$2:$J$215,9,FALSE) -> 242000000 | K21: =VLOOKUP(B21,Real_Estate_Stats!$A$2:$G$215,7,FALSE) -> 242000000 | L21: =D21-K21 -> 13758000000 | M21: 0.37 | N21: 0.05 | O21: =L21*N21 -> 687900000 | P21: =O21/(1-M21) -> 1091904762 | Q21: =P21*M21 -> 4.0400476e+08 | R21: 0.075 | S21: =L21*N21 + (L21*N21*R21*(4+3+2+1+0)/5) -> 791085000 | T21: =S21/(1-M21) -> 1255690476 | U21: =T21*M21 -> 4.6460548e+08 | V21: 2015-2024 | W21: https://fortune.com/2024/06/17/laurene-powell-jobs-94-million-malibu-mansion-apple-steve-jobs-widow/; https://www.architecturaldigest.com/story/laurene-powell-jobs-buys-record-breaking-san-francisco-home
A22: 20 | B22: Jack Dangermond | C22: $13.8B | D22: 13800000000 | E22: Redlands | F22: =VLOOKUP(B22,Raw_Data_Collection!$B$2:$F$215,5,FALSE) -> N | G22: =VLOOKUP(B22,Raw_Data_Collection!$B$2:$J$215,6,FALSE) | J22: =VLOOKUP(B22,Raw_Data_Collection!$B$2:$J$215,9,FALSE) | K22: =VLOOKUP(B22,Real_Estate_Stats!$A$2:$G$215,7,FALSE) -> 87772929 | L22: =D22-K22 -> 13712227071 | M22: 0.37 | N22: 0.05 | O22: =L22*N22 -> 6.8561135e+08 | P22: =O22/(1-M22) -> 1088271990 | Q22: =P22*M22 -> 4.0266064e+08 | R22: 0.075 | S22: =L22*N22 + (L22*N22*R22*(4+3+2+1+0)/5) -> 7.8845306e+08 | T22: =S22/(1-M22) -> 1251512788 | U22: =T22*M22 -> 4.6305973e+08
A23: 21 | B23: Antony Ressler | C23: $13.1B | D23: 13100000000 | E23: Los Angeles | F23: =VLOOKUP(B23,Raw_Data_Collection!$B$2:$F$215,5,FALSE) -> N | G23: =VLOOKUP(B23,Raw_Data_Collection!$B$2:$J$215,6,FALSE) -> 60000000 | H23: https://www.finance-monthly.com/antony-resslers-net-worth-2025-billionaire-financier-sports-owner-and-philanthropist/ | I23: 2025 | J23: =VLOOKUP(B23,Raw_Data_Collection!$B$2:$J$215,9,FALSE) -> 100000000 | K23: =VLOOKUP(B23,Real_Estate_Stats!$A$2:$G$215,7,FALSE) -> 100000000 | L23: =D23-K23 -> 13000000000 | M23: 0.37 | N23: 0.05 | O23: =L23*N23 -> 650000000 | P23: =O23/(1-M23) -> 1031746032 | Q23: =P23*M23 -> 3.8174603e+08 | R23: 0.075 | S23: =L23*N23 + (L23*N23*R23*(4+3+2+1+0)/5) -> 747500000 | T23: =S23/(1-M23) -> 1186507937 | U23: =T23*M23 -> 4.3900794e+08 | V23: 2025 | W23: https://www.finance-monthly.com/antony-resslers-net-worth-2025-billionaire-financier-sports-owner-and-philanthropist/ | X23: Ressler's various LA properties are estimated to be worth over $100,000,000.
A24: 22 | B24: Vinod Khosla | C24: $12.5B | D24: 12500000000 | E24: Portola Valley | F24: =VLOOKUP(B24,Raw_Data_Collection!$B$2:$F$215,5,FALSE) -> N | G24: =VLOOKUP(B24,Raw_Data_Collection!$B$2:$J$215,6,FALSE) -> 17100579 | J24: =VLOOKUP(B24,Raw_Data_Collection!$B$2:$J$215,9,FALSE) -> 17100579 | K24: =VLOOKUP(B24,Real_Estate_Stats!$A$2:$G$215,7,FALSE) -> 79504464 | L24: =D24-K24 -> 12420495536 | M24: 0.37 | N24: 0.05 | O24: =L24*N24 -> 6.2102478e+08 | P24: =O24/(1-M24) -> 9.8575361e+08 | Q24: =P24*M24 -> 3.6472884e+08 | R24: 0.075 | S24: =L24*N24 + (L24*N24*R24*(4+3+2+1+0)/5) -> 7.1417849e+08 | T24: =S24/(1-M24) -> 1133616656 | U24: =T24*M24 -> 4.1943816e+08
A25: 23 | B25: Riley Bechtel | C25: $11.6B | D25: 11600000000 | E25: Woodside | F25: =VLOOKUP(B25,Raw_Data_Collection!$B$2:$F$215,5,FALSE) -> N | G25: =VLOOKUP(B25,Raw_Data_Collection!$B$2:$J$215,6,FALSE) -> 63300000 | H25: https://www.yahoo.com/entertainment/billionaire-riley-bechtel-pays-record-201404351.html | I25: 2020 | J25: =VLOOKUP(B25,Raw_Data_Collection!$B$2:$J$215,9,FALSE) -> 86100000 | K25: =VLOOKUP(B25,Real_Estate_Stats!$A$2:$G$215,7,FALSE) -> 86100000 | L25: =D25-K25 -> 11513900000 | M25: 0.37 | N25: 0.05 | O25: =L25*N25 -> 575695000 | P25: =O25/(1-M25) -> 9.1380159e+08 | Q25: =P25*M25 -> 3.3810659e+08 | R25: 0.075 | S25: =L25*N25 + (L25*N25*R25*(4+3+2+1+0)/5) -> 662049250 | T25: =S25/(1-M25) -> 1050871825 | U25: =T25*M25 -> 3.8882258e+08 | V25: 2011-2020 | W25: https://www.yahoo.com/entertainment/billionaire-riley-bechtel-pays-record-201404351.html
A26: 24 | B26: Dustin Moskovitz | C26: $11.2B | D26: 11200000000 | E26: San Francisco | F26: =VLOOKUP(B26,Raw_Data_Collection!$B$2:$F$215,5,FALSE) -> N | G26: =VLOOKUP(B26,Raw_Data_Collection!$B$2:$J$215,6,FALSE) -> 800000 | H26: https://www.seattletimes.com/business/young-tech-millionaires-keeping-1-bedroom-lifestyle/ | I26: 2011 | J26: =VLOOKUP(B26,Raw_Data_Collection!$B$2:$J$215,9,FALSE) | K26: =VLOOKUP(B26,Real_Estate_Stats!$A$2:$G$215,7,FALSE) -> 800000 | L26: =D26-K26 -> 11199200000 | M26: 0.37 | N26: 0.05 | O26: =L26*N26 -> 559960000 | P26: =O26/(1-M26) -> 8.888254e+08 | Q26: =P26*M26 -> 3.288654e+08 | R26: 0.075 | S26: =L26*N26 + (L26*N26*R26*(4+3+2+1+0)/5) -> 643954000 | T26: =S26/(1-M26) -> 1022149206 | U26: =T26*M26 -> 3.7819521e+08 | X26: Moskovitz' primary residence is an $800,000 San Francisco condo.
A27: 25 | B27: Douglas Leone | C27: $10.7B | D27: 10700000000 | E27: Napa | F27: =VLOOKUP(B27,Raw_Data_Collection!$B$2:$F$215,5,FALSE) -> N | G27: =VLOOKUP(B27,Raw_Data_Collection!$B$2:$J$215,6,FALSE) -> 10000000 | H27: https://www.celebritynetworth.com/richest-businessmen/richest-billionaires/douglas-leone-net-worth/ | I27: 2026 | J27: =VLOOKUP(B27,Raw_Data_Collection!$B$2:$J$215,9,FALSE) -> 80000000 | K27: =VLOOKUP(B27,Real_Estate_Stats!$A$2:$G$215,7,FALSE) -> 80000000 | L27: =D27-K27 -> 10620000000 | M27: 0.37 | N27: 0.05 | O27: =L27*N27 -> 531000000 | P27: =O27/(1-M27) -> 8.4285714e+08 | Q27: =P27*M27 -> 3.1185714e+08 | R27: 0.075 | S27: =L27*N27 + (L27*N27*R27*(4+3+2+1+0)/5) -> 610650000 | T27: =S27/(1-M27) -> 9.6928571e+08 | U27: =T27*M27 -> 3.5863571e+08 | V27: 2000-2026 | W27: https://www.celebritynetworth.com/richest-businessmen/richest-billionaires/douglas-leone-net-worth/
A28: 26 | B28: Chris Larsen | C28: $10.2B | D28: 10200000000 | E28: San Francisco | F28: =VLOOKUP(B28,Raw_Data_Collection!$B$2:$F$215,5,FALSE) -> N | G28: =VLOOKUP(B28,Raw_Data_Collection!$B$2:$J$215,6,FALSE) -> 13500000 | H28: https://sfstandard.com/2025/09/09/chris-larsen-napa-home/ | I28: 2025 | J28: =VLOOKUP(B28,Raw_Data_Collection!$B$2:$J$215,9,FALSE) -> 13500000 | K28: =VLOOKUP(B28,Real_Estate_Stats!$A$2:$G$215,7,FALSE) -> 13500000 | L28: =D28-K28 -> 10186500000 | M28: 0.37 | N28: 0.05 | O28: =L28*N28 -> 509325000 | P28: =O28/(1-M28) -> 808452381 | Q28: =P28*M28 -> 299127381 | R28: 0.075 | S28: =L28*N28 + (L28*N28*R28*(4+3+2+1+0)/5) -> 585723750 | T28: =S28/(1-M28) -> 9.2972024e+08 | U28: =T28*M28 -> 3.4399649e+08 | V28: 2025 | W28: https://docs.google.com/spreadsheets/d/1-d_IAr8tITUy_s8QmIzH-FLYoODzaBxNMWShu9W7IFk/edit?gid=1121030019#gid=1121030019
A29: 27 | B29: Brian Armstrong | C29: $10.1B | D29: 10100000000 | E29: Los Angeles | F29: =VLOOKUP(B29,Raw_Data_Collection!$B$2:$F$215,5,FALSE) -> N | G29: =VLOOKUP(B29,Raw_Data_Collection!$B$2:$J$215,6,FALSE) -> 133000000 | H29: https://www.urbansplatter.com/2022/05/brian-armstrong-house-the-los-angeles-mansion/ | I29: 2022 | J29: =VLOOKUP(B29,Raw_Data_Collection!$B$2:$J$215,9,FALSE) -> 133000000 | K29: =VLOOKUP(B29,Real_Estate_Stats!$A$2:$G$215,7,FALSE) -> 133000000 | L29: =D29-K29 -> 9967000000 | M29: 0.37 | N29: 0.05 | O29: =L29*N29 -> 498350000 | P29: =O29/(1-M29) -> 791031746 | Q29: =P29*M29 -> 292681746 | R29: 0.075 | S29: =L29*N29 + (L29*N29*R29*(4+3+2+1+0)/5) -> 573102500 | T29: =S29/(1-M29) -> 9.0968651e+08 | U29: =T29*M29 -> 3.3658401e+08 | V29: 2022 | W29: https://www.urbansplatter.com/2022/05/brian-armstrong-house-the-los-angeles-mansion/
A30: 28 | B30: Marijke Mars | C30: $10B | D30: 10000000000 | E30: Los Angeles | F30: =VLOOKUP(B30,Raw_Data_Collection!$B$2:$F$215,5,FALSE) -> N | G30: =VLOOKUP(B30,Raw_Data_Collection!$B$2:$J$215,6,FALSE) | J30: =VLOOKUP(B30,Raw_Data_Collection!$B$2:$J$215,9,FALSE) | K30: =VLOOKUP(B30,Real_Estate_Stats!$A$2:$G$215,7,FALSE) -> 63603571 | L30: =D30-K30 -> 9936396429 | M30: 0.37 | N30: 0.05 | O30: =L30*N30 -> 4.9681982e+08 | P30: =O30/(1-M30) -> 7.8860289e+08 | Q30: =P30*M30 -> 2.9178307e+08 | R30: 0.075 | S30: =L30*N30 + (L30*N30*R30*(4+3+2+1+0)/5) -> 5.7134279e+08 | T30: =S30/(1-M30) -> 9.0689332e+08 | U30: =T30*M30 -> 3.3555053e+08
A31: 29 | B31: Tom Gores | C31: $10B | D31: 10000000000 | E31: Beverly Hills | F31: =VLOOKUP(B31,Raw_Data_Collection!$B$2:$F$215,5,FALSE) -> N | G31: =VLOOKUP(B31,Raw_Data_Collection!$B$2:$J$215,6,FALSE) -> 100000000 | H31: https://therealdeal.com/la/2016/10/24/platinum-equity-ceo-buys-holmby-hills-spec-home-for-100m/ | I31: 2016 | J31: =VLOOKUP(B31,Raw_Data_Collection!$B$2:$J$215,9,FALSE) -> 138000000 | K31: =VLOOKUP(B31,Real_Estate_Stats!$A$2:$G$215,7,FALSE) -> 138000000 | L31: =D31-K31 -> 9862000000 | M31: 0.37 | N31: 0.05 | O31: =L31*N31 -> 493100000 | P31: =O31/(1-M31) -> 7.8269841e+08 | Q31: =P31*M31 -> 2.8959841e+08 | R31: 0.075 | S31: =L31*N31 + (L31*N31*R31*(4+3+2+1+0)/5) -> 567065000 | T31: =S31/(1-M31) -> 9.0010317e+08 | U31: =T31*M31 -> 3.3303817e+08 | V31: 2016-2017 | W31: https://therealdeal.com/la/2016/10/24/platinum-equity-ceo-buys-holmby-hills-spec-home-for-100m/; https://therealdeal.com/la/2017/12/04/detroit-pistons-owner-tom-gores-pays-38m-for-his-former-beverly-park-home/
A32: 30 | B32: Andrew Karam | C32: $9.8B | D32: 9800000000 | F32: =VLOOKUP(B32,Raw_Data_Collection!$B$2:$F$215,5,FALSE) -> N | G32: =VLOOKUP(B32,Raw_Data_Collection!$B$2:$J$215,6,FALSE) | J32: =VLOOKUP(B32,Raw_Data_Collection!$B$2:$J$215,9,FALSE) | K32: =VLOOKUP(B32,Real_Estate_Stats!$A$2:$G$215,7,FALSE) -> 62331500 | L32: =D32-K32 -> 9737668500 | M32: 0.37 | N32: 0.05 | O32: =L32*N32 -> 486883425 | P32: =O32/(1-M32) -> 7.7283083e+08 | Q32: =P32*M32 -> 2.8594741e+08 | R32: 0.075 | S32: =L32*N32 + (L32*N32*R32*(4+3+2+1+0)/5) -> 5.5991594e+08 | T32: =S32/(1-M32) -> 8.8875546e+08 | U32: =T32*M32 -> 3.2883952e+08
A33: 31 | B33: Brian Chesky | C33: $9.6B | D33: 9600000000 | E33: San Francisco | F33: =VLOOKUP(B33,Raw_Data_Collection!$B$2:$F$215,5,FALSE) -> N | G33: =VLOOKUP(B33,Raw_Data_Collection!$B$2:$J$215,6,FALSE) | J33: =VLOOKUP(B33,Raw_Data_Collection!$B$2:$J$215,9,FALSE) | K33: =VLOOKUP(B33,Real_Estate_Stats!$A$2:$G$215,7,FALSE) -> 61059429 | L33: =D33-K33 -> 9538940571 | M33: 0.37 | N33: 0.05 | O33: =L33*N33 -> 4.7694703e+08 | P33: =O33/(1-M33) -> 7.5705878e+08 | Q33: =P33*M33 -> 2.8011175e+08 | R33: 0.075 | S33: =L33*N33 + (L33*N33*R33*(4+3+2+1+0)/5) -> 5.4848908e+08 | T33: =S33/(1-M33) -> 8.7061759e+08 | U33: =T33*M33 -> 322128509 | Y33: https://www.washingtonpost.com/technology/2026/01/19/california-wealth-tax-exodus/
A34: 32 | B34: Marc Benioff | C34: $9.3B | D34: 9300000000 | E34: San Francisco | F34: =VLOOKUP(B34,Raw_Data_Collection!$B$2:$F$215,5,FALSE) -> N | G34: =VLOOKUP(B34,Raw_Data_Collection!$B$2:$J$215,6,FALSE) -> 18000000 | H34: https://www.yahoo.com/entertainment/twitter-ceo-jack-dorsey-scoops-011751538.html | I34: 2009 | J34: =VLOOKUP(B34,Raw_Data_Collection!$B$2:$J$215,9,FALSE) | K34: =VLOOKUP(B34,Real_Estate_Stats!$A$2:$G$215,7,FALSE) -> 18000000 | L34: =D34-K34 -> 9282000000 | M34: 0.37 | N34: 0.05 | O34: =L34*N34 -> 464100000 | P34: =O34/(1-M34) -> 7.3666667e+08 | Q34: =P34*M34 -> 2.7256667e+08 | R34: 0.075 | S34: =L34*N34 + (L34*N34*R34*(4+3+2+1+0)/5) -> 533715000 | T34: =S34/(1-M34) -> 8.4716667e+08 | U34: =T34*M34 -> 3.1345167e+08
A35: 33 | B35: David Geffen | C35: $9.2B | D35: 9200000000 | E35: Beverly Hills | F35: =VLOOKUP(B35,Raw_Data_Collection!$B$2:$F$215,5,FALSE) -> N | G35: =VLOOKUP(B35,Raw_Data_Collection!$B$2:$J$215,6,FALSE) -> 68000000 | H35: https://finance.yahoo.com/news/david-geffen-completes-68-million-192458970.html | I35: 2020 | J35: =VLOOKUP(B35,Raw_Data_Collection!$B$2:$J$215,9,FALSE) -> 132000000 | K35: =VLOOKUP(B35,Real_Estate_Stats!$A$2:$G$215,7,FALSE) -> 132000000 | L35: =D35-K35 -> 9068000000 | M35: 0.37 | N35: 0.05 | O35: =L35*N35 -> 453400000 | P35: =O35/(1-M35) -> 7.1968254e+08 | Q35: =P35*M35 -> 2.6628254e+08 | R35: 0.075 | S35: =L35*N35 + (L35*N35*R35*(4+3+2+1+0)/5) -> 521410000 | T35: =S35/(1-M35) -> 8.2763492e+08 | U35: =T35*M35 -> 3.0622492e+08 | V35: 2010-2020 | W35: https://www.inman.com/2020/06/11/entertainment-mogul-david-geffen-buys-la-luxury-estate-for-68m/; https://www.forbes.com/sites/erincarlyle/2014/05/07/a-look-at-billionaire-david-geffens-1-1-billion-stash-of-dream-palaces/
A36: 34 | B36: Nathan Blecharczyk | C36: $9.1B | D36: 9100000000 | E36: San Francisco | F36: =VLOOKUP(B36,Raw_Data_Collection!$B$2:$F$215,5,FALSE) -> N | G36: =VLOOKUP(B36,Raw_Data_Collection!$B$2:$J$215,6,FALSE) | J36: =VLOOKUP(B36,Raw_Data_Collection!$B$2:$J$215,9,FALSE) | K36: =VLOOKUP(B36,Real_Estate_Stats!$A$2:$G$215,7,FALSE) -> 57879250 | L36: =D36-K36 -> 9042120750 | M36: 0.37 | N36: 0.05 | O36: =L36*N36 -> 4.5210604e+08 | P36: =O36/(1-M36) -> 717628631 | Q36: =P36*M36 -> 2.6552259e+08 | R36: 0.075 | S36: =L36*N36 + (L36*N36*R36*(4+3+2+1+0)/5) -> 5.1992194e+08 | T36: =S36/(1-M36) -> 8.2527293e+08 | U36: =T36*M36 -> 3.0535098e+08
A37: 35 | B37: Lynsi Snyder | C37: $8.6B | D37: 8600000000 | E37: Glendora | F37: =VLOOKUP(B37,Raw_Data_Collection!$B$2:$F$215,5,FALSE) -> Y | G37: =VLOOKUP(B37,Raw_Data_Collection!$B$2:$J$215,6,FALSE) | J37: =VLOOKUP(B37,Raw_Data_Collection!$B$2:$J$215,9,FALSE) | K37: =VLOOKUP(B37,Real_Estate_Stats!$A$2:$G$215,7,FALSE) -> 54699071 | L37: =D37-K37 -> 8545300929 | M37: 0.37 | N37: 0.05 | O37: =L37*N37 -> 4.2726505e+08 | P37: =O37/(1-M37) -> 6.7819849e+08 | Q37: =P37*M37 -> 250933440 | R37: 0.075 | S37: =L37*N37 + (L37*N37*R37*(4+3+2+1+0)/5) -> 4.913548e+08 | T37: =S37/(1-M37) -> 7.7992826e+08 | U37: =T37*M37 -> 288573456 | X37: Confirmed to be moving, not clear if due to CA Wealth Tax | Y37: https://apnews.com/article/innout-ceo-moving-af175b4926847325970b5bcba52276fe
A38: 36 | B38: Steven Rales | C38: $8.6B | D38: 8600000000 | E38: Santa Barbara | F38: =VLOOKUP(B38,Raw_Data_Collection!$B$2:$F$215,5,FALSE) -> N | G38: =VLOOKUP(B38,Raw_Data_Collection!$B$2:$J$215,6,FALSE) | J38: =VLOOKUP(B38,Raw_Data_Collection!$B$2:$J$215,9,FALSE) | K38: =VLOOKUP(B38,Real_Estate_Stats!$A$2:$G$215,7,FALSE) -> 54699071 | L38: =D38-K38 -> 8545300929 | M38: 0.37 | N38: 0.05 | O38: =L38*N38 -> 4.2726505e+08 | P38: =O38/(1-M38) -> 6.7819849e+08 | Q38: =P38*M38 -> 250933440 | R38: 0.075 | S38: =L38*N38 + (L38*N38*R38*(4+3+2+1+0)/5) -> 4.913548e+08 | T38: =S38/(1-M38) -> 7.7992826e+08 | U38: =T38*M38 -> 288573456
A39: 37 | B39: Don Hankey | C39: $8.1B | D39: 8100000000 | E39: Malibu | F39: =VLOOKUP(B39,Raw_Data_Collection!$B$2:$F$215,5,FALSE) -> Y | G39: =VLOOKUP(B39,Raw_Data_Collection!$B$2:$J$215,6,FALSE) -> 10659988 | H39: https://www.homes.com/property/27450-pacific-coast-hwy-malibu-ca/gt8keb94hyyzn/ | I39: 2026 | J39: =VLOOKUP(B39,Raw_Data_Collection!$B$2:$J$215,9,FALSE) -> 51300000 | K39: =VLOOKUP(B39,Real_Estate_Stats!$A$2:$G$215,7,FALSE) -> 51300000 | L39: =D39-K39 -> 8048700000 | M39: 0.37 | N39: 0.05 | O39: =L39*N39 -> 402435000 | P39: =O39/(1-M39) -> 6.3878571e+08 | Q39: =P39*M39 -> 2.3635071e+08 | R39: 0.075 | S39: =L39*N39 + (L39*N39*R39*(4+3+2+1+0)/5) -> 462800250 | T39: =S39/(1-M39) -> 7.3460357e+08 | U39: =T39*M39 -> 2.7180332e+08 | V39: 2021-2026 | W39: https://www.reviewjournal.com/business/housing/l-a-billionaire-buys-summerlin-condo-for-record-high-21m-3609182/; https://therealdeal.com/miami/2021/10/13/billionaire-don-hankey-buys-oceanfront-highland-beach-mansion-for-30m/ | X39: Estimated value on homes.com is $6,882,000 - $19,119,746 | Y39: https://www.forbes.com/sites/chasewithorn/2026/01/15/los-angeles-billionaire-moves-to-nevada-after-california-threatens-to-tax-wealth/
A40: 38 | B40: Tench Coxe | C40: $7.8B | D40: 7800000000 | E40: Palo Alto | F40: =VLOOKUP(B40,Raw_Data_Collection!$B$2:$F$215,5,FALSE) -> N | G40: =VLOOKUP(B40,Raw_Data_Collection!$B$2:$J$215,6,FALSE) -> 8683775 | H40: https://www.homes.com/property/1401-emerson-st-palo-alto-ca/znpl6z10qsgvy/ | I40: 2026 | J40: =VLOOKUP(B40,Raw_Data_Collection!$B$2:$J$215,9,FALSE) -> 8683775 | K40: =VLOOKUP(B40,Real_Estate_Stats!$A$2:$G$215,7,FALSE) -> 8683775 | L40: =D40-K40 -> 7791316225 | M40: 0.37 | N40: 0.05 | O40: =L40*N40 -> 3.8956581e+08 | P40: =O40/(1-M40) -> 6.1835843e+08 | Q40: =P40*M40 -> 2.2879262e+08 | R40: 0.075 | S40: =L40*N40 + (L40*N40*R40*(4+3+2+1+0)/5) -> 4.4800068e+08 | T40: =S40/(1-M40) -> 7.111122e+08 | U40: =T40*M40 -> 2.6311151e+08 | V40: 2026 | W40: https://www.homes.com/property/1401-emerson-st-palo-alto-ca/znpl6z10qsgvy/ | X40: Estimated value on homes.com is $5,573,000 $8,683,775
A41: 39 | B41: Michael Moritz | C41: $7.7B | D41: 7700000000 | E41: San Francisco | F41: =VLOOKUP(B41,Raw_Data_Collection!$B$2:$F$215,5,FALSE) -> N | G41: =VLOOKUP(B41,Raw_Data_Collection!$B$2:$J$215,6,FALSE) -> 10600000 | H41: https://blockshopper.com/ca/san-francisco-county/san-francisco/property/0953006/2626-vallejo-street | I41: 2002 | J41: =VLOOKUP(B41,Raw_Data_Collection!$B$2:$J$215,9,FALSE) -> 10600000 | K41: =VLOOKUP(B41,Real_Estate_Stats!$A$2:$G$215,7,FALSE) -> 10600000 | L41: =D41-K41 -> 7689400000 | M41: 0.37 | N41: 0.05 | O41: =L41*N41 -> 384470000 | P41: =O41/(1-M41) -> 6.1026984e+08 | Q41: =P41*M41 -> 2.2579984e+08 | R41: 0.075 | S41: =L41*N41 + (L41*N41*R41*(4+3+2+1+0)/5) -> 442140500 | T41: =S41/(1-M41) -> 7.0181032e+08 | U41: =T41*M41 -> 2.5966982e+08 | V41: 2002 | W41: https://blockshopper.com/ca/san-francisco-county/san-francisco/property/0953006/2626-vallejo-street | Y41: https://www.bloomberg.com/news/articles/2026-01-08/california-wealth-tax-threat-pushes-billionaires-to-texas-florida
A42: 40 | B42: Edward Roski Jr | C42: $7.6B | D42: 7600000000 | E42: Los Angeles | F42: =VLOOKUP(B42,Raw_Data_Collection!$B$2:$F$215,5,FALSE) -> N | G42: =VLOOKUP(B42,Raw_Data_Collection!$B$2:$J$215,6,FALSE) -> 8107000 | H42: https://www.homes.com/property/10051-valley-spring-ln-toluca-lake-ca/kd8ylmg68cld1/ | I42: 2026 | J42: =VLOOKUP(B42,Raw_Data_Collection!$B$2:$J$215,9,FALSE) -> 8107000 | K42: =VLOOKUP(B42,Real_Estate_Stats!$A$2:$G$215,7,FALSE) -> 8107000 | L42: =D42-K42 -> 7591893000 | M42: 0.37 | N42: 0.05 | O42: =L42*N42 -> 379594650 | P42: =O42/(1-M42) -> 6.0253119e+08 | Q42: =P42*M42 -> 2.2293654e+08 | R42: 0.075 | S42: =L42*N42 + (L42*N42*R42*(4+3+2+1+0)/5) -> 4.3653385e+08 | T42: =S42/(1-M42) -> 692910869 | U42: =T42*M42 -> 2.5637702e+08 | V42: 2026 | W42: https://www.homes.com/property/10051-valley-spring-ln-toluca-lake-ca/kd8ylmg68cld1/ | X42: Estimated value on homes.com is $6,522,000 - $8,107,000.
A43: 41 | B43: Michael Milken | C43: $7.4B | D43: 7400000000 | E43: Los Angeles | F43: =VLOOKUP(B43,Raw_Data_Collection!$B$2:$F$215,5,FALSE) -> N | G43: =VLOOKUP(B43,Raw_Data_Collection!$B$2:$J$215,6,FALSE) -> 102000000 | H43: https://www.forbes.com/sites/trulia/2014/04/04/las-super-mansion-fleur-de-lys-sells-for-a-record-breaking-102-million/ | I43: 2014 | J43: =VLOOKUP(B43,Raw_Data_Collection!$B$2:$J$215,9,FALSE) -> 179750000 | K43: =VLOOKUP(B43,Real_Estate_Stats!$A$2:$G$215,7,FALSE) -> 179750000 | L43: =D43-K43 -> 7220250000 | M43: 0.37 | N43: 0.05 | O43: =L43*N43 -> 361012500 | P43: =O43/(1-M43) -> 5.7303571e+08 | Q43: =P43*M43 -> 2.1202321e+08 | R43: 0.075 | S43: =L43*N43 + (L43*N43*R43*(4+3+2+1+0)/5) -> 415164375 | T43: =S43/(1-M43) -> 6.5899107e+08 | U43: =T43*M43 -> 2.438267e+08 | V43: 2011-2026 | W43: https://palisadesnews.com/michael-milkens-pacific-palisades-estate-goes-on-sale-for-64-million/; https://virtualglobetrotting.com/map/michael-milkens-house-4/view/google/; https://www.forbes.com/sites/trulia/2014/04/04/las-super-mansion-fleur-de-lys-sells-for-a-record-breaking-102-million/
A44: 42 | B44: Steven Spielberg | C44: $7B | D44: 7000000000 | E44: Pacific Palisades | F44: =VLOOKUP(B44,Raw_Data_Collection!$B$2:$F$215,5,FALSE) -> N | G44: =VLOOKUP(B44,Raw_Data_Collection!$B$2:$J$215,6,FALSE) -> 250000000 | H44: https://www.finance-monthly.com/steven-spielbergs-net-worth-9-5-billion-in-2025/ | I44: 2024 | J44: =VLOOKUP(B44,Raw_Data_Collection!$B$2:$J$215,9,FALSE) -> 250000000 | K44: =VLOOKUP(B44,Real_Estate_Stats!$A$2:$G$215,7,FALSE) -> 250000000 | L44: =D44-K44 -> 6750000000 | M44: 0.37 | N44: 0.05 | O44: =L44*N44 -> 337500000 | P44: =O44/(1-M44) -> 5.3571429e+08 | Q44: =P44*M44 -> 1.9821429e+08 | R44: 0.075 | S44: =L44*N44 + (L44*N44*R44*(4+3+2+1+0)/5) -> 388125000 | T44: =S44/(1-M44) -> 6.1607143e+08 | U44: =T44*M44 -> 2.2794643e+08 | V44: 2024 | W44: https://www.finance-monthly.com/steven-spielbergs-net-worth-9-5-billion-in-2025/ | X44: Spielberg's property is estimated to be between $100 million and $250 million.
A45: 43 | B45: Edythe Broad | C45: $6.9B | D45: 6900000000 | E45: Los Angeles | F45: =VLOOKUP(B45,Raw_Data_Collection!$B$2:$F$215,5,FALSE) -> N | G45: =VLOOKUP(B45,Raw_Data_Collection!$B$2:$J$215,6,FALSE) -> 13283376 | J45: =VLOOKUP(B45,Raw_Data_Collection!$B$2:$J$215,9,FALSE) -> 13283376 | K45: =VLOOKUP(B45,Real_Estate_Stats!$A$2:$G$215,7,FALSE) -> 43886464 | L45: =D45-K45 -> 6856113536 | M45: 0.37 | N45: 0.05 | O45: =L45*N45 -> 3.4280568e+08 | P45: =O45/(1-M45) -> 5.4413599e+08 | Q45: =P45*M45 -> 2.0133032e+08 | R45: 0.075 | S45: =L45*N45 + (L45*N45*R45*(4+3+2+1+0)/5) -> 3.9422653e+08 | T45: =S45/(1-M45) -> 6.2575639e+08 | U45: =T45*M45 -> 2.3152987e+08
A46: 44 | B46: Scott Cook | C46: $6.9B | D46: 6900000000 | E46: Woodside | F46: =VLOOKUP(B46,Raw_Data_Collection!$B$2:$F$215,5,FALSE) -> N | G46: =VLOOKUP(B46,Raw_Data_Collection!$B$2:$J$215,6,FALSE) -> 15830193 | H46: https://www.homes.com/property/376-mountain-home-rd-woodside-ca/p6sh3hp6plvk6/ | I46: 2026 | J46: =VLOOKUP(B46,Raw_Data_Collection!$B$2:$J$215,9,FALSE) -> 15830193 | K46: =VLOOKUP(B46,Real_Estate_Stats!$A$2:$G$215,7,FALSE) -> 15830193 | L46: =D46-K46 -> 6884169807 | M46: 0.37 | N46: 0.05 | O46: =L46*N46 -> 3.4420849e+08 | P46: =O46/(1-M46) -> 5.4636268e+08 | Q46: =P46*M46 -> 2.0215419e+08 | R46: 0.075 | S46: =L46*N46 + (L46*N46*R46*(4+3+2+1+0)/5) -> 3.9583976e+08 | T46: =S46/(1-M46) -> 6.2831709e+08 | U46: =T46*M46 -> 2.3247732e+08 | V46: 2026 | W46: https://www.homes.com/property/376-mountain-home-rd-woodside-ca/p6sh3hp6plvk6/ | X46: Estimated value on homes.com is 6,309,000-15,830,193
A47: 45 | B47: Baiju Bhatt | C47: $6.7B | D47: 6700000000 | E47: Palo Alto | F47: =VLOOKUP(B47,Raw_Data_Collection!$B$2:$F$215,5,FALSE) -> N | G47: =VLOOKUP(B47,Raw_Data_Collection!$B$2:$J$215,6,FALSE) | J47: =VLOOKUP(B47,Raw_Data_Collection!$B$2:$J$215,9,FALSE) | K47: =VLOOKUP(B47,Real_Estate_Stats!$A$2:$G$215,7,FALSE) -> 42614393 | L47: =D47-K47 -> 6657385607 | M47: 0.37 | N47: 0.05 | O47: =L47*N47 -> 3.3286928e+08 | P47: =O47/(1-M47) -> 5.2836394e+08 | Q47: =P47*M47 -> 1.9549466e+08 | R47: 0.075 | S47: =L47*N47 + (L47*N47*R47*(4+3+2+1+0)/5) -> 3.8279967e+08 | T47: =S47/(1-M47) -> 6.0761853e+08 | U47: =T47*M47 -> 2.2481886e+08
A48: 46 | B48: Vlad Tenev | C48: $6.4B | D48: 6400000000 | E48: Palo Alto | F48: =VLOOKUP(B48,Raw_Data_Collection!$B$2:$F$215,5,FALSE) -> N | G48: =VLOOKUP(B48,Raw_Data_Collection!$B$2:$J$215,6,FALSE) | J48: =VLOOKUP(B48,Raw_Data_Collection!$B$2:$J$215,9,FALSE) | K48: =VLOOKUP(B48,Real_Estate_Stats!$A$2:$G$215,7,FALSE) -> 40706286 | L48: =D48-K48 -> 6359293714 | M48: 0.37 | N48: 0.05 | O48: =L48*N48 -> 3.1796469e+08 | P48: =O48/(1-M48) -> 5.0470585e+08 | Q48: =P48*M48 -> 1.8674116e+08 | R48: 0.075 | S48: =L48*N48 + (L48*N48*R48*(4+3+2+1+0)/5) -> 3.6565939e+08 | T48: =S48/(1-M48) -> 5.8041173e+08 | U48: =T48*M48 -> 2.1475234e+08
A49: 47 | B49: John A. Sobrato | C49: $6.4B | D49: 6400000000 | E49: Atherton | F49: =VLOOKUP(B49,Raw_Data_Collection!$B$2:$F$215,5,FALSE) -> N | G49: =VLOOKUP(B49,Raw_Data_Collection!$B$2:$J$215,6,FALSE) | J49: =VLOOKUP(B49,Raw_Data_Collection!$B$2:$J$215,9,FALSE) | K49: =VLOOKUP(B49,Real_Estate_Stats!$A$2:$G$215,7,FALSE) -> 40706286 | L49: =D49-K49 -> 6359293714 | M49: 0.37 | N49: 0.05 | O49: =L49*N49 -> 3.1796469e+08 | P49: =O49/(1-M49) -> 5.0470585e+08 | Q49: =P49*M49 -> 1.8674116e+08 | R49: 0.075 | S49: =L49*N49 + (L49*N49*R49*(4+3+2+1+0)/5) -> 3.6565939e+08 | T49: =S49/(1-M49) -> 5.8041173e+08 | U49: =T49*M49 -> 2.1475234e+08 | Y49: https://www.bloomberg.com/news/articles/2026-01-08/california-wealth-tax-threat-pushes-billionaires-to-texas-florida
A50: 48 | B50: Stephen Cohen | C50: $6.3B | D50: 6300000000 | E50: Palo Alto | F50: =VLOOKUP(B50,Raw_Data_Collection!$B$2:$F$215,5,FALSE) -> N | G50: =VLOOKUP(B50,Raw_Data_Collection!$B$2:$J$215,6,FALSE) -> 1031715 | H50: https://www.homes.com/property/20-willow-rd-menlo-park-ca-unit-8/hbwec8jc2rsrg/ | I50: 2026 | J50: =VLOOKUP(B50,Raw_Data_Collection!$B$2:$J$215,9,FALSE) | K50: =VLOOKUP(B50,Real_Estate_Stats!$A$2:$G$215,7,FALSE) -> 1031715 | L50: =D50-K50 -> 6298968285 | M50: 0.37 | N50: 0.05 | O50: =L50*N50 -> 3.1494841e+08 | P50: =O50/(1-M50) -> 4.9991812e+08 | Q50: =P50*M50 -> 1.849697e+08 | R50: 0.075 | S50: =L50*N50 + (L50*N50*R50*(4+3+2+1+0)/5) -> 3.6219068e+08 | T50: =S50/(1-M50) -> 5.7490584e+08 | U50: =T50*M50 -> 2.1271516e+08 | X50: Estimated value on homes.com is $916,859 - $1,131,000
A51: 49 | B51: Rick Caruso | C51: $5.9B | D51: 5900000000 | E51: Los Angeles | F51: =VLOOKUP(B51,Raw_Data_Collection!$B$2:$F$215,5,FALSE) -> N | G51: =VLOOKUP(B51,Raw_Data_Collection!$B$2:$J$215,6,FALSE) -> 80000000 | H51: https://xabisinc.com/blog/rick-carusos-net-worth-the-secrets-behind-his-real-estate-success/ | I51: 2025 | J51: =VLOOKUP(B51,Raw_Data_Collection!$B$2:$J$215,9,FALSE) -> 86500000 | K51: =VLOOKUP(B51,Real_Estate_Stats!$A$2:$G$215,7,FALSE) -> 86500000 | L51: =D51-K51 -> 5813500000 | M51: 0.37 | N51: 0.05 | O51: =L51*N51 -> 290675000 | P51: =O51/(1-M51) -> 4.6138889e+08 | Q51: =P51*M51 -> 1.7071389e+08 | R51: 0.075 | S51: =L51*N51 + (L51*N51*R51*(4+3+2+1+0)/5) -> 334276250 | T51: =S51/(1-M51) -> 5.3059722e+08 | U51: =T51*M51 -> 1.9632097e+08 | V51: 2015-2025 | W51: https://www.celebritynetworth.com/richest-businessmen/richest-billionaires/rick-caruso-net-worth/ | X51: Caruso's primary estate is estimated to be worth $60-80 million.
A52: 50 | B52: Ken Xie | C52: $5.7B | D52: 5700000000 | E52: Los Altos Hills | F52: =VLOOKUP(B52,Raw_Data_Collection!$B$2:$F$215,5,FALSE) -> N | G52: =VLOOKUP(B52,Raw_Data_Collection!$B$2:$J$215,6,FALSE) -> 18104324 | J52: =VLOOKUP(B52,Raw_Data_Collection!$B$2:$J$215,9,FALSE) -> 14340561 | K52: =VLOOKUP(B52,Real_Estate_Stats!$A$2:$G$215,7,FALSE) -> 14340561 | L52: =D52-K52 -> 5685659439 | M52: 0.37 | N52: 0.05 | O52: =L52*N52 -> 284282972 | P52: =O52/(1-M52) -> 4.5124281e+08 | Q52: =P52*M52 -> 1.6695984e+08 | R52: 0.075 | S52: =L52*N52 + (L52*N52*R52*(4+3+2+1+0)/5) -> 3.2692542e+08 | T52: =S52/(1-M52) -> 5.1892923e+08 | U52: =T52*M52 -> 1.9200382e+08 | V52: 2004-2024 | W52: https://www.celebritynetworth.com/richest-businessmen/richest-billionaires/ken-xie-net-worth/; https://blockshopper.com/ca/san-mateo-county/atherton/property/070120060/9-tuscaloosa-avenue
A53: 51 | B53: Jayshree Ullal | C53: $5.6B | D53: 5600000000 | E53: Saratoga | F53: =VLOOKUP(B53,Raw_Data_Collection!$B$2:$F$215,5,FALSE) -> N | G53: =VLOOKUP(B53,Raw_Data_Collection!$B$2:$J$215,6,FALSE) -> 877000 | H53: https://www.homes.com/property/190-n-lafayette-st-tracy-ca/x6xzt2lw9j9cx/ | I53: 2026 | J53: =VLOOKUP(B53,Raw_Data_Collection!$B$2:$J$215,9,FALSE) -> 7862000 | K53: =VLOOKUP(B53,Real_Estate_Stats!$A$2:$G$215,7,FALSE) -> 7862000 | L53: =D53-K53 -> 5592138000 | M53: 0.37 | N53: 0.05 | O53: =L53*N53 -> 279606900 | P53: =O53/(1-M53) -> 4.4382048e+08 | Q53: =P53*M53 -> 1.6421358e+08 | R53: 0.075 | S53: =L53*N53 + (L53*N53*R53*(4+3+2+1+0)/5) -> 321547935 | T53: =S53/(1-M53) -> 5.1039355e+08 | U53: =T53*M53 -> 1.8884561e+08 | V53: 2026 | W53: https://www.homes.com/property/19384-chablis-ct-saratoga-ca/e3n5y70n6ed3h/; https://www.homes.com/property/190-n-lafayette-st-tracy-ca/x6xzt2lw9j9cx/ | X53: Estimated values on homes.com is $803,000 - $877,000 and $6,190,389 - $6,985,000.
A54: 52 | B54: Archie Aldis Emmerson | C54: $5.6B | D54: 5600000000 | E54: Redding | F54: =VLOOKUP(B54,Raw_Data_Collection!$B$2:$F$215,5,FALSE) -> N | G54: =VLOOKUP(B54,Raw_Data_Collection!$B$2:$J$215,6,FALSE) -> 4101800 | J54: =VLOOKUP(B54,Raw_Data_Collection!$B$2:$J$215,9,FALSE) -> 4101800 | K54: =VLOOKUP(B54,Real_Estate_Stats!$A$2:$G$215,7,FALSE) -> 35618000 | L54: =D54-K54 -> 5564382000 | M54: 0.37 | N54: 0.05 | O54: =L54*N54 -> 278219100 | P54: =O54/(1-M54) -> 441617619 | Q54: =P54*M54 -> 163398519 | R54: 0.075 | S54: =L54*N54 + (L54*N54*R54*(4+3+2+1+0)/5) -> 319951965 | T54: =S54/(1-M54) -> 5.0786026e+08 | U54: =T54*M54 -> 1.879083e+08
A55: 53 | B55: Romesh T. Wadhwani | C55: $5.5B | D55: 5500000000 | E55: Palo Alto | F55: =VLOOKUP(B55,Raw_Data_Collection!$B$2:$F$215,5,FALSE) -> N | G55: =VLOOKUP(B55,Raw_Data_Collection!$B$2:$J$215,6,FALSE) -> 13169940 | J55: =VLOOKUP(B55,Raw_Data_Collection!$B$2:$J$215,9,FALSE) -> 13169940 | K55: =VLOOKUP(B55,Real_Estate_Stats!$A$2:$G$215,7,FALSE) -> 34981964 | L55: =D55-K55 -> 5465018036 | M55: 0.37 | N55: 0.05 | O55: =L55*N55 -> 2.732509e+08 | P55: =O55/(1-M55) -> 4.3373159e+08 | Q55: =P55*M55 -> 1.6048069e+08 | R55: 0.075 | S55: =L55*N55 + (L55*N55*R55*(4+3+2+1+0)/5) -> 3.1423854e+08 | T55: =S55/(1-M55) -> 4.9879133e+08 | U55: =T55*M55 -> 1.8455279e+08
A56: 54 | B56: Neal Blue | C56: $5.4B | D56: 5400000000 | E56: San Diego | F56: =VLOOKUP(B56,Raw_Data_Collection!$B$2:$F$215,5,FALSE) -> N | G56: =VLOOKUP(B56,Raw_Data_Collection!$B$2:$J$215,6,FALSE) | J56: =VLOOKUP(B56,Raw_Data_Collection!$B$2:$J$215,9,FALSE) | K56: =VLOOKUP(B56,Real_Estate_Stats!$A$2:$G$215,7,FALSE) -> 34345929 | L56: =D56-K56 -> 5365654071 | M56: 0.37 | N56: 0.05 | O56: =L56*N56 -> 2.682827e+08 | P56: =O56/(1-M56) -> 4.2584556e+08 | Q56: =P56*M56 -> 1.5756286e+08 | R56: 0.075 | S56: =L56*N56 + (L56*N56*R56*(4+3+2+1+0)/5) -> 3.0852511e+08 | T56: =S56/(1-M56) -> 4.897224e+08 | U56: =T56*M56 -> 1.8119729e+08
A57: 55 | B57: Gordon Getty | C57: $5.4B | D57: 5400000000 | E57: San Francisco | F57: =VLOOKUP(B57,Raw_Data_Collection!$B$2:$F$215,5,FALSE) -> N | G57: =VLOOKUP(B57,Raw_Data_Collection!$B$2:$J$215,6,FALSE) -> 29608760 | H57: https://blockshopper.com/ca/san-francisco-county/san-francisco/property/0958030/2870-broadway-street; https://www.redfin.com/CA/San-Francisco/2870-Broadway-St-94115/home/1811887#property-details | I57: 2026 | J57: =VLOOKUP(B57,Raw_Data_Collection!$B$2:$J$215,9,FALSE) -> 29608760 | K57: =VLOOKUP(B57,Real_Estate_Stats!$A$2:$G$215,7,FALSE) -> 29608760 | L57: =D57-K57 -> 5370391240 | M57: 0.37 | N57: 0.05 | O57: =L57*N57 -> 268519562 | P57: =O57/(1-M57) -> 426221527 | Q57: =P57*M57 -> 157701965 | R57: 0.075 | S57: =L57*N57 + (L57*N57*R57*(4+3+2+1+0)/5) -> 3.087975e+08 | T57: =S57/(1-M57) -> 490154756 | U57: =T57*M57 -> 1.8135726e+08 | V57: 2026 | W57: https://blockshopper.com/ca/san-francisco-county/san-francisco/property/0958030/2870-broadway-street; https://www.redfin.com/CA/San-Francisco/2870-Broadway-St-94115/home/1811887#property-details | X57: Estimated value on redfin.com is $29,608,760.
A58: 56 | B58: Patrick Soon-Shiong | C58: $5.4B | D58: 5400000000 | E58: Los Angeles | F58: =VLOOKUP(B58,Raw_Data_Collection!$B$2:$F$215,5,FALSE) -> N | G58: =VLOOKUP(B58,Raw_Data_Collection!$B$2:$J$215,6,FALSE) -> 30000000 | H58: https://www.celebritynetworth.com/articles/celebrity-homes/patrick-soon-shiongs-house-brentwood-billionaire-doctor-demolished-seven-houses-build-one-insane-mega-property/ | I58: 2014 | J58: =VLOOKUP(B58,Raw_Data_Collection!$B$2:$J$215,9,FALSE) -> 162500000 | K58: =VLOOKUP(B58,Real_Estate_Stats!$A$2:$G$215,7,FALSE) -> 162500000 | L58: =D58-K58 -> 5237500000 | M58: 0.37 | N58: 0.05 | O58: =L58*N58 -> 261875000 | P58: =O58/(1-M58) -> 4.156746e+08 | Q58: =P58*M58 -> 1.537996e+08 | R58: 0.075 | S58: =L58*N58 + (L58*N58*R58*(4+3+2+1+0)/5) -> 301156250 | T58: =S58/(1-M58) -> 4.7802579e+08 | U58: =T58*M58 -> 1.7686954e+08 | V58: 2005-2016 | W58: https://www.ocregister.com/2016/02/04/oceanfront-laguna-beach-estate-twin-points-sells-for-record-shattering-45-million/; https://virtualglobetrotting.com/map/patrick-soon-shiongs-house-2/view/google/; https://www.ocbj.com/special-report/ocs-wealthiest-2024/ocs-wealthiest-2024-patrick-soon-shiong/; https://www.celebritynetworth.com/articles/celebrity-homes/patrick-soon-shiongs-house-brentwood-billionaire-doctor-demolished-seven-houses-build-one-insane-mega-property/ | X58: Main estate consists of 7 properties combined for $30 million dollars according to celebritynetworth.com
A59: 57 | B59: Jean (Gigi) Pritzker | C59: $5.4B | D59: 5400000000 | E59: Los Angeles | F59: =VLOOKUP(B59,Raw_Data_Collection!$B$2:$F$215,5,FALSE) -> N | G59: =VLOOKUP(B59,Raw_Data_Collection!$B$2:$J$215,6,FALSE) | J59: =VLOOKUP(B59,Raw_Data_Collection!$B$2:$J$215,9,FALSE) | K59: =VLOOKUP(B59,Real_Estate_Stats!$A$2:$G$215,7,FALSE) -> 34345929 | L59: =D59-K59 -> 5365654071 | M59: 0.37 | N59: 0.05 | O59: =L59*N59 -> 2.682827e+08 | P59: =O59/(1-M59) -> 4.2584556e+08 | Q59: =P59*M59 -> 1.5756286e+08 | R59: 0.075 | S59: =L59*N59 + (L59*N59*R59*(4+3+2+1+0)/5) -> 3.0852511e+08 | T59: =S59/(1-M59) -> 4.897224e+08 | U59: =T59*M59 -> 1.8119729e+08
A60: 58 | B60: Stewart Resnick | C60: $5.3B | D60: 5300000000 | E60: Beverly Hills | F60: =VLOOKUP(B60,Raw_Data_Collection!$B$2:$F$215,5,FALSE) -> N | G60: =VLOOKUP(B60,Raw_Data_Collection!$B$2:$J$215,6,FALSE) -> 17115689 | H60: https://www.homes.com/property/9491-sunset-blvd-beverly-hills-ca/sw2h7klpb942m/ | I60: 2026 | J60: =VLOOKUP(B60,Raw_Data_Collection!$B$2:$J$215,9,FALSE) -> 17115689 | K60: =VLOOKUP(B60,Real_Estate_Stats!$A$2:$G$215,7,FALSE) -> 17115689 | L60: =D60-K60 -> 5282884311 | M60: 0.37 | N60: 0.05 | O60: =L60*N60 -> 2.6414422e+08 | P60: =O60/(1-M60) -> 4.1927653e+08 | Q60: =P60*M60 -> 1.5513232e+08 | R60: 0.075 | S60: =L60*N60 + (L60*N60*R60*(4+3+2+1+0)/5) -> 3.0376585e+08 | T60: =S60/(1-M60) -> 4.8216801e+08 | U60: =T60*M60 -> 1.7840216e+08 | V60: 2026 | W60: https://www.homes.com/property/9491-sunset-blvd-beverly-hills-ca/sw2h7klpb942m/ | X60: Estimated value on homes.com is $8,902,000 - $17,115,689.
A61: 59 | B61: Lynda Resnick | C61: $5.3B | D61: 5300000000 | E61: Beverly Hills | F61: =VLOOKUP(B61,Raw_Data_Collection!$B$2:$F$215,5,FALSE) -> N | G61: =VLOOKUP(B61,Raw_Data_Collection!$B$2:$J$215,6,FALSE) -> 17115689 | H61: https://www.homes.com/property/9491-sunset-blvd-beverly-hills-ca/sw2h7klpb942m/ | I61: 2026 | J61: =VLOOKUP(B61,Raw_Data_Collection!$B$2:$J$215,9,FALSE) -> 17115689 | K61: =VLOOKUP(B61,Real_Estate_Stats!$A$2:$G$215,7,FALSE) -> 17115689 | L61: =D61-K61 -> 5282884311 | M61: 0.37 | N61: 0.05 | O61: =L61*N61 -> 2.6414422e+08 | P61: =O61/(1-M61) -> 4.1927653e+08 | Q61: =P61*M61 -> 1.5513232e+08 | R61: 0.075 | S61: =L61*N61 + (L61*N61*R61*(4+3+2+1+0)/5) -> 3.0376585e+08 | T61: =S61/(1-M61) -> 4.8216801e+08 | U61: =T61*M61 -> 1.7840216e+08 | V61: 2026 | W61: https://www.homes.com/property/9491-sunset-blvd-beverly-hills-ca/sw2h7klpb942m/ | X61: Estimated value on homes.com is $8,902,000 - $17,115,689.
A62: 60 | B62: Eduardo Vivas | C62: $5.3B | D62: 5300000000 | E62: Palo Alto | F62: =VLOOKUP(B62,Raw_Data_Collection!$B$2:$F$215,5,FALSE) -> N | G62: =VLOOKUP(B62,Raw_Data_Collection!$B$2:$J$215,6,FALSE) | J62: =VLOOKUP(B62,Raw_Data_Collection!$B$2:$J$215,9,FALSE) | K62: =VLOOKUP(B62,Real_Estate_Stats!$A$2:$G$215,7,FALSE) -> 33709893 | L62: =D62-K62 -> 5266290107 | M62: 0.37 | N62: 0.05 | O62: =L62*N62 -> 2.6331451e+08 | P62: =O62/(1-M62) -> 4.1795953e+08 | Q62: =P62*M62 -> 154645027 | R62: 0.075 | S62: =L62*N62 + (L62*N62*R62*(4+3+2+1+0)/5) -> 3.0281168e+08 | T62: =S62/(1-M62) -> 4.8065346e+08 | U62: =T62*M62 -> 177841781
A63: 61 | B63: George Lucas | C63: $5.3B | D63: 5300000000 | E63: San Anselmo | F63: =VLOOKUP(B63,Raw_Data_Collection!$B$2:$F$215,5,FALSE) -> N | G63: =VLOOKUP(B63,Raw_Data_Collection!$B$2:$J$215,6,FALSE) -> 41600000 | H63: https://www.marinij.com/2023/07/29/george-lucas-sues-to-secure-san-anselmo-parcel-ownership/ | I63: 2026 | J63: =VLOOKUP(B63,Raw_Data_Collection!$B$2:$J$215,9,FALSE) -> 123000000 | K63: =VLOOKUP(B63,Real_Estate_Stats!$A$2:$G$215,7,FALSE) -> 123000000 | L63: =D63-K63 -> 5177000000 | M63: 0.37 | N63: 0.05 | O63: =L63*N63 -> 258850000 | P63: =O63/(1-M63) -> 4.1087302e+08 | Q63: =P63*M63 -> 1.5202302e+08 | R63: 0.075 | S63: =L63*N63 + (L63*N63*R63*(4+3+2+1+0)/5) -> 297677500 | T63: =S63/(1-M63) -> 4.7250397e+08 | U63: =T63*M63 -> 1.7482647e+08 | V63: 2010-2023 | W63: https://robbreport.com/shelter/celebrity-homes/lists/george-lucas-property-portfolio-1237348814/; https://www.sfgate.com/realestate/article/George-Lucas-Carpinteria-houses-owned-property-14885154.php; https://www.marinij.com/2023/07/29/george-lucas-sues-to-secure-san-anselmo-parcel-ownership/ | X63: Lucas also owns "Skywalker Ranch", but this is not a residential property and is instead used for business.
A64: 62 | B64: Reed Hastings | C64: $5.1B | D64: 5100000000 | E64: Santa Cruz | F64: =VLOOKUP(B64,Raw_Data_Collection!$B$2:$F$215,5,FALSE) -> Y | G64: =VLOOKUP(B64,Raw_Data_Collection!$B$2:$J$215,6,FALSE) -> 1750000 | H64: https://www.celebritynetworth.com/richest-businessmen/ceos/reed-hastings-net-worth/ | I64: 2016 | J64: =VLOOKUP(B64,Raw_Data_Collection!$B$2:$J$215,9,FALSE) -> 3250000 | K64: =VLOOKUP(B64,Real_Estate_Stats!$A$2:$G$215,7,FALSE) -> 3250000 | L64: =D64-K64 -> 5096750000 | M64: 0.37 | N64: 0.05 | O64: =L64*N64 -> 254837500 | P64: =O64/(1-M64) -> 4.0450397e+08 | Q64: =P64*M64 -> 1.4966647e+08 | R64: 0.075 | S64: =L64*N64 + (L64*N64*R64*(4+3+2+1+0)/5) -> 293063125 | T64: =S64/(1-M64) -> 4.6517956e+08 | U64: =T64*M64 -> 1.7211644e+08 | V64: 2013-2016 | W64: https://www.celebritynetworth.com/richest-businessmen/ceos/reed-hastings-net-worth/ | X64: Hastings also owns property in Hollywood. | Y64: https://nypost.com/2026/01/08/real-estate/tech-titans-leaving-california-for-florida-over-billionaire-tax/
A65: 63 | B65: Eric Yuan | C65: $5.1B | D65: 5100000000 | E65: Santa Clara | F65: =VLOOKUP(B65,Raw_Data_Collection!$B$2:$F$215,5,FALSE) -> N | G65: =VLOOKUP(B65,Raw_Data_Collection!$B$2:$J$215,6,FALSE) | J65: =VLOOKUP(B65,Raw_Data_Collection!$B$2:$J$215,9,FALSE) | K65: =VLOOKUP(B65,Real_Estate_Stats!$A$2:$G$215,7,FALSE) -> 32437821 | L65: =D65-K65 -> 5067562179 | M65: 0.37 | N65: 0.05 | O65: =L65*N65 -> 2.5337811e+08 | P65: =O65/(1-M65) -> 4.0218747e+08 | Q65: =P65*M65 -> 1.4880937e+08 | R65: 0.075 | S65: =L65*N65 + (L65*N65*R65*(4+3+2+1+0)/5) -> 2.9138483e+08 | T65: =S65/(1-M65) -> 4.625156e+08 | U65: =T65*M65 -> 1.7113077e+08
A66: 64 | B66: Gwendolyn Sontheim Meyer | C66: $5B | D66: 5000000000 | E66: Rancho Santa Fe | F66: =VLOOKUP(B66,Raw_Data_Collection!$B$2:$F$215,5,FALSE) -> N | G66: =VLOOKUP(B66,Raw_Data_Collection!$B$2:$J$215,6,FALSE) | J66: =VLOOKUP(B66,Raw_Data_Collection!$B$2:$J$215,9,FALSE) | K66: =VLOOKUP(B66,Real_Estate_Stats!$A$2:$G$215,7,FALSE) -> 31801786 | L66: =D66-K66 -> 4968198214 | M66: 0.37 | N66: 0.05 | O66: =L66*N66 -> 2.4840991e+08 | P66: =O66/(1-M66) -> 3.9430145e+08 | Q66: =P66*M66 -> 1.4589153e+08 | R66: 0.075 | S66: =L66*N66 + (L66*N66*R66*(4+3+2+1+0)/5) -> 2.856714e+08 | T66: =S66/(1-M66) -> 4.5344666e+08 | U66: =T66*M66 -> 1.6777527e+08
A67: 65 | B67: Jim Coulter | C67: $5B | D67: 5000000000 | E67: San Francisco | F67: =VLOOKUP(B67,Raw_Data_Collection!$B$2:$F$215,5,FALSE) -> N | G67: =VLOOKUP(B67,Raw_Data_Collection!$B$2:$J$215,6,FALSE) | J67: =VLOOKUP(B67,Raw_Data_Collection!$B$2:$J$215,9,FALSE) | K67: =VLOOKUP(B67,Real_Estate_Stats!$A$2:$G$215,7,FALSE) -> 31801786 | L67: =D67-K67 -> 4968198214 | M67: 0.37 | N67: 0.05 | O67: =L67*N67 -> 2.4840991e+08 | P67: =O67/(1-M67) -> 3.9430145e+08 | Q67: =P67*M67 -> 1.4589153e+08 | R67: 0.075 | S67: =L67*N67 + (L67*N67*R67*(4+3+2+1+0)/5) -> 2.856714e+08 | T67: =S67/(1-M67) -> 4.5344666e+08 | U67: =T67*M67 -> 1.6777527e+08
A68: 66 | B68: Jack Dorsey | C68: $4.9B | D68: 4900000000 | E68: San Francisco | F68: =VLOOKUP(B68,Raw_Data_Collection!$B$2:$F$215,5,FALSE) -> N | G68: =VLOOKUP(B68,Raw_Data_Collection!$B$2:$J$215,6,FALSE) -> 31900000 | H68: https://www.yahoo.com/entertainment/twitter-ceo-jack-dorsey-scoops-011751538.html | I68: 2018 | J68: =VLOOKUP(B68,Raw_Data_Collection!$B$2:$J$215,9,FALSE) -> 31900000 | K68: =VLOOKUP(B68,Real_Estate_Stats!$A$2:$G$215,7,FALSE) -> 31900000 | L68: =D68-K68 -> 4868100000 | M68: 0.37 | N68: 0.05 | O68: =L68*N68 -> 243405000 | P68: =O68/(1-M68) -> 3.8635714e+08 | Q68: =P68*M68 -> 1.4295214e+08 | R68: 0.075 | S68: =L68*N68 + (L68*N68*R68*(4+3+2+1+0)/5) -> 279915750 | T68: =S68/(1-M68) -> 4.4431071e+08 | U68: =T68*M68 -> 1.6439496e+08 | V68: 2012-2018 | W68: https://www.yahoo.com/entertainment/twitter-ceo-jack-dorsey-scoops-011751538.html; https://www.yahoo.com/entertainment/jack-dorsey-hollywood-hills-hideaway-015224916.html | X68: Compound consists of two residences, one bought in 2012 for $10 million and one bought in 2019 for $21.9 million. His Hollywood Hills residence was later sold.
A69: 67 | B69: David Baszucki | C69: $4.9B | D69: 4900000000 | E69: San Francisco | F69: =VLOOKUP(B69,Raw_Data_Collection!$B$2:$F$215,5,FALSE) -> N | G69: =VLOOKUP(B69,Raw_Data_Collection!$B$2:$J$215,6,FALSE) | J69: =VLOOKUP(B69,Raw_Data_Collection!$B$2:$J$215,9,FALSE) | K69: =VLOOKUP(B69,Real_Estate_Stats!$A$2:$G$215,7,FALSE) -> 31165750 | L69: =D69-K69 -> 4868834250 | M69: 0.37 | N69: 0.05 | O69: =L69*N69 -> 2.4344171e+08 | P69: =O69/(1-M69) -> 3.8641542e+08 | Q69: =P69*M69 -> 1.429737e+08 | R69: 0.075 | S69: =L69*N69 + (L69*N69*R69*(4+3+2+1+0)/5) -> 2.7995797e+08 | T69: =S69/(1-M69) -> 4.4437773e+08 | U69: =T69*M69 -> 1.6441976e+08
A70: 68 | B70: Scott Crabill | C70: $4.8B | D70: 4800000000 | E70: San Francisco | F70: =VLOOKUP(B70,Raw_Data_Collection!$B$2:$F$215,5,FALSE) -> N | G70: =VLOOKUP(B70,Raw_Data_Collection!$B$2:$J$215,6,FALSE) -> 22222762 | H70: https://www.homes.com/property/34-maple-st-san-francisco-ca/83sknmj9zbck7/ | I70: 2026 | J70: =VLOOKUP(B70,Raw_Data_Collection!$B$2:$J$215,9,FALSE) -> 59322762 | K70: =VLOOKUP(B70,Real_Estate_Stats!$A$2:$G$215,7,FALSE) -> 59322762 | L70: =D70-K70 -> 4740677238 | M70: 0.37 | N70: 0.05 | O70: =L70*N70 -> 2.3703386e+08 | P70: =O70/(1-M70) -> 3.7624423e+08 | Q70: =P70*M70 -> 1.3921036e+08 | R70: 0.075 | S70: =L70*N70 + (L70*N70*R70*(4+3+2+1+0)/5) -> 2.7258894e+08 | T70: =S70/(1-M70) -> 432680859 | U70: =T70*M70 -> 1.6009192e+08 | V70: 2017-2026 | W70: https://www.homes.com/property/34-maple-st-san-francisco-ca/83sknmj9zbck7/; https://www.compass.com/homedetails/1710-Cabernet-Ln-St-Helena-CA-94574/7885975409678385_lid/; https://www.compass.com/homedetails/12-Upper-Ames-Ave-Ross-CA-94957/1018950796530693897_lid/; https://www.compass.com/homedetails/3712-Jackson-St-San-Francisco-CA-94118/778822386949832337_lid/ | X70: Estimated value on homes.com is $7,527,000 - $22,222,762.
A71: 69 | B71: Holden Spaht | C71: $4.8B | D71: 4800000000 | E71: San Francisco | F71: =VLOOKUP(B71,Raw_Data_Collection!$B$2:$F$215,5,FALSE) -> N | G71: =VLOOKUP(B71,Raw_Data_Collection!$B$2:$J$215,6,FALSE) -> 6849000 | H71: https://www.homes.com/property/2324-pacific-ave-san-francisco-ca/qpzresp8fbygw/ | I71: 2026 | J71: =VLOOKUP(B71,Raw_Data_Collection!$B$2:$J$215,9,FALSE) -> 6849000 | K71: =VLOOKUP(B71,Real_Estate_Stats!$A$2:$G$215,7,FALSE) -> 6849000 | L71: =D71-K71 -> 4793151000 | M71: 0.37 | N71: 0.05 | O71: =L71*N71 -> 239657550 | P71: =O71/(1-M71) -> 3.8040881e+08 | Q71: =P71*M71 -> 1.4075126e+08 | R71: 0.075 | S71: =L71*N71 + (L71*N71*R71*(4+3+2+1+0)/5) -> 2.7560618e+08 | T71: =S71/(1-M71) -> 437470131 | U71: =T71*M71 -> 1.6186395e+08 | V71: 2026 | W71: https://www.homes.com/property/2324-pacific-ave-san-francisco-ca/qpzresp8fbygw/ | X71: Estimated value on homes.com is $6,849,000.
A72: 70 | B72: Seth Boro | C72: $4.8B | D72: 4800000000 | E72: San Anselmo | F72: =VLOOKUP(B72,Raw_Data_Collection!$B$2:$F$215,5,FALSE) -> N | G72: =VLOOKUP(B72,Raw_Data_Collection!$B$2:$J$215,6,FALSE) -> 5884000 | H72: https://www.homes.com/property/429-elizabeth-st-san-francisco-ca/xpxfwnhw0x4kw/ | I72: 2026 | J72: =VLOOKUP(B72,Raw_Data_Collection!$B$2:$J$215,9,FALSE) -> 5884000 | K72: =VLOOKUP(B72,Real_Estate_Stats!$A$2:$G$215,7,FALSE) -> 5884000 | L72: =D72-K72 -> 4794116000 | M72: 0.37 | N72: 0.05 | O72: =L72*N72 -> 239705800 | P72: =O72/(1-M72) -> 3.804854e+08 | Q72: =P72*M72 -> 1.407796e+08 | R72: 0.075 | S72: =L72*N72 + (L72*N72*R72*(4+3+2+1+0)/5) -> 275661670 | T72: =S72/(1-M72) -> 4.3755821e+08 | U72: =T72*M72 -> 1.6189654e+08 | V72: 2026 | W72: https://www.homes.com/property/429-elizabeth-st-san-francisco-ca/xpxfwnhw0x4kw/ | X72: Estimated value on homes.com is $2,842,000 - $5,884,000.
A73: 71 | B73: Michael Xie | C73: $4.8B | D73: 4800000000 | E73: Los Altos Hills | F73: =VLOOKUP(B73,Raw_Data_Collection!$B$2:$F$215,5,FALSE) -> N | G73: =VLOOKUP(B73,Raw_Data_Collection!$B$2:$J$215,6,FALSE) -> 13269963 | H73: https://www.homes.com/property/27161-w-fremont-rd-los-altos-hills-ca/yneqges0z8j44/ | I73: 2026 | J73: =VLOOKUP(B73,Raw_Data_Collection!$B$2:$J$215,9,FALSE) -> 25671792 | K73: =VLOOKUP(B73,Real_Estate_Stats!$A$2:$G$215,7,FALSE) -> 25671792 | L73: =D73-K73 -> 4774328208 | M73: 0.37 | N73: 0.05 | O73: =L73*N73 -> 2.3871641e+08 | P73: =O73/(1-M73) -> 3.7891494e+08 | Q73: =P73*M73 -> 1.4019853e+08 | R73: 0.075 | S73: =L73*N73 + (L73*N73*R73*(4+3+2+1+0)/5) -> 274523872 | T73: =S73/(1-M73) -> 4.3575218e+08 | U73: =T73*M73 -> 1.6122831e+08 | V73: 2026 | W73: https://www.homes.com/property/27161-w-fremont-rd-los-altos-hills-ca/yneqges0z8j44/; https://www.homes.com/property/1218-portola-rd-pebble-beach-ca/pyl3bhymmvf5d/ | X73: Estimated value on homes.com is $8,136,000 - $13,269,963
A74: 72 | B74: Dagmar Dolby | C74: $4.8B | D74: 4800000000 | E74: San Francisco | F74: =VLOOKUP(B74,Raw_Data_Collection!$B$2:$F$215,5,FALSE) -> N | G74: =VLOOKUP(B74,Raw_Data_Collection!$B$2:$J$215,6,FALSE) -> 7809894 | H74: https://www.homes.com/property/3340-jackson-st-san-francisco-ca/lemwwpgc5tfrh/ | I74: 2026 | J74: =VLOOKUP(B74,Raw_Data_Collection!$B$2:$J$215,9,FALSE) -> 90000000 | K74: =VLOOKUP(B74,Real_Estate_Stats!$A$2:$G$215,7,FALSE) -> 90000000 | L74: =D74-K74 -> 4710000000 | M74: 0.37 | N74: 0.05 | O74: =L74*N74 -> 235500000 | P74: =O74/(1-M74) -> 3.7380952e+08 | Q74: =P74*M74 -> 1.3830952e+08 | R74: 0.075 | S74: =L74*N74 + (L74*N74*R74*(4+3+2+1+0)/5) -> 270825000 | T74: =S74/(1-M74) -> 4.2988095e+08 | U74: =T74*M74 -> 1.5905595e+08 | V74: 2023 | W74: https://www.forbes.com/sites/forbeswealthteam/2023/08/26/when-10-homes-isnt-enough-which-billionaires-own-the-most-properties-larry-ellison-jeff-bezos-oprah-winfrey/ | X74: Estimated value on homes.com is $5,631,000 - $7,809,894.
A75: 73 | B75: David Filo | C75: $4.5B | D75: 4500000000 | E75: Palo Alto | F75: =VLOOKUP(B75,Raw_Data_Collection!$B$2:$F$215,5,FALSE) -> N | G75: =VLOOKUP(B75,Raw_Data_Collection!$B$2:$J$215,6,FALSE) | J75: =VLOOKUP(B75,Raw_Data_Collection!$B$2:$J$215,9,FALSE) | K75: =VLOOKUP(B75,Real_Estate_Stats!$A$2:$G$215,7,FALSE) -> 28621607 | L75: =D75-K75 -> 4471378393 | M75: 0.37 | N75: 0.05 | O75: =L75*N75 -> 2.2356892e+08 | P75: =O75/(1-M75) -> 354871301 | Q75: =P75*M75 -> 1.3130238e+08 | R75: 0.075 | S75: =L75*N75 + (L75*N75*R75*(4+3+2+1+0)/5) -> 2.5710426e+08 | T75: =S75/(1-M75) -> 4.08102e+08 | U75: =T75*M75 -> 1.5099774e+08
A76: 74 | B76: Rupert Johnson Jr | C76: $4.4B | D76: 4400000000 | E76: Burlingame | F76: =VLOOKUP(B76,Raw_Data_Collection!$B$2:$F$215,5,FALSE) -> N | G76: =VLOOKUP(B76,Raw_Data_Collection!$B$2:$J$215,6,FALSE) | J76: =VLOOKUP(B76,Raw_Data_Collection!$B$2:$J$215,9,FALSE) | K76: =VLOOKUP(B76,Real_Estate_Stats!$A$2:$G$215,7,FALSE) -> 27985571 | L76: =D76-K76 -> 4372014429 | M76: 0.37 | N76: 0.05 | O76: =L76*N76 -> 2.1860072e+08 | P76: =O76/(1-M76) -> 3.4698527e+08 | Q76: =P76*M76 -> 1.2838455e+08 | R76: 0.075 | S76: =L76*N76 + (L76*N76*R76*(4+3+2+1+0)/5) -> 2.5139083e+08 | T76: =S76/(1-M76) -> 3.9903306e+08 | U76: =T76*M76 -> 1.4764223e+08
A77: 75 | B77: Anthony Pritzker | C77: $4.4B | D77: 4400000000 | E77: Los Angeles | F77: =VLOOKUP(B77,Raw_Data_Collection!$B$2:$F$215,5,FALSE) -> N | G77: =VLOOKUP(B77,Raw_Data_Collection!$B$2:$J$215,6,FALSE) -> 195000000 | H77: https://kanebridgenews.com/one-of-americas-biggest-homes-hits-the-market-for-195-million/ | I77: 2024 | J77: =VLOOKUP(B77,Raw_Data_Collection!$B$2:$J$215,9,FALSE) -> 195000000 | K77: =VLOOKUP(B77,Real_Estate_Stats!$A$2:$G$215,7,FALSE) -> 195000000 | L77: =D77-K77 -> 4205000000 | M77: 0.37 | N77: 0.05 | O77: =L77*N77 -> 210250000 | P77: =O77/(1-M77) -> 3.3373016e+08 | Q77: =P77*M77 -> 1.2348016e+08 | R77: 0.075 | S77: =L77*N77 + (L77*N77*R77*(4+3+2+1+0)/5) -> 241787500 | T77: =S77/(1-M77) -> 3.8378968e+08 | U77: =T77*M77 -> 1.4200218e+08 | V77: 2024 | W77: https://kanebridgenews.com/one-of-americas-biggest-homes-hits-the-market-for-195-million/
A78: 76 | B78: Rodney Sacks | C78: $4.3B | D78: 4300000000 | E78: Laguna Beach | F78: =VLOOKUP(B78,Raw_Data_Collection!$B$2:$F$215,5,FALSE) -> N | G78: =VLOOKUP(B78,Raw_Data_Collection!$B$2:$J$215,6,FALSE) | J78: =VLOOKUP(B78,Raw_Data_Collection!$B$2:$J$215,9,FALSE) | K78: =VLOOKUP(B78,Real_Estate_Stats!$A$2:$G$215,7,FALSE) -> 27349536 | L78: =D78-K78 -> 4272650464 | M78: 0.37 | N78: 0.05 | O78: =L78*N78 -> 2.1363252e+08 | P78: =O78/(1-M78) -> 3.3909924e+08 | Q78: =P78*M78 -> 125466720 | R78: 0.075 | S78: =L78*N78 + (L78*N78*R78*(4+3+2+1+0)/5) -> 2.456774e+08 | T78: =S78/(1-M78) -> 3.8996413e+08 | U78: =T78*M78 -> 144286728
A79: 77 | B79: Donald Sterling | C79: $4.3B | D79: 4300000000 | E79: Beverly Hills | F79: =VLOOKUP(B79,Raw_Data_Collection!$B$2:$F$215,5,FALSE) -> N | G79: =VLOOKUP(B79,Raw_Data_Collection!$B$2:$J$215,6,FALSE) -> 11443465 | H79: https://www.homes.com/property/808-n-beverly-dr-beverly-hills-ca/lgnr8czbm0szq/ | I79: 2026 | J79: =VLOOKUP(B79,Raw_Data_Collection!$B$2:$J$215,9,FALSE) -> 29825465 | K79: =VLOOKUP(B79,Real_Estate_Stats!$A$2:$G$215,7,FALSE) -> 29825465 | L79: =D79-K79 -> 4270174535 | M79: 0.37 | N79: 0.05 | O79: =L79*N79 -> 2.1350873e+08 | P79: =O79/(1-M79) -> 3.3890274e+08 | Q79: =P79*M79 -> 1.2539401e+08 | R79: 0.075 | S79: =L79*N79 + (L79*N79*R79*(4+3+2+1+0)/5) -> 2.4553504e+08 | T79: =S79/(1-M79) -> 389738152 | U79: =T79*M79 -> 1.4420312e+08 | V79: 2015-2026 | W79: https://www.homes.com/property/808-n-beverly-dr-beverly-hills-ca/lgnr8czbm0szq/; https://www.realtytoday.com/articles/36434/20150918/former-la-clipper-owner-donald-sterling-buys-beverly-hills-home-for-18m.htm | X79: Estimated value on homes.com is $5,584,000 - $11,443,465.
A80: 78 | B80: Sanjit Biswas | C80: $4.1B | D80: 4100000000 | E80: San Francisco | F80: =VLOOKUP(B80,Raw_Data_Collection!$B$2:$F$215,5,FALSE) -> N | G80: =VLOOKUP(B80,Raw_Data_Collection!$B$2:$J$215,6,FALSE) | J80: =VLOOKUP(B80,Raw_Data_Collection!$B$2:$J$215,9,FALSE) | K80: =VLOOKUP(B80,Real_Estate_Stats!$A$2:$G$215,7,FALSE) -> 26077464 | L80: =D80-K80 -> 4073922536 | M80: 0.37 | N80: 0.05 | O80: =L80*N80 -> 2.0369613e+08 | P80: =O80/(1-M80) -> 3.2332719e+08 | Q80: =P80*M80 -> 1.1963106e+08 | R80: 0.075 | S80: =L80*N80 + (L80*N80*R80*(4+3+2+1+0)/5) -> 2.3425055e+08 | T80: =S80/(1-M80) -> 3.7182626e+08 | U80: =T80*M80 -> 1.3757572e+08
A81: 79 | B81: Thomas Siebel | C81: $4B | D81: 4000000000 | E81: Woodside | F81: =VLOOKUP(B81,Raw_Data_Collection!$B$2:$F$215,5,FALSE) -> N | G81: =VLOOKUP(B81,Raw_Data_Collection!$B$2:$J$215,6,FALSE) | J81: =VLOOKUP(B81,Raw_Data_Collection!$B$2:$J$215,9,FALSE) | K81: =VLOOKUP(B81,Real_Estate_Stats!$A$2:$G$215,7,FALSE) -> 25441429 | L81: =D81-K81 -> 3974558571 | M81: 0.37 | N81: 0.05 | O81: =L81*N81 -> 1.9872793e+08 | P81: =O81/(1-M81) -> 3.1544116e+08 | Q81: =P81*M81 -> 1.1671323e+08 | R81: 0.075 | S81: =L81*N81 + (L81*N81*R81*(4+3+2+1+0)/5) -> 2.2853712e+08 | T81: =S81/(1-M81) -> 3.6275733e+08 | U81: =T81*M81 -> 1.3422021e+08
A82: 80 | B82: John Bicket | C82: $4B | D82: 4000000000 | E82: San Francisco | F82: =VLOOKUP(B82,Raw_Data_Collection!$B$2:$F$215,5,FALSE) -> N | G82: =VLOOKUP(B82,Raw_Data_Collection!$B$2:$J$215,6,FALSE) | J82: =VLOOKUP(B82,Raw_Data_Collection!$B$2:$J$215,9,FALSE) | K82: =VLOOKUP(B82,Real_Estate_Stats!$A$2:$G$215,7,FALSE) -> 25441429 | L82: =D82-K82 -> 3974558571 | M82: 0.37 | N82: 0.05 | O82: =L82*N82 -> 1.9872793e+08 | P82: =O82/(1-M82) -> 3.1544116e+08 | Q82: =P82*M82 -> 1.1671323e+08 | R82: 0.075 | S82: =L82*N82 + (L82*N82*R82*(4+3+2+1+0)/5) -> 2.2853712e+08 | T82: =S82/(1-M82) -> 3.6275733e+08 | U82: =T82*M82 -> 1.3422021e+08
A83: 81 | B83: José E. Feliciano | C83: $3.8B | D83: 3800000000 | E83: Los Angeles | F83: =VLOOKUP(B83,Raw_Data_Collection!$B$2:$F$215,5,FALSE) -> N | G83: =VLOOKUP(B83,Raw_Data_Collection!$B$2:$J$215,6,FALSE) -> 50000000 | H83: https://palisadesnews.com/private-equity-billionaire-jose-e-feliciano-buys-50-palisades-million-mansion-narrowly-avoids-new-mansion-tax/ | I83: 2023 | J83: =VLOOKUP(B83,Raw_Data_Collection!$B$2:$J$215,9,FALSE) -> 50000000 | K83: =VLOOKUP(B83,Real_Estate_Stats!$A$2:$G$215,7,FALSE) -> 50000000 | L83: =D83-K83 -> 3750000000 | M83: 0.37 | N83: 0.05 | O83: =L83*N83 -> 187500000 | P83: =O83/(1-M83) -> 2.9761905e+08 | Q83: =P83*M83 -> 1.1011905e+08 | R83: 0.075 | S83: =L83*N83 + (L83*N83*R83*(4+3+2+1+0)/5) -> 215625000 | T83: =S83/(1-M83) -> 3.422619e+08 | U83: =T83*M83 -> 1.266369e+08 | V83: 2023 | W83: https://palisadesnews.com/private-equity-billionaire-jose-e-feliciano-buys-50-palisades-million-mansion-narrowly-avoids-new-mansion-tax/
A84: 82 | B84: Meg Whitman | C84: $3.8B | D84: 3800000000 | E84: Los Angeles | F84: =VLOOKUP(B84,Raw_Data_Collection!$B$2:$F$215,5,FALSE) -> N | G84: =VLOOKUP(B84,Raw_Data_Collection!$B$2:$J$215,6,FALSE) -> 6500000 | H84: https://www.latimes.com/business/real-estate/story/2020-08-10/quibi-chief-meg-whitman-lists-west-hollywood-condo-for-6-5-million | I84: 2020 | J84: =VLOOKUP(B84,Raw_Data_Collection!$B$2:$J$215,9,FALSE) -> 6500000 | K84: =VLOOKUP(B84,Real_Estate_Stats!$A$2:$G$215,7,FALSE) -> 6500000 | L84: =D84-K84 -> 3793500000 | M84: 0.37 | N84: 0.05 | O84: =L84*N84 -> 189675000 | P84: =O84/(1-M84) -> 3.0107143e+08 | Q84: =P84*M84 -> 1.1139643e+08 | R84: 0.075 | S84: =L84*N84 + (L84*N84*R84*(4+3+2+1+0)/5) -> 218126250 | T84: =S84/(1-M84) -> 3.4623214e+08 | U84: =T84*M84 -> 1.2810589e+08 | V84: 2020 | W84: https://www.latimes.com/business/real-estate/story/2020-08-10/quibi-chief-meg-whitman-lists-west-hollywood-condo-for-6-5-million | X84: While listed for sale, Whitman still seems to have not sold the residence yet.
A85: 83 | B85: Behdad Eghbali | C85: $3.8B | D85: 3800000000 | E85: Los Angeles | F85: =VLOOKUP(B85,Raw_Data_Collection!$B$2:$F$215,5,FALSE) -> N | G85: =VLOOKUP(B85,Raw_Data_Collection!$B$2:$J$215,6,FALSE) -> 21000000 | H85: https://www.yahoo.com/entertainment/billionaire-behdad-eghbali-buys-21-224623408.html | I85: 2020 | J85: =VLOOKUP(B85,Raw_Data_Collection!$B$2:$J$215,9,FALSE) | K85: =VLOOKUP(B85,Real_Estate_Stats!$A$2:$G$215,7,FALSE) -> 21000000 | L85: =D85-K85 -> 3779000000 | M85: 0.37 | N85: 0.05 | O85: =L85*N85 -> 188950000 | P85: =O85/(1-M85) -> 2.9992063e+08 | Q85: =P85*M85 -> 1.1097063e+08 | R85: 0.075 | S85: =L85*N85 + (L85*N85*R85*(4+3+2+1+0)/5) -> 217292500 | T85: =S85/(1-M85) -> 3.4490873e+08 | U85: =T85*M85 -> 1.2761623e+08
A86: 84 | B86: Peter Gassner | C86: $3.8B | D86: 3800000000 | E86: Pleasanton | F86: =VLOOKUP(B86,Raw_Data_Collection!$B$2:$F$215,5,FALSE) -> N | G86: =VLOOKUP(B86,Raw_Data_Collection!$B$2:$J$215,6,FALSE) -> 1977425 | H86: https://www.homes.com/property/4512-lin-gate-st-pleasanton-ca/jfjbyjdmsmcgx/ | I86: 2026 | J86: =VLOOKUP(B86,Raw_Data_Collection!$B$2:$J$215,9,FALSE) | K86: =VLOOKUP(B86,Real_Estate_Stats!$A$2:$G$215,7,FALSE) -> 1977425 | L86: =D86-K86 -> 3798022575 | M86: 0.37 | N86: 0.05 | O86: =L86*N86 -> 1.8990113e+08 | P86: =O86/(1-M86) -> 3.0143036e+08 | Q86: =P86*M86 -> 1.1152923e+08 | R86: 0.075 | S86: =L86*N86 + (L86*N86*R86*(4+3+2+1+0)/5) -> 2.183863e+08 | T86: =S86/(1-M86) -> 3.4664492e+08 | U86: =T86*M86 -> 1.2825862e+08 | X86: Estimated value on homes.com is $1,887,000 - $2,072,000
A87: 85 | B87: John Fisher | C87: $3.7B | D87: 3700000000 | E87: San Francisco | F87: =VLOOKUP(B87,Raw_Data_Collection!$B$2:$F$215,5,FALSE) -> N | G87: =VLOOKUP(B87,Raw_Data_Collection!$B$2:$J$215,6,FALSE) -> 29250000 | J87: =VLOOKUP(B87,Raw_Data_Collection!$B$2:$J$215,9,FALSE) | K87: =VLOOKUP(B87,Real_Estate_Stats!$A$2:$G$215,7,FALSE) -> 29250000 | L87: =D87-K87 -> 3670750000 | M87: 0.37 | N87: 0.05 | O87: =L87*N87 -> 183537500 | P87: =O87/(1-M87) -> 2.9132937e+08 | Q87: =P87*M87 -> 1.0779187e+08 | R87: 0.075 | S87: =L87*N87 + (L87*N87*R87*(4+3+2+1+0)/5) -> 211068125 | T87: =S87/(1-M87) -> 3.3502877e+08 | U87: =T87*M87 -> 1.2396064e+08
A88: 86 | B88: Danny Harris | C88: $3.7B | D88: 3700000000 | E88: Los Angeles | F88: =VLOOKUP(B88,Raw_Data_Collection!$B$2:$F$215,5,FALSE) -> N | G88: =VLOOKUP(B88,Raw_Data_Collection!$B$2:$J$215,6,FALSE) -> 30000000 | H88: https://therealdeal.com/la/2017/02/21/alo-yoga-founder-buys-beverly-hills-house-from-bebe-founder-for-30m/ | I88: 2017 | J88: =VLOOKUP(B88,Raw_Data_Collection!$B$2:$J$215,9,FALSE) | K88: =VLOOKUP(B88,Real_Estate_Stats!$A$2:$G$215,7,FALSE) -> 30000000 | L88: =D88-K88 -> 3670000000 | M88: 0.37 | N88: 0.05 | O88: =L88*N88 -> 183500000 | P88: =O88/(1-M88) -> 2.9126984e+08 | Q88: =P88*M88 -> 1.0776984e+08 | R88: 0.075 | S88: =L88*N88 + (L88*N88*R88*(4+3+2+1+0)/5) -> 211025000 | T88: =S88/(1-M88) -> 3.3496032e+08 | U88: =T88*M88 -> 1.2393532e+08
A89: 87 | B89: Jared Kaplan | C89: $3.7B | D89: 3700000000 | E89: Pacifica | F89: =VLOOKUP(B89,Raw_Data_Collection!$B$2:$F$215,5,FALSE) -> N | G89: =VLOOKUP(B89,Raw_Data_Collection!$B$2:$J$215,6,FALSE) | J89: =VLOOKUP(B89,Raw_Data_Collection!$B$2:$J$215,9,FALSE) | K89: =VLOOKUP(B89,Real_Estate_Stats!$A$2:$G$215,7,FALSE) -> 23533321 | L89: =D89-K89 -> 3676466679 | M89: 0.37 | N89: 0.05 | O89: =L89*N89 -> 1.8382333e+08 | P89: =O89/(1-M89) -> 2.9178307e+08 | Q89: =P89*M89 -> 1.0795974e+08 | R89: 0.075 | S89: =L89*N89 + (L89*N89*R89*(4+3+2+1+0)/5) -> 211396834 | T89: =S89/(1-M89) -> 3.3555053e+08 | U89: =T89*M89 -> 1.241537e+08
A90: 88 | B90: Dario Amodei | C90: $3.7B | D90: 3700000000 | E90: San Francisco | F90: =VLOOKUP(B90,Raw_Data_Collection!$B$2:$F$215,5,FALSE) -> N | G90: =VLOOKUP(B90,Raw_Data_Collection!$B$2:$J$215,6,FALSE) | J90: =VLOOKUP(B90,Raw_Data_Collection!$B$2:$J$215,9,FALSE) | K90: =VLOOKUP(B90,Real_Estate_Stats!$A$2:$G$215,7,FALSE) -> 23533321 | L90: =D90-K90 -> 3676466679 | M90: 0.37 | N90: 0.05 | O90: =L90*N90 -> 1.8382333e+08 | P90: =O90/(1-M90) -> 2.9178307e+08 | Q90: =P90*M90 -> 1.0795974e+08 | R90: 0.075 | S90: =L90*N90 + (L90*N90*R90*(4+3+2+1+0)/5) -> 211396834 | T90: =S90/(1-M90) -> 3.3555053e+08 | U90: =T90*M90 -> 1.241537e+08
A91: 89 | B91: Tom Brown | C91: $3.7B | D91: 3700000000 | E91: San Francisco | F91: =VLOOKUP(B91,Raw_Data_Collection!$B$2:$F$215,5,FALSE) -> N | G91: =VLOOKUP(B91,Raw_Data_Collection!$B$2:$J$215,6,FALSE) -> 2572000 | J91: =VLOOKUP(B91,Raw_Data_Collection!$B$2:$J$215,9,FALSE) | K91: =VLOOKUP(B91,Real_Estate_Stats!$A$2:$G$215,7,FALSE) -> 2572000 | L91: =D91-K91 -> 3697428000 | M91: 0.37 | N91: 0.05 | O91: =L91*N91 -> 184871400 | P91: =O91/(1-M91) -> 2.9344667e+08 | Q91: =P91*M91 -> 1.0857527e+08 | R91: 0.075 | S91: =L91*N91 + (L91*N91*R91*(4+3+2+1+0)/5) -> 212602110 | T91: =S91/(1-M91) -> 3.3746367e+08 | U91: =T91*M91 -> 1.2486156e+08
A92: 90 | B92: Jack Clark | C92: $3.7B | D92: 3700000000 | F92: =VLOOKUP(B92,Raw_Data_Collection!$B$2:$F$215,5,FALSE) -> N | G92: =VLOOKUP(B92,Raw_Data_Collection!$B$2:$J$215,6,FALSE) | J92: =VLOOKUP(B92,Raw_Data_Collection!$B$2:$J$215,9,FALSE) | K92: =VLOOKUP(B92,Real_Estate_Stats!$A$2:$G$215,7,FALSE) -> 23533321 | L92: =D92-K92 -> 3676466679 | M92: 0.37 | N92: 0.05 | O92: =L92*N92 -> 1.8382333e+08 | P92: =O92/(1-M92) -> 2.9178307e+08 | Q92: =P92*M92 -> 1.0795974e+08 | R92: 0.075 | S92: =L92*N92 + (L92*N92*R92*(4+3+2+1+0)/5) -> 211396834 | T92: =S92/(1-M92) -> 3.3555053e+08 | U92: =T92*M92 -> 1.241537e+08
A93: 91 | B93: Sam McCandlish | C93: $3.7B | D93: 3700000000 | E93: San Francisco | F93: =VLOOKUP(B93,Raw_Data_Collection!$B$2:$F$215,5,FALSE) -> N | G93: =VLOOKUP(B93,Raw_Data_Collection!$B$2:$J$215,6,FALSE) -> 4831145 | J93: =VLOOKUP(B93,Raw_Data_Collection!$B$2:$J$215,9,FALSE) | K93: =VLOOKUP(B93,Real_Estate_Stats!$A$2:$G$215,7,FALSE) -> 4831145 | L93: =D93-K93 -> 3695168855 | M93: 0.37 | N93: 0.05 | O93: =L93*N93 -> 1.8475844e+08 | P93: =O93/(1-M93) -> 2.9326737e+08 | Q93: =P93*M93 -> 1.0850893e+08 | R93: 0.075 | S93: =L93*N93 + (L93*N93*R93*(4+3+2+1+0)/5) -> 2.1247221e+08 | T93: =S93/(1-M93) -> 3.3725747e+08 | U93: =T93*M93 -> 1.2478527e+08
A94: 92 | B94: Daniela Amodei | C94: $3.7B | D94: 3700000000 | E94: San Francisco | F94: =VLOOKUP(B94,Raw_Data_Collection!$B$2:$F$215,5,FALSE) -> N | G94: =VLOOKUP(B94,Raw_Data_Collection!$B$2:$J$215,6,FALSE) | J94: =VLOOKUP(B94,Raw_Data_Collection!$B$2:$J$215,9,FALSE) | K94: =VLOOKUP(B94,Real_Estate_Stats!$A$2:$G$215,7,FALSE) -> 23533321 | L94: =D94-K94 -> 3676466679 | M94: 0.37 | N94: 0.05 | O94: =L94*N94 -> 1.8382333e+08 | P94: =O94/(1-M94) -> 2.9178307e+08 | Q94: =P94*M94 -> 1.0795974e+08 | R94: 0.075 | S94: =L94*N94 + (L94*N94*R94*(4+3+2+1+0)/5) -> 211396834 | T94: =S94/(1-M94) -> 3.3555053e+08 | U94: =T94*M94 -> 1.241537e+08
A95: 93 | B95: Marco DeGeorge | C95: $3.6B | D95: 3600000000 | E95: Los Angeles | F95: =VLOOKUP(B95,Raw_Data_Collection!$B$2:$F$215,5,FALSE) -> N | G95: =VLOOKUP(B95,Raw_Data_Collection!$B$2:$J$215,6,FALSE) -> 12982483 | H95: https://www.homes.com/property/517-alta-ave-santa-monica-ca/vq4nqr9enjgpr/ | I95: 2026 | J95: =VLOOKUP(B95,Raw_Data_Collection!$B$2:$J$215,9,FALSE) | K95: =VLOOKUP(B95,Real_Estate_Stats!$A$2:$G$215,7,FALSE) -> 12982483 | L95: =D95-K95 -> 3587017517 | M95: 0.37 | N95: 0.05 | O95: =L95*N95 -> 1.7935088e+08 | P95: =O95/(1-M95) -> 2.8468393e+08 | Q95: =P95*M95 -> 1.0533305e+08 | R95: 0.075 | S95: =L95*N95 + (L95*N95*R95*(4+3+2+1+0)/5) -> 2.0625351e+08 | T95: =S95/(1-M95) -> 3.2738652e+08 | U95: =T95*M95 -> 1.2113301e+08 | X95: Estimated value on homes.com is $4,142,000 - $12,982,483.
A96: 94 | B96: Kavitark Ram Shriram | C96: $3.6B | D96: 3600000000 | E96: Menlo Park | F96: =VLOOKUP(B96,Raw_Data_Collection!$B$2:$F$215,5,FALSE) -> N | G96: =VLOOKUP(B96,Raw_Data_Collection!$B$2:$J$215,6,FALSE) | J96: =VLOOKUP(B96,Raw_Data_Collection!$B$2:$J$215,9,FALSE) | K96: =VLOOKUP(B96,Real_Estate_Stats!$A$2:$G$215,7,FALSE) -> 22897286 | L96: =D96-K96 -> 3577102714 | M96: 0.37 | N96: 0.05 | O96: =L96*N96 -> 1.7885514e+08 | P96: =O96/(1-M96) -> 2.8389704e+08 | Q96: =P96*M96 -> 1.0504191e+08 | R96: 0.075 | S96: =L96*N96 + (L96*N96*R96*(4+3+2+1+0)/5) -> 2.0568341e+08 | T96: =S96/(1-M96) -> 3.264816e+08 | U96: =T96*M96 -> 1.2079819e+08
A97: 95 | B97: Hemant Taneja | C97: $3.6B | D97: 3600000000 | E97: Palo Alto | F97: =VLOOKUP(B97,Raw_Data_Collection!$B$2:$F$215,5,FALSE) -> N | G97: =VLOOKUP(B97,Raw_Data_Collection!$B$2:$J$215,6,FALSE) -> 13784748 | H97: https://www.homes.com/property/13685-la-paloma-rd-los-altos-hills-ca/fmywnqbsb44wd/ | I97: 2026 | J97: =VLOOKUP(B97,Raw_Data_Collection!$B$2:$J$215,9,FALSE) | K97: =VLOOKUP(B97,Real_Estate_Stats!$A$2:$G$215,7,FALSE) -> 13784748 | L97: =D97-K97 -> 3586215252 | M97: 0.37 | N97: 0.05 | O97: =L97*N97 -> 1.7931076e+08 | P97: =O97/(1-M97) -> 2.8462026e+08 | Q97: =P97*M97 -> 1.053095e+08 | R97: 0.075 | S97: =L97*N97 + (L97*N97*R97*(4+3+2+1+0)/5) -> 206207377 | T97: =S97/(1-M97) -> 3.273133e+08 | U97: =T97*M97 -> 1.2110592e+08 | X97: Estimated value on homes.com is $9,271,000 - $13,784,748.
A98: 96 | B98: Richard Peery | C98: $3.5B | D98: 3500000000 | E98: Palo Alto | F98: =VLOOKUP(B98,Raw_Data_Collection!$B$2:$F$215,5,FALSE) -> N | G98: =VLOOKUP(B98,Raw_Data_Collection!$B$2:$J$215,6,FALSE) | J98: =VLOOKUP(B98,Raw_Data_Collection!$B$2:$J$215,9,FALSE) | K98: =VLOOKUP(B98,Real_Estate_Stats!$A$2:$G$215,7,FALSE) -> 22261250 | L98: =D98-K98 -> 3477738750 | M98: 0.37 | N98: 0.05 | O98: =L98*N98 -> 1.7388694e+08 | P98: =O98/(1-M98) -> 2.7601101e+08 | Q98: =P98*M98 -> 1.0212407e+08 | R98: 0.075 | S98: =L98*N98 + (L98*N98*R98*(4+3+2+1+0)/5) -> 1.9996998e+08 | T98: =S98/(1-M98) -> 3.1741266e+08 | U98: =T98*M98 -> 1.1744269e+08
A99: 97 | B99: Brian Acton | C99: $3.5B | D99: 3500000000 | E99: Palo Alto | F99: =VLOOKUP(B99,Raw_Data_Collection!$B$2:$F$215,5,FALSE) -> N | G99: =VLOOKUP(B99,Raw_Data_Collection!$B$2:$J$215,6,FALSE) -> 86000000 | H99: https://www.yahoo.com/entertainment/whatsapp-co-founder-brian-acton-174840726.html | I99: 2019 | J99: =VLOOKUP(B99,Raw_Data_Collection!$B$2:$J$215,9,FALSE) | K99: =VLOOKUP(B99,Real_Estate_Stats!$A$2:$G$215,7,FALSE) -> 86000000 | L99: =D99-K99 -> 3414000000 | M99: 0.37 | N99: 0.05 | O99: =L99*N99 -> 170700000 | P99: =O99/(1-M99) -> 270952381 | Q99: =P99*M99 -> 100252381 | R99: 0.075 | S99: =L99*N99 + (L99*N99*R99*(4+3+2+1+0)/5) -> 196305000 | T99: =S99/(1-M99) -> 3.1159524e+08 | U99: =T99*M99 -> 1.1529024e+08 | X99: Acton's compound consists of 7 Palo Alto houses.
A100: 98 | B100: Travis Kalanick | C100: $3.5B | D100: 3500000000 | E100: Los Angeles | F100: =VLOOKUP(B100,Raw_Data_Collection!$B$2:$F$215,5,FALSE) -> N | G100: =VLOOKUP(B100,Raw_Data_Collection!$B$2:$J$215,6,FALSE) -> 43300000 | H100: https://therealdeal.com/la/2020/05/09/uber-buy-travis-kalanick-behind-43m-bel-air-purchase/ | I100: 2020 | J100: =VLOOKUP(B100,Raw_Data_Collection!$B$2:$J$215,9,FALSE) | K100: =VLOOKUP(B100,Real_Estate_Stats!$A$2:$G$215,7,FALSE) -> 43300000 | L100: =D100-K100 -> 3456700000 | M100: 0.37 | N100: 0.05 | O100: =L100*N100 -> 172835000 | P100: =O100/(1-M100) -> 2.7434127e+08 | Q100: =P100*M100 -> 1.0150627e+08 | R100: 0.075 | S100: =L100*N100 + (L100*N100*R100*(4+3+2+1+0)/5) -> 198760250 | T100: =S100/(1-M100) -> 3.1549246e+08 | U100: =T100*M100 -> 1.1673221e+08 | Y100: https://www.forbes.com/sites/chasewithorn/2026/01/15/los-angeles-billionaire-moves-to-nevada-after-california-threatens-to-tax-wealth/
...

Sheet Real_Estate_Stats
A1: Name | B1: Net Worth Expanded | C1: House Price | D1: Total Residential Real Estate | E1: Real Estate Holdings | F1: % of Net Worth | G1: Adjusted TRRE | H1: Billionaires w/ Identified Real Estate | I1: Using Primary Residence Only | J1: Using Total Reported
A2: Larry Page | B2: 256200000000 | C2: =VLOOKUP(A2,Calculations!$B$3:$K$216,10,FALSE) -> 101500000 | E2: 101500000 | F2: =IF(E2="","",E2/B2) -> 0.00039617486 | G2: =IF(F2="",B2*Summary!$C$22,E2) -> 101500000 | H2: =IF(E2>0,1,0) -> 1 | I2: =IF(AND(C2>0, D2=0), 1, 0) -> 1 | J2: =IF(D2>0,1,0) -> 0
A3: Larry Ellison | B3: 246100000000 | C3: 45000000 | E3: 45000000 | F3: =IF(E3="","",E3/B3) -> 0.0001828525 | G3: =IF(F3="",B3*Summary!$C$22,E3) -> 45000000 | H3: =IF(E3>0,1,0) -> 1 | I3: =IF(AND(C3>0, D3=0), 1, 0) -> 1 | J3: =IF(D3>0,1,0) -> 0
A4: Sergey Brin | B4: 236400000000 | C4: 35000000 | E4: 35000000 | F4: =IF(E4="","",E4/B4) -> 0.00014805415 | G4: =IF(F4="",B4*Summary!$C$22,E4) -> 35000000 | H4: =IF(E4>0,1,0) -> 1 | I4: =IF(AND(C4>0, D4=0), 1, 0) -> 1 | J4: =IF(D4>0,1,0) -> 0
A5: Mark Zuckerberg | B5: 225100000000 | C5: 112000000 | D5: 300000000 | E5: 300000000 | F5: =IF(E5="","",E5/B5) -> 0.001332741 | G5: =IF(F5="",B5*Summary!$C$22,E5) -> 300000000 | H5: =IF(E5>0,1,0) -> 1 | I5: =IF(AND(C5>0, D5=0), 1, 0) -> 0 | J5: =IF(D5>0,1,0) -> 1
A6: Jensen Huang | B6: 162600000000 | C6: 6900000 | D6: 52400000 | E6: 52400000 | F6: =IF(E6="","",E6/B6) -> 0.00032226322 | G6: =IF(F6="",B6*Summary!$C$22,E6) -> 52400000 | H6: =IF(E6>0,1,0) -> 1 | I6: =IF(AND(C6>0, D6=0), 1, 0) -> 0 | J6: =IF(D6>0,1,0) -> 1
A7: Eric Schmidt | B7: 35600000000 | C7: 110000000 | D7: 600000000 | E7: 600000000 | F7: =IF(E7="","",E7/B7) -> 0.016853933 | G7: =IF(F7="",B7*Summary!$C$22,E7) -> 600000000 | H7: =IF(E7>0,1,0) -> 1 | I7: =IF(AND(C7>0, D7=0), 1, 0) -> 0 | J7: =IF(D7>0,1,0) -> 1
A8: Henry Samueli | B8: 32000000000 | C8: 20150000 | D8: 20150000 | E8: 20150000 | F8: =IF(E8="","",E8/B8) -> 0.0006296875 | G8: =IF(F8="",B8*Summary!$C$22,E8) -> 20150000 | H8: =IF(E8>0,1,0) -> 1 | I8: =IF(AND(C8>0, D8=0), 1, 0) -> 0 | J8: =IF(D8>0,1,0) -> 1
A9: Peter Thiel | B9: 26700000000 | C9: 11500000 | D9: 77200000 | E9: 77200000 | F9: =IF(E9="","",E9/B9) -> 0.0028913858 | G9: =IF(F9="",B9*Summary!$C$22,E9) -> 77200000 | H9: =IF(E9>0,1,0) -> 1 | I9: =IF(AND(C9>0, D9=0), 1, 0) -> 0 | J9: =IF(D9>0,1,0) -> 1
A10: Robert Pera | B10: 25500000000 | C10: 21550000 | E10: 21550000 | F10: =IF(E10="","",E10/B10) -> 0.00084509804 | G10: =IF(F10="",B10*Summary!$C$22,E10) -> 21550000 | H10: =IF(E10>0,1,0) -> 1 | I10: =IF(AND(C10>0, D10=0), 1, 0) -> 1 | J10: =IF(D10>0,1,0) -> 0
A11: Adam Foroughi | B11: 25000000000 | F11: =IF(E11="","",E11/B11) | G11: =IF(F11="",B11*Summary!$C$22,E11) -> 1.5900893e+08 | H11: =IF(E11>0,1,0) -> 0 | I11: =IF(AND(C11>0, D11=0), 1, 0) -> 0 | J11: =IF(D11>0,1,0) -> 0
A12: Henry Nicholas III | B12: 21900000000 | C12: 19777777 | D12: 19777777 | E12: 19777777 | F12: =IF(E12="","",E12/B12) -> 0.00090309484 | G12: =IF(F12="",B12*Summary!$C$22,E12) -> 19777777 | H12: =IF(E12>0,1,0) -> 1 | I12: =IF(AND(C12>0, D12=0), 1, 0) -> 0 | J12: =IF(D12>0,1,0) -> 1
A13: John Doerr | B13: 20000000000 | F13: =IF(E13="","",E13/B13) | G13: =IF(F13="",B13*Summary!$C$22,E13) -> 1.2720714e+08 | H13: =IF(E13>0,1,0) -> 0 | I13: =IF(AND(C13>0, D13=0), 1, 0) -> 0 | J13: =IF(D13>0,1,0) -> 0
A14: Donald Bren | B14: 19200000000 | F14: =IF(E14="","",E14/B14) | G14: =IF(F14="",B14*Summary!$C$22,E14) -> 1.2211886e+08 | H14: =IF(E14>0,1,0) -> 0 | I14: =IF(AND(C14>0, D14=0), 1, 0) -> 0 | J14: =IF(D14>0,1,0) -> 0
A15: Eric Smidt | B15: 17900000000 | C15: 54000000 | E15: 54000000 | F15: =IF(E15="","",E15/B15) -> 0.0030167598 | G15: =IF(F15="",B15*Summary!$C$22,E15) -> 54000000 | H15: =IF(E15>0,1,0) -> 1 | I15: =IF(AND(C15>0, D15=0), 1, 0) -> 1 | J15: =IF(D15>0,1,0) -> 0
A16: John Tu | B16: 17500000000 | C16: 7250000 | E16: 7250000 | F16: =IF(E16="","",E16/B16) -> 0.00041428571 | G16: =IF(F16="",B16*Summary!$C$22,E16) -> 7250000 | H16: =IF(E16>0,1,0) -> 1 | I16: =IF(AND(C16>0, D16=0), 1, 0) -> 1 | J16: =IF(D16>0,1,0) -> 0
A17: David Sun | B17: 17500000000 | F17: =IF(E17="","",E17/B17) | G17: =IF(F17="",B17*Summary!$C$22,E17) -> 111306250 | H17: =IF(E17>0,1,0) -> 0 | I17: =IF(AND(C17>0, D17=0), 1, 0) -> 0 | J17: =IF(D17>0,1,0) -> 0
A18: Jan Koum | B18: 17100000000 | C18: 187000000 | D18: 400000000 | E18: 400000000 | F18: =IF(E18="","",E18/B18) -> 0.023391813 | G18: =IF(F18="",B18*Summary!$C$22,E18) -> 400000000 | H18: =IF(E18>0,1,0) -> 1 | I18: =IF(AND(C18>0, D18=0), 1, 0) -> 0 | J18: =IF(D18>0,1,0) -> 1
A19: George Roberts | B19: 15900000000 | C19: 29084160 | E19: 29084160 | F19: =IF(E19="","",E19/B19) -> 0.0018291925 | G19: =IF(F19="",B19*Summary!$C$22,E19) -> 29084160 | H19: =IF(E19>0,1,0) -> 1 | I19: =IF(AND(C19>0, D19=0), 1, 0) -> 1 | J19: =IF(D19>0,1,0) -> 0
A20: Laurene Powell Jobs | B20: 14000000000 | C20: 70000000 | D20: 242000000 | E20: 242000000 | F20: =IF(E20="","",E20/B20) -> 0.017285714 | G20: =IF(F20="",B20*Summary!$C$22,E20) -> 242000000 | H20: =IF(E20>0,1,0) -> 1 | I20: =IF(AND(C20>0, D20=0), 1, 0) -> 0 | J20: =IF(D20>0,1,0) -> 1
A21: Jack Dangermond | B21: 13800000000 | F21: =IF(E21="","",E21/B21) | G21: =IF(F21="",B21*Summary!$C$22,E21) -> 87772929 | H21: =IF(E21>0,1,0) -> 0 | I21: =IF(AND(C21>0, D21=0), 1, 0) -> 0 | J21: =IF(D21>0,1,0) -> 0
A22: Antony Ressler | B22: 13100000000 | C22: 60000000 | D22: 100000000 | E22: 100000000 | F22: =IF(E22="","",E22/B22) -> 0.0076335878 | G22: =IF(F22="",B22*Summary!$C$22,E22) -> 100000000 | H22: =IF(E22>0,1,0) -> 1 | I22: =IF(AND(C22>0, D22=0), 1, 0) -> 0 | J22: =IF(D22>0,1,0) -> 1
A23: Vinod Khosla | B23: 12500000000 | F23: =IF(E23="","",E23/B23) | G23: =IF(F23="",B23*Summary!$C$22,E23) -> 79504464 | H23: =IF(E23>0,1,0) -> 0 | I23: =IF(AND(C23>0, D23=0), 1, 0) -> 0 | J23: =IF(D23>0,1,0) -> 0
A24: Riley Bechtel | B24: 11600000000 | C24: 63300000 | D24: 86100000 | E24: 86100000 | F24: =IF(E24="","",E24/B24) -> 0.0074224138 | G24: =IF(F24="",B24*Summary!$C$22,E24) -> 86100000 | H24: =IF(E24>0,1,0) -> 1 | I24: =IF(AND(C24>0, D24=0), 1, 0) -> 0 | J24: =IF(D24>0,1,0) -> 1
A25: Dustin Moskovitz | B25: 11200000000 | C25: 800000 | E25: 800000 | F25: =IF(E25="","",E25/B25) -> 7.1428571e-05 | G25: =IF(F25="",B25*Summary!$C$22,E25) -> 800000 | H25: =IF(E25>0,1,0) -> 1 | I25: =IF(AND(C25>0, D25=0), 1, 0) -> 1 | J25: =IF(D25>0,1,0) -> 0
A26: Douglas Leone | B26: 10700000000 | C26: 10000000 | D26: 80000000 | E26: 80000000 | F26: =IF(E26="","",E26/B26) -> 0.0074766355 | G26: =IF(F26="",B26*Summary!$C$22,E26) -> 80000000 | H26: =IF(E26>0,1,0) -> 1 | I26: =IF(AND(C26>0, D26=0), 1, 0) -> 0 | J26: =IF(D26>0,1,0) -> 1
A27: Chris Larsen | B27: 10200000000 | C27: 13500000 | D27: 13500000 | E27: 13500000 | F27: =IF(E27="","",E27/B27) -> 0.0013235294 | G27: =IF(F27="",B27*Summary!$C$22,E27) -> 13500000 | H27: =IF(E27>0,1,0) -> 1 | I27: =IF(AND(C27>0, D27=0), 1, 0) -> 0 | J27: =IF(D27>0,1,0) -> 1
A28: Brian Armstrong | B28: 10100000000 | C28: 133000000 | D28: 133000000 | E28: 133000000 | F28: =IF(E28="","",E28/B28) -> 0.013168317 | G28: =IF(F28="",B28*Summary!$C$22,E28) -> 133000000 | H28: =IF(E28>0,1,0) -> 1 | I28: =IF(AND(C28>0, D28=0), 1, 0) -> 0 | J28: =IF(D28>0,1,0) -> 1
A29: Marijke Mars | B29: 10000000000 | F29: =IF(E29="","",E29/B29) | G29: =IF(F29="",B29*Summary!$C$22,E29) -> 63603571 | H29: =IF(E29>0,1,0) -> 0 | I29: =IF(AND(C29>0, D29=0), 1, 0) -> 0 | J29: =IF(D29>0,1,0) -> 0
A30: Tom Gores | B30: 10000000000 | C30: 100000000 | D30: 138000000 | E30: 138000000 | F30: =IF(E30="","",E30/B30) -> 0.0138 | G30: =IF(F30="",B30*Summary!$C$22,E30) -> 138000000 | H30: =IF(E30>0,1,0) -> 1 | I30: =IF(AND(C30>0, D30=0), 1, 0) -> 0 | J30: =IF(D30>0,1,0) -> 1
A31: Andrew Karam | B31: 9800000000 | F31: =IF(E31="","",E31/B31) | G31: =IF(F31="",B31*Summary!$C$22,E31) -> 62331500 | H31: =IF(E31>0,1,0) -> 0 | I31: =IF(AND(C31>0, D31=0), 1, 0) -> 0 | J31: =IF(D31>0,1,0) -> 0
A32: Brian Chesky | B32: 9600000000 | F32: =IF(E32="","",E32/B32) | G32: =IF(F32="",B32*Summary!$C$22,E32) -> 61059429 | H32: =IF(E32>0,1,0) -> 0 | I32: =IF(AND(C32>0, D32=0), 1, 0) -> 0 | J32: =IF(D32>0,1,0) -> 0
A33: Marc Benioff | B33: 9300000000 | C33: 18000000 | E33: 18000000 | F33: =IF(E33="","",E33/B33) -> 0.0019354839 | G33: =IF(F33="",B33*Summary!$C$22,E33) -> 18000000 | H33: =IF(E33>0,1,0) -> 1 | I33: =IF(AND(C33>0, D33=0), 1, 0) -> 1 | J33: =IF(D33>0,1,0) -> 0
A34: David Geffen | B34: 9200000000 | C34: 68000000 | D34: 132000000 | E34: 132000000 | F34: =IF(E34="","",E34/B34) -> 0.014347826 | G34: =IF(F34="",B34*Summary!$C$22,E34) -> 132000000 | H34: =IF(E34>0,1,0) -> 1 | I34: =IF(AND(C34>0, D34=0), 1, 0) -> 0 | J34: =IF(D34>0,1,0) -> 1
A35: Nathan Blecharczyk | B35: 9100000000 | F35: =IF(E35="","",E35/B35) | G35: =IF(F35="",B35*Summary!$C$22,E35) -> 57879250 | H35: =IF(E35>0,1,0) -> 0 | I35: =IF(AND(C35>0, D35=0), 1, 0) -> 0 | J35: =IF(D35>0,1,0) -> 0
A36: Lynsi Snyder | B36: 8600000000 | F36: =IF(E36="","",E36/B36) | G36: =IF(F36="",B36*Summary!$C$22,E36) -> 54699071 | H36: =IF(E36>0,1,0) -> 0 | I36: =IF(AND(C36>0, D36=0), 1, 0) -> 0 | J36: =IF(D36>0,1,0) -> 0
A37: Steven Rales | B37: 8600000000 | F37: =IF(E37="","",E37/B37) | G37: =IF(F37="",B37*Summary!$C$22,E37) -> 54699071 | H37: =IF(E37>0,1,0) -> 0 | I37: =IF(AND(C37>0, D37=0), 1, 0) -> 0 | J37: =IF(D37>0,1,0) -> 0
A38: Don Hankey | B38: 8100000000 | C38: 10659988 | D38: 51300000 | E38: 51300000 | F38: =IF(E38="","",E38/B38) -> 0.0063333333 | G38: =IF(F38="",B38*Summary!$C$22,E38) -> 51300000 | H38: =IF(E38>0,1,0) -> 1 | I38: =IF(AND(C38>0, D38=0), 1, 0) -> 0 | J38: =IF(D38>0,1,0) -> 1
A39: Tench Coxe | B39: 7800000000 | C39: 8683775 | D39: 8683775 | E39: 8683775 | F39: =IF(E39="","",E39/B39) -> 0.0011133045 | G39: =IF(F39="",B39*Summary!$C$22,E39) -> 8683775 | H39: =IF(E39>0,1,0) -> 1 | I39: =IF(AND(C39>0, D39=0), 1, 0) -> 0 | J39: =IF(D39>0,1,0) -> 1
A40: Michael Moritz | B40: 7700000000 | C40: 10600000 | D40: 10600000 | E40: 10600000 | F40: =IF(E40="","",E40/B40) -> 0.0013766234 | G40: =IF(F40="",B40*Summary!$C$22,E40) -> 10600000 | H40: =IF(E40>0,1,0) -> 1 | I40: =IF(AND(C40>0, D40=0), 1, 0) -> 0 | J40: =IF(D40>0,1,0) -> 1
A41: Edward Roski Jr | B41: 7600000000 | C41: 8107000 | D41: 8107000 | E41: 8107000 | F41: =IF(E41="","",E41/B41) -> 0.0010667105 | G41: =IF(F41="",B41*Summary!$C$22,E41) -> 8107000 | H41: =IF(E41>0,1,0) -> 1 | I41: =IF(AND(C41>0, D41=0), 1, 0) -> 0 | J41: =IF(D41>0,1,0) -> 1
A42: Michael Milken | B42: 7400000000 | C42: 102000000 | D42: 179750000 | E42: 179750000 | F42: =IF(E42="","",E42/B42) -> 0.024290541 | G42: =IF(F42="",B42*Summary!$C$22,E42) -> 179750000 | H42: =IF(E42>0,1,0) -> 1 | I42: =IF(AND(C42>0, D42=0), 1, 0) -> 0 | J42: =IF(D42>0,1,0) -> 1
A43: Steven Spielberg | B43: 7000000000 | C43: 250000000 | D43: 250000000 | E43: 250000000 | F43: =IF(E43="","",E43/B43) -> 0.035714286 | G43: =IF(F43="",B43*Summary!$C$22,E43) -> 250000000 | H43: =IF(E43>0,1,0) -> 1 | I43: =IF(AND(C43>0, D43=0), 1, 0) -> 0 | J43: =IF(D43>0,1,0) -> 1
A44: Edythe Broad | B44: 6900000000 | F44: =IF(E44="","",E44/B44) | G44: =IF(F44="",B44*Summary!$C$22,E44) -> 43886464 | H44: =IF(E44>0,1,0) -> 0 | I44: =IF(AND(C44>0, D44=0), 1, 0) -> 0 | J44: =IF(D44>0,1,0) -> 0
A45: Scott Cook | B45: 6900000000 | C45: 15830193 | D45: 15830193 | E45: 15830193 | F45: =IF(E45="","",E45/B45) -> 0.0022942309 | G45: =IF(F45="",B45*Summary!$C$22,E45) -> 15830193 | H45: =IF(E45>0,1,0) -> 1 | I45: =IF(AND(C45>0, D45=0), 1, 0) -> 0 | J45: =IF(D45>0,1,0) -> 1
A46: Baiju Bhatt | B46: 6700000000 | F46: =IF(E46="","",E46/B46) | G46: =IF(F46="",B46*Summary!$C$22,E46) -> 42614393 | H46: =IF(E46>0,1,0) -> 0 | I46: =IF(AND(C46>0, D46=0), 1, 0) -> 0 | J46: =IF(D46>0,1,0) -> 0
A47: Vlad Tenev | B47: 6400000000 | F47: =IF(E47="","",E47/B47) | G47: =IF(F47="",B47*Summary!$C$22,E47) -> 40706286 | H47: =IF(E47>0,1,0) -> 0 | I47: =IF(AND(C47>0, D47=0), 1, 0) -> 0 | J47: =IF(D47>0,1,0) -> 0
A48: John A. Sobrato | B48: 6400000000 | F48: =IF(E48="","",E48/B48) | G48: =IF(F48="",B48*Summary!$C$22,E48) -> 40706286 | H48: =IF(E48>0,1,0) -> 0 | I48: =IF(AND(C48>0, D48=0), 1, 0) -> 0 | J48: =IF(D48>0,1,0) -> 0
A49: Stephen Cohen | B49: 6300000000 | C49: 1031715 | E49: 1031715 | F49: =IF(E49="","",E49/B49) -> 0.00016376429 | G49: =IF(F49="",B49*Summary!$C$22,E49) -> 1031715 | H49: =IF(E49>0,1,0) -> 1 | I49: =IF(AND(C49>0, D49=0), 1, 0) -> 1 | J49: =IF(D49>0,1,0) -> 0
A50: Rick Caruso | B50: 5900000000 | C50: 80000000 | D50: 86500000 | E50: 86500000 | F50: =IF(E50="","",E50/B50) -> 0.014661017 | G50: =IF(F50="",B50*Summary!$C$22,E50) -> 86500000 | H50: =IF(E50>0,1,0) -> 1 | I50: =IF(AND(C50>0, D50=0), 1, 0) -> 0 | J50: =IF(D50>0,1,0) -> 1
A51: Ken Xie | B51: 5700000000 | D51: 14340561 | E51: 14340561 | F51: =IF(E51="","",E51/B51) -> 0.0025158879 | G51: =IF(F51="",B51*Summary!$C$22,E51) -> 14340561 | H51: =IF(E51>0,1,0) -> 1 | I51: =IF(AND(C51>0, D51=0), 1, 0) -> 0 | J51: =IF(D51>0,1,0) -> 1
A52: Jayshree Ullal | B52: 5600000000 | C52: 877000 | D52: 7862000 | E52: 7862000 | F52: =IF(E52="","",E52/B52) -> 0.0014039286 | G52: =IF(F52="",B52*Summary!$C$22,E52) -> 7862000 | H52: =IF(E52>0,1,0) -> 1 | I52: =IF(AND(C52>0, D52=0), 1, 0) -> 0 | J52: =IF(D52>0,1,0) -> 1
A53: Archie Aldis Emmerson | B53: 5600000000 | F53: =IF(E53="","",E53/B53) | G53: =IF(F53="",B53*Summary!$C$22,E53) -> 35618000 | H53: =IF(E53>0,1,0) -> 0 | I53: =IF(AND(C53>0, D53=0), 1, 0) -> 0 | J53: =IF(D53>0,1,0) -> 0
A54: Romesh T. Wadhwani | B54: 5500000000 | F54: =IF(E54="","",E54/B54) | G54: =IF(F54="",B54*Summary!$C$22,E54) -> 34981964 | H54: =IF(E54>0,1,0) -> 0 | I54: =IF(AND(C54>0, D54=0), 1, 0) -> 0 | J54: =IF(D54>0,1,0) -> 0
A55: Neal Blue | B55: 5400000000 | F55: =IF(E55="","",E55/B55) | G55: =IF(F55="",B55*Summary!$C$22,E55) -> 34345929 | H55: =IF(E55>0,1,0) -> 0 | I55: =IF(AND(C55>0, D55=0), 1, 0) -> 0 | J55: =IF(D55>0,1,0) -> 0
A56: Gordon Getty | B56: 5400000000 | C56: 29608760 | D56: 29608760 | E56: 29608760 | F56: =IF(E56="","",E56/B56) -> 0.0054831037 | G56: =IF(F56="",B56*Summary!$C$22,E56) -> 29608760 | H56: =IF(E56>0,1,0) -> 1 | I56: =IF(AND(C56>0, D56=0), 1, 0) -> 0 | J56: =IF(D56>0,1,0) -> 1
A57: Patrick Soon-Shiong | B57: 5400000000 | C57: 30000000 | D57: 162500000 | E57: 162500000 | F57: =IF(E57="","",E57/B57) -> 0.030092593 | G57: =IF(F57="",B57*Summary!$C$22,E57) -> 162500000 | H57: =IF(E57>0,1,0) -> 1 | I57: =IF(AND(C57>0, D57=0), 1, 0) -> 0 | J57: =IF(D57>0,1,0) -> 1
A58: Jean (Gigi) Pritzker | B58: 5400000000 | F58: =IF(E58="","",E58/B58) | G58: =IF(F58="",B58*Summary!$C$22,E58) -> 34345929 | H58: =IF(E58>0,1,0) -> 0 | I58: =IF(AND(C58>0, D58=0), 1, 0) -> 0 | J58: =IF(D58>0,1,0) -> 0
A59: Stewart Resnick | B59: 5300000000 | C59: 17115689 | D59: 17115689 | E59: 17115689 | F59: =IF(E59="","",E59/B59) -> 0.0032293753 | G59: =IF(F59="",B59*Summary!$C$22,E59) -> 17115689 | H59: =IF(E59>0,1,0) -> 1 | I59: =IF(AND(C59>0, D59=0), 1, 0) -> 0 | J59: =IF(D59>0,1,0) -> 1
A60: Lynda Resnick | B60: 5300000000 | C60: 17115689 | D60: 17115689 | E60: 17115689 | F60: =IF(E60="","",E60/B60) -> 0.0032293753 | G60: =IF(F60="",B60*Summary!$C$22,E60) -> 17115689 | H60: =IF(E60>0,1,0) -> 1 | I60: =IF(AND(C60>0, D60=0), 1, 0) -> 0 | J60: =IF(D60>0,1,0) -> 1
A61: Eduardo Vivas | B61: 5300000000 | F61: =IF(E61="","",E61/B61) | G61: =IF(F61="",B61*Summary!$C$22,E61) -> 33709893 | H61: =IF(E61>0,1,0) -> 0 | I61: =IF(AND(C61>0, D61=0), 1, 0) -> 0 | J61: =IF(D61>0,1,0) -> 0
A62: George Lucas | B62: 5300000000 | C62: 41600000 | D62: 123000000 | E62: 123000000 | F62: =IF(E62="","",E62/B62) -> 0.023207547 | G62: =IF(F62="",B62*Summary!$C$22,E62) -> 123000000 | H62: =IF(E62>0,1,0) -> 1 | I62: =IF(AND(C62>0, D62=0), 1, 0) -> 0 | J62: =IF(D62>0,1,0) -> 1
A63: Reed Hastings | B63: 5100000000 | C63: 1750000 | D63: 3250000 | E63: 3250000 | F63: =IF(E63="","",E63/B63) -> 0.0006372549 | G63: =IF(F63="",B63*Summary!$C$22,E63) -> 3250000 | H63: =IF(E63>0,1,0) -> 1 | I63: =IF(AND(C63>0, D63=0), 1, 0) -> 0 | J63: =IF(D63>0,1,0) -> 1
A64: Eric Yuan | B64: 5100000000 | F64: =IF(E64="","",E64/B64) | G64: =IF(F64="",B64*Summary!$C$22,E64) -> 32437821 | H64: =IF(E64>0,1,0) -> 0 | I64: =IF(AND(C64>0, D64=0), 1, 0) -> 0 | J64: =IF(D64>0,1,0) -> 0
A65: Gwendolyn Sontheim Meyer | B65: 5000000000 | F65: =IF(E65="","",E65/B65) | G65: =IF(F65="",B65*Summary!$C$22,E65) -> 31801786 | H65: =IF(E65>0,1,0) -> 0 | I65: =IF(AND(C65>0, D65=0), 1, 0) -> 0 | J65: =IF(D65>0,1,0) -> 0
A66: Jim Coulter | B66: 5000000000 | F66: =IF(E66="","",E66/B66) | G66: =IF(F66="",B66*Summary!$C$22,E66) -> 31801786 | H66: =IF(E66>0,1,0) -> 0 | I66: =IF(AND(C66>0, D66=0), 1, 0) -> 0 | J66: =IF(D66>0,1,0) -> 0
A67: Jack Dorsey | B67: 4900000000 | C67: 31900000 | D67: 31900000 | E67: 31900000 | F67: =IF(E67="","",E67/B67) -> 0.0065102041 | G67: =IF(F67="",B67*Summary!$C$22,E67) -> 31900000 | H67: =IF(E67>0,1,0) -> 1 | I67: =IF(AND(C67>0, D67=0), 1, 0) -> 0 | J67: =IF(D67>0,1,0) -> 1
A68: David Baszucki | B68: 4900000000 | F68: =IF(E68="","",E68/B68) | G68: =IF(F68="",B68*Summary!$C$22,E68) -> 31165750 | H68: =IF(E68>0,1,0) -> 0 | I68: =IF(AND(C68>0, D68=0), 1, 0) -> 0 | J68: =IF(D68>0,1,0) -> 0
A69: Scott Crabill | B69: 4800000000 | C69: 22222762 | D69: 59322762 | E69: 59322762 | F69: =IF(E69="","",E69/B69) -> 0.012358909 | G69: =IF(F69="",B69*Summary!$C$22,E69) -> 59322762 | H69: =IF(E69>0,1,0) -> 1 | I69: =IF(AND(C69>0, D69=0), 1, 0) -> 0 | J69: =IF(D69>0,1,0) -> 1
A70: Holden Spaht | B70: 4800000000 | C70: 6849000 | D70: 6849000 | E70: 6849000 | F70: =IF(E70="","",E70/B70) -> 0.001426875 | G70: =IF(F70="",B70*Summary!$C$22,E70) -> 6849000 | H70: =IF(E70>0,1,0) -> 1 | I70: =IF(AND(C70>0, D70=0), 1, 0) -> 0 | J70: =IF(D70>0,1,0) -> 1
A71: Seth Boro | B71: 4800000000 | C71: 5884000 | D71: 5884000 | E71: 5884000 | F71: =IF(E71="","",E71/B71) -> 0.0012258333 | G71: =IF(F71="",B71*Summary!$C$22,E71) -> 5884000 | H71: =IF(E71>0,1,0) -> 1 | I71: =IF(AND(C71>0, D71=0), 1, 0) -> 0 | J71: =IF(D71>0,1,0) -> 1
A72: Michael Xie | B72: 4800000000 | C72: 13269963 | D72: 25671792 | E72: 25671792 | F72: =IF(E72="","",E72/B72) -> 0.00534829 | G72: =IF(F72="",B72*Summary!$C$22,E72) -> 25671792 | H72: =IF(E72>0,1,0) -> 1 | I72: =IF(AND(C72>0, D72=0), 1, 0) -> 0 | J72: =IF(D72>0,1,0) -> 1
A73: Dagmar Dolby | B73: 4800000000 | C73: 7809894 | D73: 90000000 | E73: 90000000 | F73: =IF(E73="","",E73/B73) -> 0.01875 | G73: =IF(F73="",B73*Summary!$C$22,E73) -> 90000000 | H73: =IF(E73>0,1,0) -> 1 | I73: =IF(AND(C73>0, D73=0), 1, 0) -> 0 | J73: =IF(D73>0,1,0) -> 1
A74: David Filo | B74: 4500000000 | F74: =IF(E74="","",E74/B74) | G74: =IF(F74="",B74*Summary!$C$22,E74) -> 28621607 | H74: =IF(E74>0,1,0) -> 0 | I74: =IF(AND(C74>0, D74=0), 1, 0) -> 0 | J74: =IF(D74>0,1,0) -> 0
A75: Rupert Johnson Jr | B75: 4400000000 | F75: =IF(E75="","",E75/B75) | G75: =IF(F75="",B75*Summary!$C$22,E75) -> 27985571 | H75: =IF(E75>0,1,0) -> 0 | I75: =IF(AND(C75>0, D75=0), 1, 0) -> 0 | J75: =IF(D75>0,1,0) -> 0
A76: Anthony Pritzker | B76: 4400000000 | C76: 195000000 | D76: 195000000 | E76: 195000000 | F76: =IF(E76="","",E76/B76) -> 0.044318182 | G76: =IF(F76="",B76*Summary!$C$22,E76) -> 195000000 | H76: =IF(E76>0,1,0) -> 1 | I76: =IF(AND(C76>0, D76=0), 1, 0) -> 0 | J76: =IF(D76>0,1,0) -> 1
A77: Rodney Sacks | B77: 4300000000 | F77: =IF(E77="","",E77/B77) | G77: =IF(F77="",B77*Summary!$C$22,E77) -> 27349536 | H77: =IF(E77>0,1,0) -> 0 | I77: =IF(AND(C77>0, D77=0), 1, 0) -> 0 | J77: =IF(D77>0,1,0) -> 0
A78: Donald Sterling | B78: 4300000000 | C78: 11443465 | D78: 29825465 | E78: 29825465 | F78: =IF(E78="","",E78/B78) -> 0.0069361547 | G78: =IF(F78="",B78*Summary!$C$22,E78) -> 29825465 | H78: =IF(E78>0,1,0) -> 1 | I78: =IF(AND(C78>0, D78=0), 1, 0) -> 0 | J78: =IF(D78>0,1,0) -> 1
A79: Sanjit Biswas | B79: 4100000000 | F79: =IF(E79="","",E79/B79) | G79: =IF(F79="",B79*Summary!$C$22,E79) -> 26077464 | H79: =IF(E79>0,1,0) -> 0 | I79: =IF(AND(C79>0, D79=0), 1, 0) -> 0 | J79: =IF(D79>0,1,0) -> 0
A80: Thomas Siebel | B80: 4000000000 | F80: =IF(E80="","",E80/B80) | G80: =IF(F80="",B80*Summary!$C$22,E80) -> 25441429 | H80: =IF(E80>0,1,0) -> 0 | I80: =IF(AND(C80>0, D80=0), 1, 0) -> 0 | J80: =IF(D80>0,1,0) -> 0
A81: John Bicket | B81: 4000000000 | F81: =IF(E81="","",E81/B81) | G81: =IF(F81="",B81*Summary!$C$22,E81) -> 25441429 | H81: =IF(E81>0,1,0) -> 0 | I81: =IF(AND(C81>0, D81=0), 1, 0) -> 0 | J81: =IF(D81>0,1,0) -> 0
A82: José E. Feliciano | B82: 3800000000 | C82: 50000000 | D82: 50000000 | E82: 50000000 | F82: =IF(E82="","",E82/B82) -> 0.013157895 | G82: =IF(F82="",B82*Summary!$C$22,E82) -> 50000000 | H82: =IF(E82>0,1,0) -> 1 | I82: =IF(AND(C82>0, D82=0), 1, 0) -> 0 | J82: =IF(D82>0,1,0) -> 1
A83: Meg Whitman | B83: 3800000000 | C83: 6500000 | D83: 6500000 | E83: 6500000 | F83: =IF(E83="","",E83/B83) -> 0.0017105263 | G83: =IF(F83="",B83*Summary!$C$22,E83) -> 6500000 | H83: =IF(E83>0,1,0) -> 1 | I83: =IF(AND(C83>0, D83=0), 1, 0) -> 0 | J83: =IF(D83>0,1,0) -> 1
A84: Behdad Eghbali | B84: 3800000000 | C84: 21000000 | E84: 21000000 | F84: =IF(E84="","",E84/B84) -> 0.0055263158 | G84: =IF(F84="",B84*Summary!$C$22,E84) -> 21000000 | H84: =IF(E84>0,1,0) -> 1 | I84: =IF(AND(C84>0, D84=0), 1, 0) -> 1 | J84: =IF(D84>0,1,0) -> 0
A85: Peter Gassner | B85: 3800000000 | C85: 1977425 | E85: 1977425 | F85: =IF(E85="","",E85/B85) -> 0.000520375 | G85: =IF(F85="",B85*Summary!$C$22,E85) -> 1977425 | H85: =IF(E85>0,1,0) -> 1 | I85: =IF(AND(C85>0, D85=0), 1, 0) -> 1 | J85: =IF(D85>0,1,0) -> 0
A86: John Fisher | B86: 3700000000 | C86: 29250000 | E86: 29250000 | F86: =IF(E86="","",E86/B86) -> 0.0079054054 | G86: =IF(F86="",B86*Summary!$C$22,E86) -> 29250000 | H86: =IF(E86>0,1,0) -> 1 | I86: =IF(AND(C86>0, D86=0), 1, 0) -> 1 | J86: =IF(D86>0,1,0) -> 0
A87: Danny Harris | B87: 3700000000 | C87: 30000000 | E87: 30000000 | F87: =IF(E87="","",E87/B87) -> 0.0081081081 | G87: =IF(F87="",B87*Summary!$C$22,E87) -> 30000000 | H87: =IF(E87>0,1,0) -> 1 | I87: =IF(AND(C87>0, D87=0), 1, 0) -> 1 | J87: =IF(D87>0,1,0) -> 0
A88: Jared Kaplan | B88: 3700000000 | F88: =IF(E88="","",E88/B88) | G88: =IF(F88="",B88*Summary!$C$22,E88) -> 23533321 | H88: =IF(E88>0,1,0) -> 0 | I88: =IF(AND(C88>0, D88=0), 1, 0) -> 0 | J88: =IF(D88>0,1,0) -> 0
A89: Dario Amodei | B89: 3700000000 | F89: =IF(E89="","",E89/B89) | G89: =IF(F89="",B89*Summary!$C$22,E89) -> 23533321 | H89: =IF(E89>0,1,0) -> 0 | I89: =IF(AND(C89>0, D89=0), 1, 0) -> 0 | J89: =IF(D89>0,1,0) -> 0
A90: Tom Brown | B90: 3700000000 | C90: 2572000 | E90: 2572000 | F90: =IF(E90="","",E90/B90) -> 0.00069513514 | G90: =IF(F90="",B90*Summary!$C$22,E90) -> 2572000 | H90: =IF(E90>0,1,0) -> 1 | I90: =IF(AND(C90>0, D90=0), 1, 0) -> 1 | J90: =IF(D90>0,1,0) -> 0
A91: Jack Clark | B91: 3700000000 | F91: =IF(E91="","",E91/B91) | G91: =IF(F91="",B91*Summary!$C$22,E91) -> 23533321 | H91: =IF(E91>0,1,0) -> 0 | I91: =IF(AND(C91>0, D91=0), 1, 0) -> 0 | J91: =IF(D91>0,1,0) -> 0
A92: Sam McCandlish | B92: 3700000000 | C92: 4831145 | E92: 4831145 | F92: =IF(E92="","",E92/B92) -> 0.0013057149 | G92: =IF(F92="",B92*Summary!$C$22,E92) -> 4831145 | H92: =IF(E92>0,1,0) -> 1 | I92: =IF(AND(C92>0, D92=0), 1, 0) -> 1 | J92: =IF(D92>0,1,0) -> 0
A93: Daniela Amodei | B93: 3700000000 | F93: =IF(E93="","",E93/B93) | G93: =IF(F93="",B93*Summary!$C$22,E93) -> 23533321 | H93: =IF(E93>0,1,0) -> 0 | I93: =IF(AND(C93>0, D93=0), 1, 0) -> 0 | J93: =IF(D93>0,1,0) -> 0
A94: Marco DeGeorge | B94: 3600000000 | C94: 12982483 | E94: 12982483 | F94: =IF(E94="","",E94/B94) -> 0.0036062453 | G94: =IF(F94="",B94*Summary!$C$22,E94) -> 12982483 | H94: =IF(E94>0,1,0) -> 1 | I94: =IF(AND(C94>0, D94=0), 1, 0) -> 1 | J94: =IF(D94>0,1,0) -> 0
A95: Kavitark Ram Shriram | B95: 3600000000 | F95: =IF(E95="","",E95/B95) | G95: =IF(F95="",B95*Summary!$C$22,E95) -> 22897286 | H95: =IF(E95>0,1,0) -> 0 | I95: =IF(AND(C95>0, D95=0), 1, 0) -> 0 | J95: =IF(D95>0,1,0) -> 0
A96: Hemant Taneja | B96: 3600000000 | C96: 13784748 | E96: 13784748 | F96: =IF(E96="","",E96/B96) -> 0.0038290967 | G96: =IF(F96="",B96*Summary!$C$22,E96) -> 13784748 | H96: =IF(E96>0,1,0) -> 1 | I96: =IF(AND(C96>0, D96=0), 1, 0) -> 1 | J96: =IF(D96>0,1,0) -> 0
A97: Richard Peery | B97: 3500000000 | F97: =IF(E97="","",E97/B97) | G97: =IF(F97="",B97*Summary!$C$22,E97) -> 22261250 | H97: =IF(E97>0,1,0) -> 0 | I97: =IF(AND(C97>0, D97=0), 1, 0) -> 0 | J97: =IF(D97>0,1,0) -> 0
A98: Brian Acton | B98: 3500000000 | C98: 86000000 | E98: 86000000 | F98: =IF(E98="","",E98/B98) -> 0.024571429 | G98: =IF(F98="",B98*Summary!$C$22,E98) -> 86000000 | H98: =IF(E98>0,1,0) -> 1 | I98: =IF(AND(C98>0, D98=0), 1, 0) -> 1 | J98: =IF(D98>0,1,0) -> 0
A99: Travis Kalanick | B99: 3500000000 | C99: 43300000 | E99: 43300000 | F99: =IF(E99="","",E99/B99) -> 0.012371429 | G99: =IF(F99="",B99*Summary!$C$22,E99) -> 43300000 | H99: =IF(E99>0,1,0) -> 1 | I99: =IF(AND(C99>0, D99=0), 1, 0) -> 1 | J99: =IF(D99>0,1,0) -> 0
A100: Palmer Luckey | B100: 3500000000 | C100: 12500000 | E100: 12500000 | F100: =IF(E100="","",E100/B100) -> 0.0035714286 | G100: =IF(F100="",B100*Summary!$C$22,E100) -> 12500000 | H100: =IF(E100>0,1,0) -> 1 | I100: =IF(AND(C100>0, D100=0), 1, 0) -> 1 | J100: =IF(D100>0,1,0) -> 0
...

Sheet Summary
B2: Wealth Tax Scenarios | J2: Results (Excl. Cap Gains) | N2: 1000000000
C3: W/o Leavers - Revenue Gains ($B) | G3: Leavers - Revenue Gains ($B)
B4: Scenarios | C4: Wealth Tax | E4: Capital Gains | F4: Total | G4: Wealth Tax | H4: Capital Gains | I4: Total | J4: % Change | K4: Wealth Tax | L4: Implied Semi-Elasticity
B5: 5% Tax | C5: =SUM(Calculations!O3:O216)/$C$8 -> 107.03925 | E5: =SUM(Calculations!Q3:Q216)/C8 -> 62.86432 | F5: =SUM(C5:E5) -> 169.90357 | G5: =SUMIF(Calculations!F3:F215,"N",Calculations!O3:O216)/$C$8 -> 66.70863 | H5: =SUMIF(Calculations!F3:F215,"N",Calculations!Q3:Q216)/$C$8 -> 39.178084 | I5: =SUM(G5:H5) -> 105.88671 | J5: =(C5-G5)/C5 -> 0.37678345 | K5: 0.05 | L5: =J5/K5 -> 7.535669
B6: 1% Per Year | C6: =SUM(Calculations!S3:S216)/C8 -> 123.09513 | E6: =SUM(Calculations!U3:U216)/C8 -> 72.293968 | F6: =SUM(C6:E6) -> 195.3891 | G6: =SUMIF(Calculations!F3:F215,"N",Calculations!S3:S216)/$C$8 -> 76.714925 | H6: =SUMIF(Calculations!F3:F215,"N",Calculations!U3:U216)/$C$8 -> 45.054797 | I6: =SUM(G6:H6) -> 121.76972 | J6: =(C6-G6)/C6 -> 0.37678345 | K6: 0.05 | L6: =J6/K6 -> 7.535669
C8: 1000000000
B9: Alt Scenarios | C9: W/o Leavers - Revenue Gains ($B) | G9: Leavers - Revenue Gains ($B) | J9: % Change | K9: Wealth Tax | L9: Implied Semi-Elasticity
B10: Brülhart | C10: 107.04 | G10: =-1*((J10*C10)-C10) -> 51.80736 | J10: =L10*K10 -> 0.516 | K10: 0.05 | L10: 10.32
B11: 1.25x | C11: 107.04 | G11: =-1*((J11*C11)-C11) -> 40.14 | J11: =L11*K11 -> 0.625 | K11: 0.05 | L11: 12.5
B12: 1.5x | C12: 107.04 | G12: =-1*((J12*C12)-C12) -> 26.76 | J12: =L12*K12 -> 0.75 | K12: 0.05 | L12: 15
B14: Type | C14: Y/N | D14: Count | E14: Tot Adj NW ($b) | F14: Prop
B15: Stayers | C15: N | D15: =COUNTIF(Calculations!$F$3:$F$216,$C15) -> 205 | E15: =SUMIF(Calculations!$F$3:$F$216,$C15,Calculations!$D$3:$D$216)/$N$2 -> 1343.2 | F15: =E16/E17 -> 0.37513956
B16: Leavers | C16: Y | D16: =COUNTIF(Calculations!$F$3:$F$216,$C16) -> 9 | E16: =SUMIF(Calculations!$F$3:$F$216,$C16,Calculations!$D$3:$D$216)/$N$2 -> 806.4 | F16: =E15/E17 -> 0.62486044
C17: Sum | D17: =SUM(D15:D16) -> 214 | E17: =SUM(E15:E16) -> 2149.6 | F17: =SUM(F15:F16) -> 1
B20: Real Estate Stats & Impact
B21: Mean | C21: =average(Real_Estate_Stats!F2:F215) -> 0.011792298
B22: Median | C22: =median(Real_Estate_Stats!F2:F215) -> 0.0063603571
B23: Net Worth Changes
B24: Net Worth Cat | C24: Net Worth Total | D24: Stayers
B25: NW | C25: =SUM(Calculations!D3:D216)/N2 -> 2149.6 | D25: =SUMIF(Calculations!F3:F216,"N",Calculations!D3:D216)/N2 -> 1343.2
B26: NW - TRRE | C26: =SUM(Calculations!L3:L216)/N2 -> 2140.7849 | D26: =SUMIF(Calculations!F3:F216,"N",Calculations!L3:L216)/N2 -> 1335.1662
B27: Diff | C27: =C25-C26 -> 8.815062 | D27: =D25-D26 -> 8.0337562

Sheet Calculations_Preferred
O1: 5% One-Time Tax Scenario | R1: 1% One-Time Tax Scenario
A2: Ranking | B2: Name | C2: Net Worth | D2: Net Worth Expanded | E2: Residence | F2: Moving? (Y/N) | G2: House Price | H2: House Price Source | I2: House Price (Assessed) Year | J2: Total Residential Real Estate | K2: Total Residential Real Estate* | L2: Net Worth - TRRE | M2: Capital Gains Rate | N2: Wealth Tax Rate | O2: 5% Wealth Tax Revenues | P2: Cap Gain Initial Calc (5%) | Q2: 5% Capital Gains Revenues | R2: Interest Rate | S2: 1% Wealth Tax Revenues | T2: Cap Gain Initial Calc (1%) | U2: 1% Capital Gains Revenues | V2: TRRE Price (Assessed) Year(s) | W2: TRRE Source | X2: Notes | Y2: Moving Source
A3: 1 | B3: Larry Page | C3: $256.2B | D3: 256200000000 | E3: Palo Alto | F3: =VLOOKUP(B3,Raw_Data_Collection!$B$2:$F$215,5,FALSE) -> Y | G3: =VLOOKUP(B3,Raw_Data_Collection!$B$2:$J$215,6,FALSE) -> 101500000 | H3: https://elmundomiami.com/economy/larry-page-invests-173-4-million-in-the-miami-real-estate-market/ | I3: 2024 | J3: =VLOOKUP(B3,Raw_Data_Collection!$B$2:$J$215,9,FALSE) | K3: =VLOOKUP(B3,Real_Estate_Stats_Preferred!$A$2:$G$215,7,FALSE) -> 101500000 | L3: =D3-K3 -> 256098500000 | M3: 0.37 | N3: 0.05 | O3: =L3*N3 -> 12804925000 | P3: =O3/(1-M3) -> 20325277778 | Q3: =P3*M3 -> 7520352778 | R3: 0.075 | S3: =L3*N3 + (L3*N3*R3*(4+3+2+1+0)/5) -> 14725663750 | T3: =S3/(1-M3) -> 23374069444 | U3: =T3*M3 -> 8648405694 | X3: Page's primary residence is now a Florida mansion. | Y3: https://www.businessinsider.com/larry-page-leave-california-wealth-billionaire-tax-koop-google-2026-1
A4: 2 | B4: Sergey Brin | C4: $236.4B | D4: 236400000000 | E4: Los Altos | F4: =VLOOKUP(B4,Raw_Data_Collection!$B$2:$F$215,5,FALSE) -> Y | G4: =VLOOKUP(B4,Raw_Data_Collection!$B$2:$J$215,6,FALSE) -> 35000000 | I4: 2025 | J4: =VLOOKUP(B4,Raw_Data_Collection!$B$2:$J$215,9,FALSE) | K4: =VLOOKUP(B4,Real_Estate_Stats_Preferred!$A$2:$G$215,7,FALSE) -> 35000000 | L4: =D4-K4 -> 236365000000 | M4: 0.37 | N4: 0.05 | O4: =L4*N4 -> 11818250000 | P4: =O4/(1-M4) -> 18759126984 | Q4: =P4*M4 -> 6940876984 | R4: 0.075 | S4: =L4*N4 + (L4*N4*R4*(4+3+2+1+0)/5) -> 13590987500 | T4: =S4/(1-M4) -> 21572996032 | U4: =T4*M4 -> 7982008532 | Y4: https://www.aol.com/news/google-cofounders-sergey-brin-larry-195211174.html
A5: 3 | B5: Mark Zuckerberg | C5: $225.1B | D5: 225100000000 | E5: Palo Alto | F5: =VLOOKUP(B5,Raw_Data_Collection!$B$2:$F$215,5,FALSE) -> N | G5: =VLOOKUP(B5,Raw_Data_Collection!$B$2:$J$215,6,FALSE) -> 112000000 | H5: https://www.realtor.com/news/celebrity-real-estate/mark-zuckerberg-palo-alto-home-fury-neighbors/ | I5: 2025 | J5: =VLOOKUP(B5,Raw_Data_Collection!$B$2:$J$215,9,FALSE) -> 300000000 | K5: =VLOOKUP(B5,Real_Estate_Stats_Preferred!$A$2:$G$215,7,FALSE) -> 300000000 | L5: =D5-K5 -> 224800000000 | M5: 0.37 | N5: 0.05 | O5: =L5*N5 -> 11240000000 | P5: =O5/(1-M5) -> 17841269841 | Q5: =P5*M5 -> 6601269841 | R5: 0.075 | S5: =L5*N5 + (L5*N5*R5*(4+3+2+1+0)/5) -> 12926000000 | T5: =S5/(1-M5) -> 20517460317 | U5: =T5*M5 -> 7591460317 | V5: 2011-2025 | W5: https://robbreport.com/shelter/celebrity-homes/mark-zuckerberg-property-portfolio-1236712447/ | X5: Zuckerberg's compund consists of 11 different properties ranging from $5 million to $15 million.
A6: 4 | B6: Jensen Huang | C6: $162.6B | D6: 162600000000 | E6: Los Altos | F6: =VLOOKUP(B6,Raw_Data_Collection!$B$2:$F$215,5,FALSE) -> N | G6: =VLOOKUP(B6,Raw_Data_Collection!$B$2:$J$215,6,FALSE) -> 6900000 | H6: https://www.yahoo.com/lifestyle/articles/3-most-expensive-properties-nvidia-115457861.html | I6: 2025 | J6: =VLOOKUP(B6,Raw_Data_Collection!$B$2:$J$215,9,FALSE) -> 52400000 | K6: =VLOOKUP(B6,Real_Estate_Stats_Preferred!$A$2:$G$215,7,FALSE) -> 52400000 | L6: =D6-K6 -> 162547600000 | M6: 0.37 | N6: 0.05 | O6: =L6*N6 -> 8127380000 | P6: =O6/(1-M6) -> 12900603175 | Q6: =P6*M6 -> 4773223175 | R6: 0.075 | S6: =L6*N6 + (L6*N6*R6*(4+3+2+1+0)/5) -> 9346487000 | T6: =S6/(1-M6) -> 14835693651 | U6: =T6*M6 -> 5489206651 | V6: 2004 | W6: https://www.foxbusiness.com/lifestyle/nvidias-ceo-extensive-rich-real-estate-portfolio | X6: Huang also has a $38 million San Francisco Mansion. | Y6: https://uk.finance.yahoo.com/news/nvidia-jensen-huang-perfectly-fine-170800688.html
A7: 5 | B7: Eric Schmidt | C7: $35.6B | D7: 35600000000 | E7: Los Angeles | F7: =VLOOKUP(B7,Raw_Data_Collection!$B$2:$F$215,5,FALSE) -> N | G7: =VLOOKUP(B7,Raw_Data_Collection!$B$2:$J$215,6,FALSE) -> 110000000 | I7: 2025 | J7: =VLOOKUP(B7,Raw_Data_Collection!$B$2:$J$215,9,FALSE) -> 600000000 | K7: =VLOOKUP(B7,Real_Estate_Stats_Preferred!$A$2:$G$215,7,FALSE) -> 600000000 | L7: =D7-K7 -> 35000000000 | M7: 0.37 | N7: 0.05 | O7: =L7*N7 -> 1750000000 | P7: =O7/(1-M7) -> 2777777778 | Q7: =P7*M7 -> 1027777778 | R7: 0.075 | S7: =L7*N7 + (L7*N7*R7*(4+3+2+1+0)/5) -> 2012500000 | T7: =S7/(1-M7) -> 3194444444 | U7: =T7*M7 -> 1181944444 | V7: 2025 | W7: https://robbreport.com/shelter/celebrity-homes/lists/eric-schmidt-property-portfolio-1236832435/ | X7: Schmidt also bought a $30.8 million estate in Montecito in 2020.
A8: 6 | B8: Henry Samueli | C8: $32B | D8: 32000000000 | E8: Newport Beach | F8: =VLOOKUP(B8,Raw_Data_Collection!$B$2:$F$215,5,FALSE) -> N | G8: =VLOOKUP(B8,Raw_Data_Collection!$B$2:$J$215,6,FALSE) -> 20150000 | H8: https://www.urbansplatter.com/2024/06/henry-samueli-house-the-california-dwelling/ | I8: 2024 | J8: =VLOOKUP(B8,Raw_Data_Collection!$B$2:$J$215,9,FALSE) -> 20150000 | K8: =VLOOKUP(B8,Real_Estate_Stats_Preferred!$A$2:$G$215,7,FALSE) -> 20150000 | L8: =D8-K8 -> 31979850000 | M8: 0.37 | N8: 0.05 | O8: =L8*N8 -> 1598992500 | P8: =O8/(1-M8) -> 2538083333 | Q8: =P8*M8 -> 9.3909083e+08 | R8: 0.075 | S8: =L8*N8 + (L8*N8*R8*(4+3+2+1+0)/5) -> 1838841375 | T8: =S8/(1-M8) -> 2918795833 | U8: =T8*M8 -> 1079954458 | V8: 2024 | W8: https://www.urbansplatter.com/2024/06/henry-samueli-house-the-california-dwelling/ | X8: Samueli only seems to have one residence.
A9: 7 | B9: Peter Thiel | C9: $26.7B | D9: 26700000000 | E9: Los Angeles | F9: =VLOOKUP(B9,Raw_Data_Collection!$B$2:$F$215,5,FALSE) -> Y | G9: =VLOOKUP(B9,Raw_Data_Collection!$B$2:$J$215,6,FALSE) -> 11500000 | H9: https://labusinessjournal.com/technology/billionaire-peter-thiel-moving-los-angeles/ | I9: 2018 | J9: =VLOOKUP(B9,Raw_Data_Collection!$B$2:$J$215,9,FALSE) -> 77200000 | K9: =VLOOKUP(B9,Real_Estate_Stats_Preferred!$A$2:$G$215,7,FALSE) -> 77200000 | L9: =D9-K9 -> 26622800000 | M9: 0.37 | N9: 0.05 | O9: =L9*N9 -> 1331140000 | P9: =O9/(1-M9) -> 2112920635 | Q9: =P9*M9 -> 7.8178063e+08 | R9: 0.075 | S9: =L9*N9 + (L9*N9*R9*(4+3+2+1+0)/5) -> 1530811000 | T9: =S9/(1-M9) -> 2429858730 | U9: =T9*M9 -> 8.9904773e+08 | V9: 2012-2024 | W9: https://www.loveproperty.com/gallerylist/73268/billionaire-boltholes-to-survive-the-end-of-the-world; https://shopoahuproperties.com/paypal-co-founder-peter-thiel-buys-maui-home-for-27m/; https://press.farm/inside-peter-thiels-lifestyle/; https://www.aol.com/news/fords-former-ceo-just-sold-164442537.html; https://press.farm/inside-peter-thiels-lifestyle/ | Y9: https://www.forbes.com/sites/tylerroush/2025/12/27/possible-california-wealth-tax-causes-billionaire-freakout-page-thiel-threaten-to-leave/
A10: 8 | B10: Robert Pera | C10: $25.5B | D10: 25500000000 | E10: San Jose | F10: =VLOOKUP(B10,Raw_Data_Collection!$B$2:$F$215,5,FALSE) -> N | G10: =VLOOKUP(B10,Raw_Data_Collection!$B$2:$J$215,6,FALSE) -> 21550000 | H10: https://www.dailymail.co.uk/sport/nba/article-12947653/Memphis-Grizzlies-billionaire-owner-Robert-Pena-Star-Island-arena.html | I10: 2024 | J10: =VLOOKUP(B10,Raw_Data_Collection!$B$2:$J$215,9,FALSE) | K10: =VLOOKUP(B10,Real_Estate_Stats_Preferred!$A$2:$G$215,7,FALSE) -> 21550000 | L10: =D10-K10 -> 25478450000 | M10: 0.37 | N10: 0.05 | O10: =L10*N10 -> 1273922500 | P10: =O10/(1-M10) -> 2022099206 | Q10: =P10*M10 -> 7.4817671e+08 | R10: 0.075 | S10: =L10*N10 + (L10*N10*R10*(4+3+2+1+0)/5) -> 1465010875 | T10: =S10/(1-M10) -> 2325414087 | U10: =T10*M10 -> 8.6040321e+08 | X10: Pera's primary residence is in San Jose, but no sources confirm its value. One of Pera's other residences is a $21.5 million NYC penthouse.
A11: 9 | B11: Adam Foroughi | C11: $25B | D11: 25000000000 | E11: Truckee | F11: =VLOOKUP(B11,Raw_Data_Collection!$B$2:$F$215,5,FALSE) -> N | G11: =VLOOKUP(B11,Raw_Data_Collection!$B$2:$J$215,6,FALSE) | J11: =VLOOKUP(B11,Raw_Data_Collection!$B$2:$J$215,9,FALSE) | K11: =VLOOKUP(B11,Real_Estate_Stats_Preferred!$A$2:$G$215,7,FALSE) -> 1.5900893e+08 | L11: =D11-K11 -> 24840991071 | M11: 0.37 | N11: 0.05 | O11: =L11*N11 -> 1242049554 | P11: =O11/(1-M11) -> 1971507228 | Q11: =P11*M11 -> 7.2945767e+08 | R11: 0.075 | S11: =L11*N11 + (L11*N11*R11*(4+3+2+1+0)/5) -> 1428356987 | T11: =S11/(1-M11) -> 2267233312 | U11: =T11*M11 -> 8.3887633e+08
A12: 10 | B12: Henry Nicholas III | C12: $21.9B | D12: 21900000000 | E12: Newport Coast | F12: =VLOOKUP(B12,Raw_Data_Collection!$B$2:$F$215,5,FALSE) -> N | G12: =VLOOKUP(B12,Raw_Data_Collection!$B$2:$J$215,6,FALSE) -> 19777777 | H12: https://hauteliving.com/2010/01/haute-estate-19-8-million-newport-coast-mansion/18762/ | I12: 2010 | J12: =VLOOKUP(B12,Raw_Data_Collection!$B$2:$J$215,9,FALSE) -> 19777777 | K12: =VLOOKUP(B12,Real_Estate_Stats_Preferred!$A$2:$G$215,7,FALSE) -> 19777777 | L12: =D12-K12 -> 21880222223 | M12: 0.37 | N12: 0.05 | O12: =L12*N12 -> 1094011111 | P12: =O12/(1-M12) -> 1736525573 | Q12: =P12*M12 -> 6.4251446e+08 | R12: 0.075 | S12: =L12*N12 + (L12*N12*R12*(4+3+2+1+0)/5) -> 1258112778 | T12: =S12/(1-M12) -> 1997004409 | U12: =T12*M12 -> 7.3889163e+08 | V12: 2010 | W12: https://hauteliving.com/2010/01/haute-estate-19-8-million-newport-coast-mansion/18762/
A13: 11 | B13: John Doerr | C13: $20B | D13: 20000000000 | E13: Woodside | F13: =VLOOKUP(B13,Raw_Data_Collection!$B$2:$F$215,5,FALSE) -> N | G13: =VLOOKUP(B13,Raw_Data_Collection!$B$2:$J$215,6,FALSE) | J13: =VLOOKUP(B13,Raw_Data_Collection!$B$2:$J$215,9,FALSE) | K13: =VLOOKUP(B13,Real_Estate_Stats_Preferred!$A$2:$G$215,7,FALSE) -> 1.2720714e+08 | L13: =D13-K13 -> 19872792857 | M13: 0.37 | N13: 0.05 | O13: =L13*N13 -> 9.9363964e+08 | P13: =O13/(1-M13) -> 1577205782 | Q13: =P13*M13 -> 5.8356614e+08 | R13: 0.075 | S13: =L13*N13 + (L13*N13*R13*(4+3+2+1+0)/5) -> 1142685589 | T13: =S13/(1-M13) -> 1813786650 | U13: =T13*M13 -> 6.7110106e+08
A14: 12 | B14: Donald Bren | C14: $19.2B | D14: 19200000000 | E14: Newport Beach | F14: =VLOOKUP(B14,Raw_Data_Collection!$B$2:$F$215,5,FALSE) -> N | G14: =VLOOKUP(B14,Raw_Data_Collection!$B$2:$J$215,6,FALSE) | J14: =VLOOKUP(B14,Raw_Data_Collection!$B$2:$J$215,9,FALSE) | K14: =VLOOKUP(B14,Real_Estate_Stats_Preferred!$A$2:$G$215,7,FALSE) -> 1.2211886e+08 | L14: =D14-K14 -> 19077881143 | M14: 0.37 | N14: 0.05 | O14: =L14*N14 -> 9.5389406e+08 | P14: =O14/(1-M14) -> 1514117551 | Q14: =P14*M14 -> 5.6022349e+08 | R14: 0.075 | S14: =L14*N14 + (L14*N14*R14*(4+3+2+1+0)/5) -> 1096978166 | T14: =S14/(1-M14) -> 1741235184 | U14: =T14*M14 -> 644257018
A15: 13 | B15: Eric Smidt | C15: $17.9B | D15: 17900000000 | E15: Beverly Hills | F15: =VLOOKUP(B15,Raw_Data_Collection!$B$2:$F$215,5,FALSE) -> N | G15: =VLOOKUP(B15,Raw_Data_Collection!$B$2:$J$215,6,FALSE) -> 54000000 | H15: https://labusinessjournal.com/special-editions/wealthiest-angelenos/wealthiest-2023/10-eric-smidt/ | I15: 2023 | J15: =VLOOKUP(B15,Raw_Data_Collection!$B$2:$J$215,9,FALSE) | K15: =VLOOKUP(B15,Real_Estate_Stats_Preferred!$A$2:$G$215,7,FALSE) -> 54000000 | L15: =D15-K15 -> 17846000000 | M15: 0.37 | N15: 0.05 | O15: =L15*N15 -> 892300000 | P15: =O15/(1-M15) -> 1416349206 | Q15: =P15*M15 -> 5.2404921e+08 | R15: 0.075 | S15: =L15*N15 + (L15*N15*R15*(4+3+2+1+0)/5) -> 1026145000 | T15: =S15/(1-M15) -> 1628801587 | U15: =T15*M15 -> 6.0265659e+08
A16: 14 | B16: John Tu | C16: $17.5B | D16: 17500000000 | E16: Rolling Hills | F16: =VLOOKUP(B16,Raw_Data_Collection!$B$2:$F$215,5,FALSE) -> N | G16: =VLOOKUP(B16,Raw_Data_Collection!$B$2:$J$215,6,FALSE) -> 7250000 | H16: https://blockshopper.com/ca/los-angeles-county/rolling-hills/property/7567015025/6-east-crest-road | I16: 2011 | J16: =VLOOKUP(B16,Raw_Data_Collection!$B$2:$J$215,9,FALSE) | K16: =VLOOKUP(B16,Real_Estate_Stats_Preferred!$A$2:$G$215,7,FALSE) -> 7250000 | L16: =D16-K16 -> 17492750000 | M16: 0.37 | N16: 0.05 | O16: =L16*N16 -> 874637500 | P16: =O16/(1-M16) -> 1388313492 | Q16: =P16*M16 -> 5.1367599e+08 | R16: 0.075 | S16: =L16*N16 + (L16*N16*R16*(4+3+2+1+0)/5) -> 1005833125 | T16: =S16/(1-M16) -> 1596560516 | U16: =T16*M16 -> 5.9072739e+08
A17: 15 | B17: David Sun | C17: $17.5B | D17: 17500000000 | E17: Irvine | F17: =VLOOKUP(B17,Raw_Data_Collection!$B$2:$F$215,5,FALSE) -> N | G17: =VLOOKUP(B17,Raw_Data_Collection!$B$2:$J$215,6,FALSE) | J17: =VLOOKUP(B17,Raw_Data_Collection!$B$2:$J$215,9,FALSE) | K17: =VLOOKUP(B17,Real_Estate_Stats_Preferred!$A$2:$G$215,7,FALSE) -> 111306250 | L17: =D17-K17 -> 17388693750 | M17: 0.37 | N17: 0.05 | O17: =L17*N17 -> 8.6943469e+08 | P17: =O17/(1-M17) -> 1380055060 | Q17: =P17*M17 -> 510620372 | R17: 0.075 | S17: =L17*N17 + (L17*N17*R17*(4+3+2+1+0)/5) -> 9.9984989e+08 | T17: =S17/(1-M17) -> 1587063318 | U17: =T17*M17 -> 5.8721343e+08
A18: 16 | B18: Jan Koum | C18: $17.1B | D18: 17100000000 | E18: Atherton | F18: N | G18: =VLOOKUP(B18,Raw_Data_Collection!$B$2:$J$215,6,FALSE) -> 187000000 | H18: https://www.celebritynetworth.com/articles/celebrity-homes/two-years-after-paying-100-million-for-a-malibu-mansion-whatsapp-founder-buys-the-house-next-door-for-87-million/ | I18: 2021 | J18: =VLOOKUP(B18,Raw_Data_Collection!$B$2:$J$215,9,FALSE) -> 400000000 | K18: =VLOOKUP(B18,Real_Estate_Stats_Preferred!$A$2:$G$215,7,FALSE) -> 400000000 | L18: =D18-K18 -> 16700000000 | M18: 0.37 | N18: 0.05 | O18: =L18*N18 -> 835000000 | P18: =O18/(1-M18) -> 1325396825 | Q18: =P18*M18 -> 4.9039683e+08 | R18: 0.075 | S18: =L18*N18 + (L18*N18*R18*(4+3+2+1+0)/5) -> 960250000 | T18: =S18/(1-M18) -> 1524206349 | U18: =T18*M18 -> 5.6395635e+08 | V18: 2021 | W18: https://www.celebritynetworth.com/articles/billionaire-news/jan-koum-grew-up-on-food-stamps-and-now-owns-more-than-400-million-worth-of-california-real-estate/ | X18: Koum's $187 million compound consists of two houses. | Y18: https://nypost.com/2026/01/08/real-estate/tech-titans-leaving-california-for-florida-over-billionaire-tax/
A19: 17 | B19: George Roberts | C19: $15.9B | D19: 15900000000 | E19: Atherton | F19: =VLOOKUP(B19,Raw_Data_Collection!$B$2:$F$215,5,FALSE) -> N | G19: =VLOOKUP(B19,Raw_Data_Collection!$B$2:$J$215,6,FALSE) -> 29084160 | H19: https://blockshopper.com/ca/san-mateo-county/atherton/property/070032440/260-atherton-avenue | I19: 2020 | J19: =VLOOKUP(B19,Raw_Data_Collection!$B$2:$J$215,9,FALSE) | K19: =VLOOKUP(B19,Real_Estate_Stats_Preferred!$A$2:$G$215,7,FALSE) -> 29084160 | L19: =D19-K19 -> 15870915840 | M19: 0.37 | N19: 0.05 | O19: =L19*N19 -> 793545792 | P19: =O19/(1-M19) -> 1259596495 | Q19: =P19*M19 -> 4.660507e+08 | R19: 0.075 | S19: =L19*N19 + (L19*N19*R19*(4+3+2+1+0)/5) -> 9.1257766e+08 | T19: =S19/(1-M19) -> 1448535970 | U19: =T19*M19 -> 5.3595831e+08
A20: 18 | B20: Laurene Powell Jobs | C20: $14B | D20: 14000000000 | E20: San Francisco | F20: =VLOOKUP(B20,Raw_Data_Collection!$B$2:$F$215,5,FALSE) -> N | G20: =VLOOKUP(B20,Raw_Data_Collection!$B$2:$J$215,6,FALSE) -> 70000000 | H20: https://fortune.com/2024/07/13/laurene-powell-jobs-buys-mansion-san-francisco-billionaires-row-70-million-record-high/ | I20: 2024 | J20: =VLOOKUP(B20,Raw_Data_Collection!$B$2:$J$215,9,FALSE) -> 242000000 | K20: =VLOOKUP(B20,Real_Estate_Stats_Preferred!$A$2:$G$215,7,FALSE) -> 242000000 | L20: =D20-K20 -> 13758000000 | M20: 0.37 | N20: 0.05 | O20: =L20*N20 -> 687900000 | P20: =O20/(1-M20) -> 1091904762 | Q20: =P20*M20 -> 4.0400476e+08 | R20: 0.075 | S20: =L20*N20 + (L20*N20*R20*(4+3+2+1+0)/5) -> 791085000 | T20: =S20/(1-M20) -> 1255690476 | U20: =T20*M20 -> 4.6460548e+08 | V20: 2015-2024 | W20: https://fortune.com/2024/06/17/laurene-powell-jobs-94-million-malibu-mansion-apple-steve-jobs-widow/; https://www.architecturaldigest.com/story/laurene-powell-jobs-buys-record-breaking-san-francisco-home
A21: 19 | B21: Jack Dangermond | C21: $13.8B | D21: 13800000000 | E21: Redlands | F21: =VLOOKUP(B21,Raw_Data_Collection!$B$2:$F$215,5,FALSE) -> N | G21: =VLOOKUP(B21,Raw_Data_Collection!$B$2:$J$215,6,FALSE) | J21: =VLOOKUP(B21,Raw_Data_Collection!$B$2:$J$215,9,FALSE) | K21: =VLOOKUP(B21,Real_Estate_Stats_Preferred!$A$2:$G$215,7,FALSE) -> 87772929 | L21: =D21-K21 -> 13712227071 | M21: 0.37 | N21: 0.05 | O21: =L21*N21 -> 6.8561135e+08 | P21: =O21/(1-M21) -> 1088271990 | Q21: =P21*M21 -> 4.0266064e+08 | R21: 0.075 | S21: =L21*N21 + (L21*N21*R21*(4+3+2+1+0)/5) -> 7.8845306e+08 | T21: =S21/(1-M21) -> 1251512788 | U21: =T21*M21 -> 4.6305973e+08
A22: 20 | B22: Antony Ressler | C22: $13.1B | D22: 13100000000 | E22: Los Angeles | F22: =VLOOKUP(B22,Raw_Data_Collection!$B$2:$F$215,5,FALSE) -> N | G22: =VLOOKUP(B22,Raw_Data_Collection!$B$2:$J$215,6,FALSE) -> 60000000 | H22: https://www.finance-monthly.com/antony-resslers-net-worth-2025-billionaire-financier-sports-owner-and-philanthropist/ | I22: 2025 | J22: =VLOOKUP(B22,Raw_Data_Collection!$B$2:$J$215,9,FALSE) -> 100000000 | K22: =VLOOKUP(B22,Real_Estate_Stats_Preferred!$A$2:$G$215,7,FALSE) -> 100000000 | L22: =D22-K22 -> 13000000000 | M22: 0.37 | N22: 0.05 | O22: =L22*N22 -> 650000000 | P22: =O22/(1-M22) -> 1031746032 | Q22: =P22*M22 -> 3.8174603e+08 | R22: 0.075 | S22: =L22*N22 + (L22*N22*R22*(4+3+2+1+0)/5) -> 747500000 | T22: =S22/(1-M22) -> 1186507937 | U22: =T22*M22 -> 4.3900794e+08 | V22: 2025 | W22: https://www.finance-monthly.com/antony-resslers-net-worth-2025-billionaire-financier-sports-owner-and-philanthropist/ | X22: Ressler's various LA properties are estimated to be worth over $100,000,000.
A23: 21 | B23: Vinod Khosla | C23: $12.5B | D23: 12500000000 | E23: Portola Valley | F23: =VLOOKUP(B23,Raw_Data_Collection!$B$2:$F$215,5,FALSE) -> N | G23: =VLOOKUP(B23,Raw_Data_Collection!$B$2:$J$215,6,FALSE) -> 17100579 | J23: =VLOOKUP(B23,Raw_Data_Collection!$B$2:$J$215,9,FALSE) -> 17100579 | K23: =VLOOKUP(B23,Real_Estate_Stats_Preferred!$A$2:$G$215,7,FALSE) -> 79504464 | L23: =D23-K23 -> 12420495536 | M23: 0.37 | N23: 0.05 | O23: =L23*N23 -> 6.2102478e+08 | P23: =O23/(1-M23) -> 9.8575361e+08 | Q23: =P23*M23 -> 3.6472884e+08 | R23: 0.075 | S23: =L23*N23 + (L23*N23*R23*(4+3+2+1+0)/5) -> 7.1417849e+08 | T23: =S23/(1-M23) -> 1133616656 | U23: =T23*M23 -> 4.1943816e+08
A24: 22 | B24: Riley Bechtel | C24: $11.6B | D24: 11600000000 | E24: Woodside | F24: =VLOOKUP(B24,Raw_Data_Collection!$B$2:$F$215,5,FALSE) -> N | G24: =VLOOKUP(B24,Raw_Data_Collection!$B$2:$J$215,6,FALSE) -> 63300000 | H24: https://www.yahoo.com/entertainment/billionaire-riley-bechtel-pays-record-201404351.html | I24: 2020 | J24: =VLOOKUP(B24,Raw_Data_Collection!$B$2:$J$215,9,FALSE) -> 86100000 | K24: =VLOOKUP(B24,Real_Estate_Stats_Preferred!$A$2:$G$215,7,FALSE) -> 86100000 | L24: =D24-K24 -> 11513900000 | M24: 0.37 | N24: 0.05 | O24: =L24*N24 -> 575695000 | P24: =O24/(1-M24) -> 9.1380159e+08 | Q24: =P24*M24 -> 3.3810659e+08 | R24: 0.075 | S24: =L24*N24 + (L24*N24*R24*(4+3+2+1+0)/5) -> 662049250 | T24: =S24/(1-M24) -> 1050871825 | U24: =T24*M24 -> 3.8882258e+08 | V24: 2011-2020 | W24: https://www.yahoo.com/entertainment/billionaire-riley-bechtel-pays-record-201404351.html
A25: 23 | B25: Dustin Moskovitz | C25: $11.2B | D25: 11200000000 | E25: San Francisco | F25: =VLOOKUP(B25,Raw_Data_Collection!$B$2:$F$215,5,FALSE) -> N | G25: =VLOOKUP(B25,Raw_Data_Collection!$B$2:$J$215,6,FALSE) -> 800000 | H25: https://www.seattletimes.com/business/young-tech-millionaires-keeping-1-bedroom-lifestyle/ | I25: 2011 | J25: =VLOOKUP(B25,Raw_Data_Collection!$B$2:$J$215,9,FALSE) | K25: =VLOOKUP(B25,Real_Estate_Stats_Preferred!$A$2:$G$215,7,FALSE) -> 800000 | L25: =D25-K25 -> 11199200000 | M25: 0.37 | N25: 0.05 | O25: =L25*N25 -> 559960000 | P25: =O25/(1-M25) -> 8.888254e+08 | Q25: =P25*M25 -> 3.288654e+08 | R25: 0.075 | S25: =L25*N25 + (L25*N25*R25*(4+3+2+1+0)/5) -> 643954000 | T25: =S25/(1-M25) -> 1022149206 | U25: =T25*M25 -> 3.7819521e+08 | X25: Moskovitz' primary residence is an $800,000 San Francisco condo.
A26: 24 | B26: Douglas Leone | C26: $10.7B | D26: 10700000000 | E26: Napa | F26: =VLOOKUP(B26,Raw_Data_Collection!$B$2:$F$215,5,FALSE) -> N | G26: =VLOOKUP(B26,Raw_Data_Collection!$B$2:$J$215,6,FALSE) -> 10000000 | H26: https://www.celebritynetworth.com/richest-businessmen/richest-billionaires/douglas-leone-net-worth/ | I26: 2026 | J26: =VLOOKUP(B26,Raw_Data_Collection!$B$2:$J$215,9,FALSE) -> 80000000 | K26: =VLOOKUP(B26,Real_Estate_Stats_Preferred!$A$2:$G$215,7,FALSE) -> 80000000 | L26: =D26-K26 -> 10620000000 | M26: 0.37 | N26: 0.05 | O26: =L26*N26 -> 531000000 | P26: =O26/(1-M26) -> 8.4285714e+08 | Q26: =P26*M26 -> 3.1185714e+08 | R26: 0.075 | S26: =L26*N26 + (L26*N26*R26*(4+3+2+1+0)/5) -> 610650000 | T26: =S26/(1-M26) -> 9.6928571e+08 | U26: =T26*M26 -> 3.5863571e+08 | V26: 2000-2026 | W26: https://www.celebritynetworth.com/richest-businessmen/richest-billionaires/douglas-leone-net-worth/
A27: 25 | B27: Chris Larsen | C27: $10.2B | D27: 10200000000 | E27: San Francisco | F27: =VLOOKUP(B27,Raw_Data_Collection!$B$2:$F$215,5,FALSE) -> N | G27: =VLOOKUP(B27,Raw_Data_Collection!$B$2:$J$215,6,FALSE) -> 13500000 | H27: https://sfstandard.com/2025/09/09/chris-larsen-napa-home/ | I27: 2025 | J27: =VLOOKUP(B27,Raw_Data_Collection!$B$2:$J$215,9,FALSE) -> 13500000 | K27: =VLOOKUP(B27,Real_Estate_Stats_Preferred!$A$2:$G$215,7,FALSE) -> 13500000 | L27: =D27-K27 -> 10186500000 | M27: 0.37 | N27: 0.05 | O27: =L27*N27 -> 509325000 | P27: =O27/(1-M27) -> 808452381 | Q27: =P27*M27 -> 299127381 | R27: 0.075 | S27: =L27*N27 + (L27*N27*R27*(4+3+2+1+0)/5) -> 585723750 | T27: =S27/(1-M27) -> 9.2972024e+08 | U27: =T27*M27 -> 3.4399649e+08 | V27: 2025 | W27: https://docs.google.com/spreadsheets/d/1-d_IAr8tITUy_s8QmIzH-FLYoODzaBxNMWShu9W7IFk/edit?gid=1121030019#gid=1121030019
A28: 26 | B28: Brian Armstrong | C28: $10.1B | D28: 10100000000 | E28: Los Angeles | F28: =VLOOKUP(B28,Raw_Data_Collection!$B$2:$F$215,5,FALSE) -> N | G28: =VLOOKUP(B28,Raw_Data_Collection!$B$2:$J$215,6,FALSE) -> 133000000 | H28: https://www.urbansplatter.com/2022/05/brian-armstrong-house-the-los-angeles-mansion/ | I28: 2022 | J28: =VLOOKUP(B28,Raw_Data_Collection!$B$2:$J$215,9,FALSE) -> 133000000 | K28: =VLOOKUP(B28,Real_Estate_Stats_Preferred!$A$2:$G$215,7,FALSE) -> 133000000 | L28: =D28-K28 -> 9967000000 | M28: 0.37 | N28: 0.05 | O28: =L28*N28 -> 498350000 | P28: =O28/(1-M28) -> 791031746 | Q28: =P28*M28 -> 292681746 | R28: 0.075 | S28: =L28*N28 + (L28*N28*R28*(4+3+2+1+0)/5) -> 573102500 | T28: =S28/(1-M28) -> 9.0968651e+08 | U28: =T28*M28 -> 3.3658401e+08 | V28: 2022 | W28: https://www.urbansplatter.com/2022/05/brian-armstrong-house-the-los-angeles-mansion/
A29: 27 | B29: Marijke Mars | C29: $10B | D29: 10000000000 | E29: Los Angeles | F29: =VLOOKUP(B29,Raw_Data_Collection!$B$2:$F$215,5,FALSE) -> N | G29: =VLOOKUP(B29,Raw_Data_Collection!$B$2:$J$215,6,FALSE) | J29: =VLOOKUP(B29,Raw_Data_Collection!$B$2:$J$215,9,FALSE) | K29: =VLOOKUP(B29,Real_Estate_Stats_Preferred!$A$2:$G$215,7,FALSE) -> 63603571 | L29: =D29-K29 -> 9936396429 | M29: 0.37 | N29: 0.05 | O29: =L29*N29 -> 4.9681982e+08 | P29: =O29/(1-M29) -> 7.8860289e+08 | Q29: =P29*M29 -> 2.9178307e+08 | R29: 0.075 | S29: =L29*N29 + (L29*N29*R29*(4+3+2+1+0)/5) -> 5.7134279e+08 | T29: =S29/(1-M29) -> 9.0689332e+08 | U29: =T29*M29 -> 3.3555053e+08
A30: 28 | B30: Tom Gores | C30: $10B | D30: 10000000000 | E30: Beverly Hills | F30: =VLOOKUP(B30,Raw_Data_Collection!$B$2:$F$215,5,FALSE) -> N | G30: =VLOOKUP(B30,Raw_Data_Collection!$B$2:$J$215,6,FALSE) -> 100000000 | H30: https://therealdeal.com/la/2016/10/24/platinum-equity-ceo-buys-holmby-hills-spec-home-for-100m/ | I30: 2016 | J30: =VLOOKUP(B30,Raw_Data_Collection!$B$2:$J$215,9,FALSE) -> 138000000 | K30: =VLOOKUP(B30,Real_Estate_Stats_Preferred!$A$2:$G$215,7,FALSE) -> 138000000 | L30: =D30-K30 -> 9862000000 | M30: 0.37 | N30: 0.05 | O30: =L30*N30 -> 493100000 | P30: =O30/(1-M30) -> 7.8269841e+08 | Q30: =P30*M30 -> 2.8959841e+08 | R30: 0.075 | S30: =L30*N30 + (L30*N30*R30*(4+3+2+1+0)/5) -> 567065000 | T30: =S30/(1-M30) -> 9.0010317e+08 | U30: =T30*M30 -> 3.3303817e+08 | V30: 2016-2017 | W30: https://therealdeal.com/la/2016/10/24/platinum-equity-ceo-buys-holmby-hills-spec-home-for-100m/; https://therealdeal.com/la/2017/12/04/detroit-pistons-owner-tom-gores-pays-38m-for-his-former-beverly-park-home/
A31: 29 | B31: Andrew Karam | C31: $9.8B | D31: 9800000000 | E31: Menlo Park | F31: =VLOOKUP(B31,Raw_Data_Collection!$B$2:$F$215,5,FALSE) -> N | G31: =VLOOKUP(B31,Raw_Data_Collection!$B$2:$J$215,6,FALSE) | J31: =VLOOKUP(B31,Raw_Data_Collection!$B$2:$J$215,9,FALSE) | K31: =VLOOKUP(B31,Real_Estate_Stats_Preferred!$A$2:$G$215,7,FALSE) -> 62331500 | L31: =D31-K31 -> 9737668500 | M31: 0.37 | N31: 0.05 | O31: =L31*N31 -> 486883425 | P31: =O31/(1-M31) -> 7.7283083e+08 | Q31: =P31*M31 -> 2.8594741e+08 | R31: 0.075 | S31: =L31*N31 + (L31*N31*R31*(4+3+2+1+0)/5) -> 5.5991594e+08 | T31: =S31/(1-M31) -> 8.8875546e+08 | U31: =T31*M31 -> 3.2883952e+08
A32: 30 | B32: Brian Chesky | C32: $9.6B | D32: 9600000000 | E32: San Francisco | F32: =VLOOKUP(B32,Raw_Data_Collection!$B$2:$F$215,5,FALSE) -> N | G32: =VLOOKUP(B32,Raw_Data_Collection!$B$2:$J$215,6,FALSE) | J32: =VLOOKUP(B32,Raw_Data_Collection!$B$2:$J$215,9,FALSE) | K32: =VLOOKUP(B32,Real_Estate_Stats_Preferred!$A$2:$G$215,7,FALSE) -> 61059429 | L32: =D32-K32 -> 9538940571 | M32: 0.37 | N32: 0.05 | O32: =L32*N32 -> 4.7694703e+08 | P32: =O32/(1-M32) -> 7.5705878e+08 | Q32: =P32*M32 -> 2.8011175e+08 | R32: 0.075 | S32: =L32*N32 + (L32*N32*R32*(4+3+2+1+0)/5) -> 5.4848908e+08 | T32: =S32/(1-M32) -> 8.7061759e+08 | U32: =T32*M32 -> 322128509 | Y32: https://www.washingtonpost.com/technology/2026/01/19/california-wealth-tax-exodus/
A33: 31 | B33: Marc Benioff | C33: $9.3B | D33: 9300000000 | E33: San Francisco | F33: =VLOOKUP(B33,Raw_Data_Collection!$B$2:$F$215,5,FALSE) -> N | G33: =VLOOKUP(B33,Raw_Data_Collection!$B$2:$J$215,6,FALSE) -> 18000000 | H33: https://www.yahoo.com/entertainment/twitter-ceo-jack-dorsey-scoops-011751538.html | I33: 2009 | J33: =VLOOKUP(B33,Raw_Data_Collection!$B$2:$J$215,9,FALSE) | K33: =VLOOKUP(B33,Real_Estate_Stats_Preferred!$A$2:$G$215,7,FALSE) -> 18000000 | L33: =D33-K33 -> 9282000000 | M33: 0.37 | N33: 0.05 | O33: =L33*N33 -> 464100000 | P33: =O33/(1-M33) -> 7.3666667e+08 | Q33: =P33*M33 -> 2.7256667e+08 | R33: 0.075 | S33: =L33*N33 + (L33*N33*R33*(4+3+2+1+0)/5) -> 533715000 | T33: =S33/(1-M33) -> 8.4716667e+08 | U33: =T33*M33 -> 3.1345167e+08
A34: 32 | B34: David Geffen | C34: $9.2B | D34: 9200000000 | E34: Beverly Hills | F34: =VLOOKUP(B34,Raw_Data_Collection!$B$2:$F$215,5,FALSE) -> N | G34: =VLOOKUP(B34,Raw_Data_Collection!$B$2:$J$215,6,FALSE) -> 68000000 | H34: https://finance.yahoo.com/news/david-geffen-completes-68-million-192458970.html | I34: 2020 | J34: =VLOOKUP(B34,Raw_Data_Collection!$B$2:$J$215,9,FALSE) -> 132000000 | K34: =VLOOKUP(B34,Real_Estate_Stats_Preferred!$A$2:$G$215,7,FALSE) -> 132000000 | L34: =D34-K34 -> 9068000000 | M34: 0.37 | N34: 0.05 | O34: =L34*N34 -> 453400000 | P34: =O34/(1-M34) -> 7.1968254e+08 | Q34: =P34*M34 -> 2.6628254e+08 | R34: 0.075 | S34: =L34*N34 + (L34*N34*R34*(4+3+2+1+0)/5) -> 521410000 | T34: =S34/(1-M34) -> 8.2763492e+08 | U34: =T34*M34 -> 3.0622492e+08 | V34: 2010-2020 | W34: https://www.inman.com/2020/06/11/entertainment-mogul-david-geffen-buys-la-luxury-estate-for-68m/; https://www.forbes.com/sites/erincarlyle/2014/05/07/a-look-at-billionaire-david-geffens-1-1-billion-stash-of-dream-palaces/
A35: 33 | B35: Nathan Blecharczyk | C35: $9.1B | D35: 9100000000 | E35: San Francisco | F35: =VLOOKUP(B35,Raw_Data_Collection!$B$2:$F$215,5,FALSE) -> N | G35: =VLOOKUP(B35,Raw_Data_Collection!$B$2:$J$215,6,FALSE) | J35: =VLOOKUP(B35,Raw_Data_Collection!$B$2:$J$215,9,FALSE) | K35: =VLOOKUP(B35,Real_Estate_Stats_Preferred!$A$2:$G$215,7,FALSE) -> 57879250 | L35: =D35-K35 -> 9042120750 | M35: 0.37 | N35: 0.05 | O35: =L35*N35 -> 4.5210604e+08 | P35: =O35/(1-M35) -> 717628631 | Q35: =P35*M35 -> 2.6552259e+08 | R35: 0.075 | S35: =L35*N35 + (L35*N35*R35*(4+3+2+1+0)/5) -> 5.1992194e+08 | T35: =S35/(1-M35) -> 8.2527293e+08 | U35: =T35*M35 -> 3.0535098e+08
A36: 34 | B36: Steven Rales | C36: $8.6B | D36: 8600000000 | E36: Santa Barbara | F36: =VLOOKUP(B36,Raw_Data_Collection!$B$2:$F$215,5,FALSE) -> N | G36: =VLOOKUP(B36,Raw_Data_Collection!$B$2:$J$215,6,FALSE) | J36: =VLOOKUP(B36,Raw_Data_Collection!$B$2:$J$215,9,FALSE) | K36: =VLOOKUP(B36,Real_Estate_Stats_Preferred!$A$2:$G$215,7,FALSE) -> 54699071 | L36: =D36-K36 -> 8545300929 | M36: 0.37 | N36: 0.05 | O36: =L36*N36 -> 4.2726505e+08 | P36: =O36/(1-M36) -> 6.7819849e+08 | Q36: =P36*M36 -> 250933440 | R36: 0.075 | S36: =L36*N36 + (L36*N36*R36*(4+3+2+1+0)/5) -> 4.913548e+08 | T36: =S36/(1-M36) -> 7.7992826e+08 | U36: =T36*M36 -> 288573456
A37: 35 | B37: Don Hankey | C37: $8.1B | D37: 8100000000 | E37: Malibu | F37: =VLOOKUP(B37,Raw_Data_Collection!$B$2:$F$215,5,FALSE) -> Y | G37: =VLOOKUP(B37,Raw_Data_Collection!$B$2:$J$215,6,FALSE) -> 10659988 | H37: https://www.homes.com/property/27450-pacific-coast-hwy-malibu-ca/gt8keb94hyyzn/ | I37: 2026 | J37: =VLOOKUP(B37,Raw_Data_Collection!$B$2:$J$215,9,FALSE) -> 51300000 | K37: =VLOOKUP(B37,Real_Estate_Stats_Preferred!$A$2:$G$215,7,FALSE) -> 51300000 | L37: =D37-K37 -> 8048700000 | M37: 0.37 | N37: 0.05 | O37: =L37*N37 -> 402435000 | P37: =O37/(1-M37) -> 6.3878571e+08 | Q37: =P37*M37 -> 2.3635071e+08 | R37: 0.075 | S37: =L37*N37 + (L37*N37*R37*(4+3+2+1+0)/5) -> 462800250 | T37: =S37/(1-M37) -> 7.3460357e+08 | U37: =T37*M37 -> 2.7180332e+08 | V37: 2021-2026 | W37: https://www.reviewjournal.com/business/housing/l-a-billionaire-buys-summerlin-condo-for-record-high-21m-3609182/; https://therealdeal.com/miami/2021/10/13/billionaire-don-hankey-buys-oceanfront-highland-beach-mansion-for-30m/ | X37: Estimated value on homes.com is $6,882,000 - $19,119,746 | Y37: https://www.forbes.com/sites/chasewithorn/2026/01/15/los-angeles-billionaire-moves-to-nevada-after-california-threatens-to-tax-wealth/
A38: 36 | B38: Tench Coxe | C38: $7.8B | D38: 7800000000 | E38: Palo Alto | F38: =VLOOKUP(B38,Raw_Data_Collection!$B$2:$F$215,5,FALSE) -> N | G38: =VLOOKUP(B38,Raw_Data_Collection!$B$2:$J$215,6,FALSE) -> 8683775 | H38: https://www.homes.com/property/1401-emerson-st-palo-alto-ca/znpl6z10qsgvy/ | I38: 2026 | J38: =VLOOKUP(B38,Raw_Data_Collection!$B$2:$J$215,9,FALSE) -> 8683775 | K38: =VLOOKUP(B38,Real_Estate_Stats_Preferred!$A$2:$G$215,7,FALSE) -> 8683775 | L38: =D38-K38 -> 7791316225 | M38: 0.37 | N38: 0.05 | O38: =L38*N38 -> 3.8956581e+08 | P38: =O38/(1-M38) -> 6.1835843e+08 | Q38: =P38*M38 -> 2.2879262e+08 | R38: 0.075 | S38: =L38*N38 + (L38*N38*R38*(4+3+2+1+0)/5) -> 4.4800068e+08 | T38: =S38/(1-M38) -> 7.111122e+08 | U38: =T38*M38 -> 2.6311151e+08 | V38: 2026 | W38: https://www.homes.com/property/1401-emerson-st-palo-alto-ca/znpl6z10qsgvy/ | X38: Estimated value on homes.com is $5,573,000 $8,683,775
A39: 37 | B39: Michael Moritz | C39: $7.7B | D39: 7700000000 | E39: San Francisco | F39: =VLOOKUP(B39,Raw_Data_Collection!$B$2:$F$215,5,FALSE) -> N | G39: =VLOOKUP(B39,Raw_Data_Collection!$B$2:$J$215,6,FALSE) -> 10600000 | H39: https://blockshopper.com/ca/san-francisco-county/san-francisco/property/0953006/2626-vallejo-street | I39: 2002 | J39: =VLOOKUP(B39,Raw_Data_Collection!$B$2:$J$215,9,FALSE) -> 10600000 | K39: =VLOOKUP(B39,Real_Estate_Stats_Preferred!$A$2:$G$215,7,FALSE) -> 10600000 | L39: =D39-K39 -> 7689400000 | M39: 0.37 | N39: 0.05 | O39: =L39*N39 -> 384470000 | P39: =O39/(1-M39) -> 6.1026984e+08 | Q39: =P39*M39 -> 2.2579984e+08 | R39: 0.075 | S39: =L39*N39 + (L39*N39*R39*(4+3+2+1+0)/5) -> 442140500 | T39: =S39/(1-M39) -> 7.0181032e+08 | U39: =T39*M39 -> 2.5966982e+08 | V39: 2002 | W39: https://blockshopper.com/ca/san-francisco-county/san-francisco/property/0953006/2626-vallejo-street | Y39: https://www.bloomberg.com/news/articles/2026-01-08/california-wealth-tax-threat-pushes-billionaires-to-texas-florida
A40: 38 | B40: Edward Roski Jr | C40: $7.6B | D40: 7600000000 | E40: Los Angeles | F40: =VLOOKUP(B40,Raw_Data_Collection!$B$2:$F$215,5,FALSE) -> N | G40: =VLOOKUP(B40,Raw_Data_Collection!$B$2:$J$215,6,FALSE) -> 8107000 | H40: https://www.homes.com/property/10051-valley-spring-ln-toluca-lake-ca/kd8ylmg68cld1/ | I40: 2026 | J40: =VLOOKUP(B40,Raw_Data_Collection!$B$2:$J$215,9,FALSE) -> 8107000 | K40: =VLOOKUP(B40,Real_Estate_Stats_Preferred!$A$2:$G$215,7,FALSE) -> 8107000 | L40: =D40-K40 -> 7591893000 | M40: 0.37 | N40: 0.05 | O40: =L40*N40 -> 379594650 | P40: =O40/(1-M40) -> 6.0253119e+08 | Q40: =P40*M40 -> 2.2293654e+08 | R40: 0.075 | S40: =L40*N40 + (L40*N40*R40*(4+3+2+1+0)/5) -> 4.3653385e+08 | T40: =S40/(1-M40) -> 692910869 | U40: =T40*M40 -> 2.5637702e+08 | V40: 2026 | W40: https://www.homes.com/property/10051-valley-spring-ln-toluca-lake-ca/kd8ylmg68cld1/ | X40: Estimated value on homes.com is $6,522,000 - $8,107,000.
A41: 39 | B41: Michael Milken | C41: $7.4B | D41: 7400000000 | E41: Los Angeles | F41: =VLOOKUP(B41,Raw_Data_Collection!$B$2:$F$215,5,FALSE) -> N | G41: =VLOOKUP(B41,Raw_Data_Collection!$B$2:$J$215,6,FALSE) -> 102000000 | H41: https://www.forbes.com/sites/trulia/2014/04/04/las-super-mansion-fleur-de-lys-sells-for-a-record-breaking-102-million/ | I41: 2014 | J41: =VLOOKUP(B41,Raw_Data_Collection!$B$2:$J$215,9,FALSE) -> 179750000 | K41: =VLOOKUP(B41,Real_Estate_Stats_Preferred!$A$2:$G$215,7,FALSE) -> 179750000 | L41: =D41-K41 -> 7220250000 | M41: 0.37 | N41: 0.05 | O41: =L41*N41 -> 361012500 | P41: =O41/(1-M41) -> 5.7303571e+08 | Q41: =P41*M41 -> 2.1202321e+08 | R41: 0.075 | S41: =L41*N41 + (L41*N41*R41*(4+3+2+1+0)/5) -> 415164375 | T41: =S41/(1-M41) -> 6.5899107e+08 | U41: =T41*M41 -> 2.438267e+08 | V41: 2011-2026 | W41: https://palisadesnews.com/michael-milkens-pacific-palisades-estate-goes-on-sale-for-64-million/; https://virtualglobetrotting.com/map/michael-milkens-house-4/view/google/; https://www.forbes.com/sites/trulia/2014/04/04/las-super-mansion-fleur-de-lys-sells-for-a-record-breaking-102-million/
A42: 40 | B42: Steven Spielberg | C42: $7B | D42: 7000000000 | E42: Pacific Palisades | F42: Y | G42: =VLOOKUP(B42,Raw_Data_Collection!$B$2:$J$215,6,FALSE) -> 250000000 | H42: https://www.finance-monthly.com/steven-spielbergs-net-worth-9-5-billion-in-2025/ | I42: 2024 | J42: =VLOOKUP(B42,Raw_Data_Collection!$B$2:$J$215,9,FALSE) -> 250000000 | K42: =VLOOKUP(B42,Real_Estate_Stats_Preferred!$A$2:$G$215,7,FALSE) -> 250000000 | L42: =D42-K42 -> 6750000000 | M42: 0.37 | N42: 0.05 | O42: =L42*N42 -> 337500000 | P42: =O42/(1-M42) -> 5.3571429e+08 | Q42: =P42*M42 -> 1.9821429e+08 | R42: 0.075 | S42: =L42*N42 + (L42*N42*R42*(4+3+2+1+0)/5) -> 388125000 | T42: =S42/(1-M42) -> 6.1607143e+08 | U42: =T42*M42 -> 2.2794643e+08 | V42: 2024 | W42: https://www.finance-monthly.com/steven-spielbergs-net-worth-9-5-billion-in-2025/ | X42: Spielberg's property is estimated to be between $100 million and $250 million.
A43: 41 | B43: Edythe Broad | C43: $6.9B | D43: 6900000000 | E43: Los Angeles | F43: =VLOOKUP(B43,Raw_Data_Collection!$B$2:$F$215,5,FALSE) -> N | G43: =VLOOKUP(B43,Raw_Data_Collection!$B$2:$J$215,6,FALSE) -> 13283376 | J43: =VLOOKUP(B43,Raw_Data_Collection!$B$2:$J$215,9,FALSE) -> 13283376 | K43: =VLOOKUP(B43,Real_Estate_Stats_Preferred!$A$2:$G$215,7,FALSE) -> 43886464 | L43: =D43-K43 -> 6856113536 | M43: 0.37 | N43: 0.05 | O43: =L43*N43 -> 3.4280568e+08 | P43: =O43/(1-M43) -> 5.4413599e+08 | Q43: =P43*M43 -> 2.0133032e+08 | R43: 0.075 | S43: =L43*N43 + (L43*N43*R43*(4+3+2+1+0)/5) -> 3.9422653e+08 | T43: =S43/(1-M43) -> 6.2575639e+08 | U43: =T43*M43 -> 2.3152987e+08
A44: 42 | B44: Scott Cook | C44: $6.9B | D44: 6900000000 | E44: Woodside | F44: =VLOOKUP(B44,Raw_Data_Collection!$B$2:$F$215,5,FALSE) -> N | G44: =VLOOKUP(B44,Raw_Data_Collection!$B$2:$J$215,6,FALSE) -> 15830193 | H44: https://www.homes.com/property/376-mountain-home-rd-woodside-ca/p6sh3hp6plvk6/ | I44: 2026 | J44: =VLOOKUP(B44,Raw_Data_Collection!$B$2:$J$215,9,FALSE) -> 15830193 | K44: =VLOOKUP(B44,Real_Estate_Stats_Preferred!$A$2:$G$215,7,FALSE) -> 15830193 | L44: =D44-K44 -> 6884169807 | M44: 0.37 | N44: 0.05 | O44: =L44*N44 -> 3.4420849e+08 | P44: =O44/(1-M44) -> 5.4636268e+08 | Q44: =P44*M44 -> 2.0215419e+08 | R44: 0.075 | S44: =L44*N44 + (L44*N44*R44*(4+3+2+1+0)/5) -> 3.9583976e+08 | T44: =S44/(1-M44) -> 6.2831709e+08 | U44: =T44*M44 -> 2.3247732e+08 | V44: 2026 | W44: https://www.homes.com/property/376-mountain-home-rd-woodside-ca/p6sh3hp6plvk6/ | X44: Estimated value on homes.com is 6,309,000-15,830,193
A45: 43 | B45: Baiju Bhatt | C45: $6.7B | D45: 6700000000 | E45: Palo Alto | F45: =VLOOKUP(B45,Raw_Data_Collection!$B$2:$F$215,5,FALSE) -> N | G45: =VLOOKUP(B45,Raw_Data_Collection!$B$2:$J$215,6,FALSE) | J45: =VLOOKUP(B45,Raw_Data_Collection!$B$2:$J$215,9,FALSE) | K45: =VLOOKUP(B45,Real_Estate_Stats_Preferred!$A$2:$G$215,7,FALSE) -> 42614393 | L45: =D45-K45 -> 6657385607 | M45: 0.37 | N45: 0.05 | O45: =L45*N45 -> 3.3286928e+08 | P45: =O45/(1-M45) -> 5.2836394e+08 | Q45: =P45*M45 -> 1.9549466e+08 | R45: 0.075 | S45: =L45*N45 + (L45*N45*R45*(4+3+2+1+0)/5) -> 3.8279967e+08 | T45: =S45/(1-M45) -> 6.0761853e+08 | U45: =T45*M45 -> 2.2481886e+08
A46: 44 | B46: Vlad Tenev | C46: $6.4B | D46: 6400000000 | E46: Palo Alto | F46: =VLOOKUP(B46,Raw_Data_Collection!$B$2:$F$215,5,FALSE) -> N | G46: =VLOOKUP(B46,Raw_Data_Collection!$B$2:$J$215,6,FALSE) | J46: =VLOOKUP(B46,Raw_Data_Collection!$B$2:$J$215,9,FALSE) | K46: =VLOOKUP(B46,Real_Estate_Stats_Preferred!$A$2:$G$215,7,FALSE) -> 40706286 | L46: =D46-K46 -> 6359293714 | M46: 0.37 | N46: 0.05 | O46: =L46*N46 -> 3.1796469e+08 | P46: =O46/(1-M46) -> 5.0470585e+08 | Q46: =P46*M46 -> 1.8674116e+08 | R46: 0.075 | S46: =L46*N46 + (L46*N46*R46*(4+3+2+1+0)/5) -> 3.6565939e+08 | T46: =S46/(1-M46) -> 5.8041173e+08 | U46: =T46*M46 -> 2.1475234e+08
A47: 45 | B47: John A. Sobrato | C47: $6.4B | D47: 6400000000 | E47: Atherton | F47: =VLOOKUP(B47,Raw_Data_Collection!$B$2:$F$215,5,FALSE) -> N | G47: =VLOOKUP(B47,Raw_Data_Collection!$B$2:$J$215,6,FALSE) | J47: =VLOOKUP(B47,Raw_Data_Collection!$B$2:$J$215,9,FALSE) | K47: =VLOOKUP(B47,Real_Estate_Stats_Preferred!$A$2:$G$215,7,FALSE) -> 40706286 | L47: =D47-K47 -> 6359293714 | M47: 0.37 | N47: 0.05 | O47: =L47*N47 -> 3.1796469e+08 | P47: =O47/(1-M47) -> 5.0470585e+08 | Q47: =P47*M47 -> 1.8674116e+08 | R47: 0.075 | S47: =L47*N47 + (L47*N47*R47*(4+3+2+1+0)/5) -> 3.6565939e+08 | T47: =S47/(1-M47) -> 5.8041173e+08 | U47: =T47*M47 -> 2.1475234e+08 | Y47: https://www.bloomberg.com/news/articles/2026-01-08/california-wealth-tax-threat-pushes-billionaires-to-texas-florida
A48: 46 | B48: Stephen Cohen | C48: $6.3B | D48: 6300000000 | E48: Palo Alto | F48: =VLOOKUP(B48,Raw_Data_Collection!$B$2:$F$215,5,FALSE) -> N | G48: =VLOOKUP(B48,Raw_Data_Collection!$B$2:$J$215,6,FALSE) -> 1031715 | H48: https://www.homes.com/property/20-willow-rd-menlo-park-ca-unit-8/hbwec8jc2rsrg/ | I48: 2026 | J48: =VLOOKUP(B48,Raw_Data_Collection!$B$2:$J$215,9,FALSE) | K48: =VLOOKUP(B48,Real_Estate_Stats_Preferred!$A$2:$G$215,7,FALSE) -> 1031715 | L48: =D48-K48 -> 6298968285 | M48: 0.37 | N48: 0.05 | O48: =L48*N48 -> 3.1494841e+08 | P48: =O48/(1-M48) -> 4.9991812e+08 | Q48: =P48*M48 -> 1.849697e+08 | R48: 0.075 | S48: =L48*N48 + (L48*N48*R48*(4+3+2+1+0)/5) -> 3.6219068e+08 | T48: =S48/(1-M48) -> 5.7490584e+08 | U48: =T48*M48 -> 2.1271516e+08 | X48: Estimated value on homes.com is $916,859 - $1,131,000
A49: 47 | B49: Rick Caruso | C49: $5.9B | D49: 5900000000 | E49: Los Angeles | F49: =VLOOKUP(B49,Raw_Data_Collection!$B$2:$F$215,5,FALSE) -> N | G49: =VLOOKUP(B49,Raw_Data_Collection!$B$2:$J$215,6,FALSE) -> 80000000 | H49: https://xabisinc.com/blog/rick-carusos-net-worth-the-secrets-behind-his-real-estate-success/ | I49: 2025 | J49: =VLOOKUP(B49,Raw_Data_Collection!$B$2:$J$215,9,FALSE) -> 86500000 | K49: =VLOOKUP(B49,Real_Estate_Stats_Preferred!$A$2:$G$215,7,FALSE) -> 86500000 | L49: =D49-K49 -> 5813500000 | M49: 0.37 | N49: 0.05 | O49: =L49*N49 -> 290675000 | P49: =O49/(1-M49) -> 4.6138889e+08 | Q49: =P49*M49 -> 1.7071389e+08 | R49: 0.075 | S49: =L49*N49 + (L49*N49*R49*(4+3+2+1+0)/5) -> 334276250 | T49: =S49/(1-M49) -> 5.3059722e+08 | U49: =T49*M49 -> 1.9632097e+08 | V49: 2015-2025 | W49: https://www.celebritynetworth.com/richest-businessmen/richest-billionaires/rick-caruso-net-worth/ | X49: Caruso's primary estate is estimated to be worth $60-80 million.
A50: 48 | B50: Ken Xie | C50: $5.7B | D50: 5700000000 | E50: Los Altos Hills | F50: =VLOOKUP(B50,Raw_Data_Collection!$B$2:$F$215,5,FALSE) -> N | G50: =VLOOKUP(B50,Raw_Data_Collection!$B$2:$J$215,6,FALSE) -> 18104324 | J50: =VLOOKUP(B50,Raw_Data_Collection!$B$2:$J$215,9,FALSE) -> 14340561 | K50: =VLOOKUP(B50,Real_Estate_Stats_Preferred!$A$2:$G$215,7,FALSE) -> 14340561 | L50: =D50-K50 -> 5685659439 | M50: 0.37 | N50: 0.05 | O50: =L50*N50 -> 284282972 | P50: =O50/(1-M50) -> 4.5124281e+08 | Q50: =P50*M50 -> 1.6695984e+08 | R50: 0.075 | S50: =L50*N50 + (L50*N50*R50*(4+3+2+1+0)/5) -> 3.2692542e+08 | T50: =S50/(1-M50) -> 5.1892923e+08 | U50: =T50*M50 -> 1.9200382e+08 | V50: 2004-2024 | W50: https://www.celebritynetworth.com/richest-businessmen/richest-billionaires/ken-xie-net-worth/; https://blockshopper.com/ca/san-mateo-county/atherton/property/070120060/9-tuscaloosa-avenue
A51: 49 | B51: Jayshree Ullal | C51: $5.6B | D51: 5600000000 | E51: Saratoga | F51: =VLOOKUP(B51,Raw_Data_Collection!$B$2:$F$215,5,FALSE) -> N | G51: =VLOOKUP(B51,Raw_Data_Collection!$B$2:$J$215,6,FALSE) -> 877000 | H51: https://www.homes.com/property/190-n-lafayette-st-tracy-ca/x6xzt2lw9j9cx/ | I51: 2026 | J51: =VLOOKUP(B51,Raw_Data_Collection!$B$2:$J$215,9,FALSE) -> 7862000 | K51: =VLOOKUP(B51,Real_Estate_Stats_Preferred!$A$2:$G$215,7,FALSE) -> 7862000 | L51: =D51-K51 -> 5592138000 | M51: 0.37 | N51: 0.05 | O51: =L51*N51 -> 279606900 | P51: =O51/(1-M51) -> 4.4382048e+08 | Q51: =P51*M51 -> 1.6421358e+08 | R51: 0.075 | S51: =L51*N51 + (L51*N51*R51*(4+3+2+1+0)/5) -> 321547935 | T51: =S51/(1-M51) -> 5.1039355e+08 | U51: =T51*M51 -> 1.8884561e+08 | V51: 2026 | W51: https://www.homes.com/property/19384-chablis-ct-saratoga-ca/e3n5y70n6ed3h/; https://www.homes.com/property/190-n-lafayette-st-tracy-ca/x6xzt2lw9j9cx/ | X51: Estimated values on homes.com is $803,000 - $877,000 and $6,190,389 - $6,985,000.
A52: 50 | B52: Archie Aldis Emmerson | C52: $5.6B | D52: 5600000000 | E52: Redding | F52: =VLOOKUP(B52,Raw_Data_Collection!$B$2:$F$215,5,FALSE) -> N | G52: =VLOOKUP(B52,Raw_Data_Collection!$B$2:$J$215,6,FALSE) -> 4101800 | J52: =VLOOKUP(B52,Raw_Data_Collection!$B$2:$J$215,9,FALSE) -> 4101800 | K52: =VLOOKUP(B52,Real_Estate_Stats_Preferred!$A$2:$G$215,7,FALSE) -> 35618000 | L52: =D52-K52 -> 5564382000 | M52: 0.37 | N52: 0.05 | O52: =L52*N52 -> 278219100 | P52: =O52/(1-M52) -> 441617619 | Q52: =P52*M52 -> 163398519 | R52: 0.075 | S52: =L52*N52 + (L52*N52*R52*(4+3+2+1+0)/5) -> 319951965 | T52: =S52/(1-M52) -> 5.0786026e+08 | U52: =T52*M52 -> 1.879083e+08
A53: 51 | B53: Romesh T. Wadhwani | C53: $5.5B | D53: 5500000000 | E53: Palo Alto | F53: =VLOOKUP(B53,Raw_Data_Collection!$B$2:$F$215,5,FALSE) -> N | G53: =VLOOKUP(B53,Raw_Data_Collection!$B$2:$J$215,6,FALSE) -> 13169940 | J53: =VLOOKUP(B53,Raw_Data_Collection!$B$2:$J$215,9,FALSE) -> 13169940 | K53: =VLOOKUP(B53,Real_Estate_Stats_Preferred!$A$2:$G$215,7,FALSE) -> 34981964 | L53: =D53-K53 -> 5465018036 | M53: 0.37 | N53: 0.05 | O53: =L53*N53 -> 2.732509e+08 | P53: =O53/(1-M53) -> 4.3373159e+08 | Q53: =P53*M53 -> 1.6048069e+08 | R53: 0.075 | S53: =L53*N53 + (L53*N53*R53*(4+3+2+1+0)/5) -> 3.1423854e+08 | T53: =S53/(1-M53) -> 4.9879133e+08 | U53: =T53*M53 -> 1.8455279e+08
A54: 52 | B54: Neal Blue | C54: $5.4B | D54: 5400000000 | E54: San Diego | F54: =VLOOKUP(B54,Raw_Data_Collection!$B$2:$F$215,5,FALSE) -> N | G54: =VLOOKUP(B54,Raw_Data_Collection!$B$2:$J$215,6,FALSE) | J54: =VLOOKUP(B54,Raw_Data_Collection!$B$2:$J$215,9,FALSE) | K54: =VLOOKUP(B54,Real_Estate_Stats_Preferred!$A$2:$G$215,7,FALSE) -> 34345929 | L54: =D54-K54 -> 5365654071 | M54: 0.37 | N54: 0.05 | O54: =L54*N54 -> 2.682827e+08 | P54: =O54/(1-M54) -> 4.2584556e+08 | Q54: =P54*M54 -> 1.5756286e+08 | R54: 0.075 | S54: =L54*N54 + (L54*N54*R54*(4+3+2+1+0)/5) -> 3.0852511e+08 | T54: =S54/(1-M54) -> 4.897224e+08 | U54: =T54*M54 -> 1.8119729e+08
A55: 53 | B55: Gordon Getty | C55: $5.4B | D55: 5400000000 | E55: San Francisco | F55: =VLOOKUP(B55,Raw_Data_Collection!$B$2:$F$215,5,FALSE) -> N | G55: =VLOOKUP(B55,Raw_Data_Collection!$B$2:$J$215,6,FALSE) -> 29608760 | H55: https://blockshopper.com/ca/san-francisco-county/san-francisco/property/0958030/2870-broadway-street; https://www.redfin.com/CA/San-Francisco/2870-Broadway-St-94115/home/1811887#property-details | I55: 2026 | J55: =VLOOKUP(B55,Raw_Data_Collection!$B$2:$J$215,9,FALSE) -> 29608760 | K55: =VLOOKUP(B55,Real_Estate_Stats_Preferred!$A$2:$G$215,7,FALSE) -> 29608760 | L55: =D55-K55 -> 5370391240 | M55: 0.37 | N55: 0.05 | O55: =L55*N55 -> 268519562 | P55: =O55/(1-M55) -> 426221527 | Q55: =P55*M55 -> 157701965 | R55: 0.075 | S55: =L55*N55 + (L55*N55*R55*(4+3+2+1+0)/5) -> 3.087975e+08 | T55: =S55/(1-M55) -> 490154756 | U55: =T55*M55 -> 1.8135726e+08 | V55: 2026 | W55: https://blockshopper.com/ca/san-francisco-county/san-francisco/property/0958030/2870-broadway-street; https://www.redfin.com/CA/San-Francisco/2870-Broadway-St-94115/home/1811887#property-details | X55: Estimated value on redfin.com is $29,608,760.
A56: 54 | B56: Patrick Soon-Shiong | C56: $5.4B | D56: 5400000000 | E56: Los Angeles | F56: =VLOOKUP(B56,Raw_Data_Collection!$B$2:$F$215,5,FALSE) -> N | G56: =VLOOKUP(B56,Raw_Data_Collection!$B$2:$J$215,6,FALSE) -> 30000000 | H56: https://www.celebritynetworth.com/articles/celebrity-homes/patrick-soon-shiongs-house-brentwood-billionaire-doctor-demolished-seven-houses-build-one-insane-mega-property/ | I56: 2014 | J56: =VLOOKUP(B56,Raw_Data_Collection!$B$2:$J$215,9,FALSE) -> 162500000 | K56: =VLOOKUP(B56,Real_Estate_Stats_Preferred!$A$2:$G$215,7,FALSE) -> 162500000 | L56: =D56-K56 -> 5237500000 | M56: 0.37 | N56: 0.05 | O56: =L56*N56 -> 261875000 | P56: =O56/(1-M56) -> 4.156746e+08 | Q56: =P56*M56 -> 1.537996e+08 | R56: 0.075 | S56: =L56*N56 + (L56*N56*R56*(4+3+2+1+0)/5) -> 301156250 | T56: =S56/(1-M56) -> 4.7802579e+08 | U56: =T56*M56 -> 1.7686954e+08 | V56: 2005-2016 | W56: https://www.ocregister.com/2016/02/04/oceanfront-laguna-beach-estate-twin-points-sells-for-record-shattering-45-million/; https://virtualglobetrotting.com/map/patrick-soon-shiongs-house-2/view/google/; https://www.ocbj.com/special-report/ocs-wealthiest-2024/ocs-wealthiest-2024-patrick-soon-shiong/; https://www.celebritynetworth.com/articles/celebrity-homes/patrick-soon-shiongs-house-brentwood-billionaire-doctor-demolished-seven-houses-build-one-insane-mega-property/ | X56: Main estate consists of 7 properties combined for $30 million dollars according to celebritynetworth.com
A57: 55 | B57: Jean (Gigi) Pritzker | C57: $5.4B | D57: 5400000000 | E57: Los Angeles | F57: =VLOOKUP(B57,Raw_Data_Collection!$B$2:$F$215,5,FALSE) -> N | G57: =VLOOKUP(B57,Raw_Data_Collection!$B$2:$J$215,6,FALSE) | J57: =VLOOKUP(B57,Raw_Data_Collection!$B$2:$J$215,9,FALSE) | K57: =VLOOKUP(B57,Real_Estate_Stats_Preferred!$A$2:$G$215,7,FALSE) -> 34345929 | L57: =D57-K57 -> 5365654071 | M57: 0.37 | N57: 0.05 | O57: =L57*N57 -> 2.682827e+08 | P57: =O57/(1-M57) -> 4.2584556e+08 | Q57: =P57*M57 -> 1.5756286e+08 | R57: 0.075 | S57: =L57*N57 + (L57*N57*R57*(4+3+2+1+0)/5) -> 3.0852511e+08 | T57: =S57/(1-M57) -> 4.897224e+08 | U57: =T57*M57 -> 1.8119729e+08
A58: 56 | B58: Stewart Resnick | C58: $5.3B | D58: 5300000000 | E58: Beverly Hills | F58: =VLOOKUP(B58,Raw_Data_Collection!$B$2:$F$215,5,FALSE) -> N | G58: =VLOOKUP(B58,Raw_Data_Collection!$B$2:$J$215,6,FALSE) -> 17115689 | H58: https://www.homes.com/property/9491-sunset-blvd-beverly-hills-ca/sw2h7klpb942m/ | I58: 2026 | J58: =VLOOKUP(B58,Raw_Data_Collection!$B$2:$J$215,9,FALSE) -> 17115689 | K58: =VLOOKUP(B58,Real_Estate_Stats_Preferred!$A$2:$G$215,7,FALSE) -> 17115689 | L58: =D58-K58 -> 5282884311 | M58: 0.37 | N58: 0.05 | O58: =L58*N58 -> 2.6414422e+08 | P58: =O58/(1-M58) -> 4.1927653e+08 | Q58: =P58*M58 -> 1.5513232e+08 | R58: 0.075 | S58: =L58*N58 + (L58*N58*R58*(4+3+2+1+0)/5) -> 3.0376585e+08 | T58: =S58/(1-M58) -> 4.8216801e+08 | U58: =T58*M58 -> 1.7840216e+08 | V58: 2026 | W58: https://www.homes.com/property/9491-sunset-blvd-beverly-hills-ca/sw2h7klpb942m/ | X58: Estimated value on homes.com is $8,902,000 - $17,115,689.
A59: 57 | B59: Lynda Resnick | C59: $5.3B | D59: 5300000000 | E59: Beverly Hills | F59: =VLOOKUP(B59,Raw_Data_Collection!$B$2:$F$215,5,FALSE) -> N | G59: =VLOOKUP(B59,Raw_Data_Collection!$B$2:$J$215,6,FALSE) -> 17115689 | H59: https://www.homes.com/property/9491-sunset-blvd-beverly-hills-ca/sw2h7klpb942m/ | I59: 2026 | J59: =VLOOKUP(B59,Raw_Data_Collection!$B$2:$J$215,9,FALSE) -> 17115689 | K59: =VLOOKUP(B59,Real_Estate_Stats_Preferred!$A$2:$G$215,7,FALSE) -> 17115689 | L59: =D59-K59 -> 5282884311 | M59: 0.37 | N59: 0.05 | O59: =L59*N59 -> 2.6414422e+08 | P59: =O59/(1-M59) -> 4.1927653e+08 | Q59: =P59*M59 -> 1.5513232e+08 | R59: 0.075 | S59: =L59*N59 + (L59*N59*R59*(4+3+2+1+0)/5) -> 3.0376585e+08 | T59: =S59/(1-M59) -> 4.8216801e+08 | U59: =T59*M59 -> 1.7840216e+08 | V59: 2026 | W59: https://www.homes.com/property/9491-sunset-blvd-beverly-hills-ca/sw2h7klpb942m/ | X59: Estimated value on homes.com is $8,902,000 - $17,115,689.
A60: 58 | B60: Eduardo Vivas | C60: $5.3B | D60: 5300000000 | E60: Palo Alto | F60: =VLOOKUP(B60,Raw_Data_Collection!$B$2:$F$215,5,FALSE) -> N | G60: =VLOOKUP(B60,Raw_Data_Collection!$B$2:$J$215,6,FALSE) | J60: =VLOOKUP(B60,Raw_Data_Collection!$B$2:$J$215,9,FALSE) | K60: =VLOOKUP(B60,Real_Estate_Stats_Preferred!$A$2:$G$215,7,FALSE) -> 33709893 | L60: =D60-K60 -> 5266290107 | M60: 0.37 | N60: 0.05 | O60: =L60*N60 -> 2.6331451e+08 | P60: =O60/(1-M60) -> 4.1795953e+08 | Q60: =P60*M60 -> 154645027 | R60: 0.075 | S60: =L60*N60 + (L60*N60*R60*(4+3+2+1+0)/5) -> 3.0281168e+08 | T60: =S60/(1-M60) -> 4.8065346e+08 | U60: =T60*M60 -> 177841781
A61: 59 | B61: George Lucas | C61: $5.3B | D61: 5300000000 | E61: San Anselmo | F61: =VLOOKUP(B61,Raw_Data_Collection!$B$2:$F$215,5,FALSE) -> N | G61: =VLOOKUP(B61,Raw_Data_Collection!$B$2:$J$215,6,FALSE) -> 41600000 | H61: https://www.marinij.com/2023/07/29/george-lucas-sues-to-secure-san-anselmo-parcel-ownership/ | I61: 2026 | J61: =VLOOKUP(B61,Raw_Data_Collection!$B$2:$J$215,9,FALSE) -> 123000000 | K61: =VLOOKUP(B61,Real_Estate_Stats_Preferred!$A$2:$G$215,7,FALSE) -> 123000000 | L61: =D61-K61 -> 5177000000 | M61: 0.37 | N61: 0.05 | O61: =L61*N61 -> 258850000 | P61: =O61/(1-M61) -> 4.1087302e+08 | Q61: =P61*M61 -> 1.5202302e+08 | R61: 0.075 | S61: =L61*N61 + (L61*N61*R61*(4+3+2+1+0)/5) -> 297677500 | T61: =S61/(1-M61) -> 4.7250397e+08 | U61: =T61*M61 -> 1.7482647e+08 | V61: 2010-2023 | W61: https://robbreport.com/shelter/celebrity-homes/lists/george-lucas-property-portfolio-1237348814/; https://www.sfgate.com/realestate/article/George-Lucas-Carpinteria-houses-owned-property-14885154.php; https://www.marinij.com/2023/07/29/george-lucas-sues-to-secure-san-anselmo-parcel-ownership/ | X61: Lucas also owns "Skywalker Ranch", but this is not a residential property and is instead used for business.
A62: 60 | B62: Reed Hastings | C62: $5.1B | D62: 5100000000 | E62: Santa Cruz | F62: N | G62: =VLOOKUP(B62,Raw_Data_Collection!$B$2:$J$215,6,FALSE) -> 1750000 | H62: https://www.celebritynetworth.com/richest-businessmen/ceos/reed-hastings-net-worth/ | I62: 2016 | J62: =VLOOKUP(B62,Raw_Data_Collection!$B$2:$J$215,9,FALSE) -> 3250000 | K62: =VLOOKUP(B62,Real_Estate_Stats_Preferred!$A$2:$G$215,7,FALSE) -> 3250000 | L62: =D62-K62 -> 5096750000 | M62: 0.37 | N62: 0.05 | O62: =L62*N62 -> 254837500 | P62: =O62/(1-M62) -> 4.0450397e+08 | Q62: =P62*M62 -> 1.4966647e+08 | R62: 0.075 | S62: =L62*N62 + (L62*N62*R62*(4+3+2+1+0)/5) -> 293063125 | T62: =S62/(1-M62) -> 4.6517956e+08 | U62: =T62*M62 -> 1.7211644e+08 | V62: 2013-2016 | W62: https://www.celebritynetworth.com/richest-businessmen/ceos/reed-hastings-net-worth/ | X62: Hastings also owns property in Hollywood. | Y62: https://nypost.com/2026/01/08/real-estate/tech-titans-leaving-california-for-florida-over-billionaire-tax/
A63: 61 | B63: Eric Yuan | C63: $5.1B | D63: 5100000000 | E63: Santa Clara | F63: =VLOOKUP(B63,Raw_Data_Collection!$B$2:$F$215,5,FALSE) -> N | G63: =VLOOKUP(B63,Raw_Data_Collection!$B$2:$J$215,6,FALSE) | J63: =VLOOKUP(B63,Raw_Data_Collection!$B$2:$J$215,9,FALSE) | K63: =VLOOKUP(B63,Real_Estate_Stats_Preferred!$A$2:$G$215,7,FALSE) -> 32437821 | L63: =D63-K63 -> 5067562179 | M63: 0.37 | N63: 0.05 | O63: =L63*N63 -> 2.5337811e+08 | P63: =O63/(1-M63) -> 4.0218747e+08 | Q63: =P63*M63 -> 1.4880937e+08 | R63: 0.075 | S63: =L63*N63 + (L63*N63*R63*(4+3+2+1+0)/5) -> 2.9138483e+08 | T63: =S63/(1-M63) -> 4.625156e+08 | U63: =T63*M63 -> 1.7113077e+08
A64: 62 | B64: Gwendolyn Sontheim Meyer | C64: $5B | D64: 5000000000 | E64: Rancho Santa Fe | F64: =VLOOKUP(B64,Raw_Data_Collection!$B$2:$F$215,5,FALSE) -> N | G64: =VLOOKUP(B64,Raw_Data_Collection!$B$2:$J$215,6,FALSE) | J64: =VLOOKUP(B64,Raw_Data_Collection!$B$2:$J$215,9,FALSE) | K64: =VLOOKUP(B64,Real_Estate_Stats_Preferred!$A$2:$G$215,7,FALSE) -> 31801786 | L64: =D64-K64 -> 4968198214 | M64: 0.37 | N64: 0.05 | O64: =L64*N64 -> 2.4840991e+08 | P64: =O64/(1-M64) -> 3.9430145e+08 | Q64: =P64*M64 -> 1.4589153e+08 | R64: 0.075 | S64: =L64*N64 + (L64*N64*R64*(4+3+2+1+0)/5) -> 2.856714e+08 | T64: =S64/(1-M64) -> 4.5344666e+08 | U64: =T64*M64 -> 1.6777527e+08
A65: 63 | B65: Jim Coulter | C65: $5B | D65: 5000000000 | E65: San Francisco | F65: =VLOOKUP(B65,Raw_Data_Collection!$B$2:$F$215,5,FALSE) -> N | G65: =VLOOKUP(B65,Raw_Data_Collection!$B$2:$J$215,6,FALSE) | J65: =VLOOKUP(B65,Raw_Data_Collection!$B$2:$J$215,9,FALSE) | K65: =VLOOKUP(B65,Real_Estate_Stats_Preferred!$A$2:$G$215,7,FALSE) -> 31801786 | L65: =D65-K65 -> 4968198214 | M65: 0.37 | N65: 0.05 | O65: =L65*N65 -> 2.4840991e+08 | P65: =O65/(1-M65) -> 3.9430145e+08 | Q65: =P65*M65 -> 1.4589153e+08 | R65: 0.075 | S65: =L65*N65 + (L65*N65*R65*(4+3+2+1+0)/5) -> 2.856714e+08 | T65: =S65/(1-M65) -> 4.5344666e+08 | U65: =T65*M65 -> 1.6777527e+08
A66: 64 | B66: Jack Dorsey | C66: $4.9B | D66: 4900000000 | E66: San Francisco | F66: =VLOOKUP(B66,Raw_Data_Collection!$B$2:$F$215,5,FALSE) -> N | G66: =VLOOKUP(B66,Raw_Data_Collection!$B$2:$J$215,6,FALSE) -> 31900000 | H66: https://www.yahoo.com/entertainment/twitter-ceo-jack-dorsey-scoops-011751538.html | I66: 2018 | J66: =VLOOKUP(B66,Raw_Data_Collection!$B$2:$J$215,9,FALSE) -> 31900000 | K66: =VLOOKUP(B66,Real_Estate_Stats_Preferred!$A$2:$G$215,7,FALSE) -> 31900000 | L66: =D66-K66 -> 4868100000 | M66: 0.37 | N66: 0.05 | O66: =L66*N66 -> 243405000 | P66: =O66/(1-M66) -> 3.8635714e+08 | Q66: =P66*M66 -> 1.4295214e+08 | R66: 0.075 | S66: =L66*N66 + (L66*N66*R66*(4+3+2+1+0)/5) -> 279915750 | T66: =S66/(1-M66) -> 4.4431071e+08 | U66: =T66*M66 -> 1.6439496e+08 | V66: 2012-2018 | W66: https://www.yahoo.com/entertainment/twitter-ceo-jack-dorsey-scoops-011751538.html; https://www.yahoo.com/entertainment/jack-dorsey-hollywood-hills-hideaway-015224916.html | X66: Compound consists of two residences, one bought in 2012 for $10 million and one bought in 2019 for $21.9 million. His Hollywood Hills residence was later sold.
A67: 65 | B67: David Baszucki | C67: $4.9B | D67: 4900000000 | E67: San Francisco | F67: =VLOOKUP(B67,Raw_Data_Collection!$B$2:$F$215,5,FALSE) -> N | G67: =VLOOKUP(B67,Raw_Data_Collection!$B$2:$J$215,6,FALSE) | J67: =VLOOKUP(B67,Raw_Data_Collection!$B$2:$J$215,9,FALSE) | K67: =VLOOKUP(B67,Real_Estate_Stats_Preferred!$A$2:$G$215,7,FALSE) -> 31165750 | L67: =D67-K67 -> 4868834250 | M67: 0.37 | N67: 0.05 | O67: =L67*N67 -> 2.4344171e+08 | P67: =O67/(1-M67) -> 3.8641542e+08 | Q67: =P67*M67 -> 1.429737e+08 | R67: 0.075 | S67: =L67*N67 + (L67*N67*R67*(4+3+2+1+0)/5) -> 2.7995797e+08 | T67: =S67/(1-M67) -> 4.4437773e+08 | U67: =T67*M67 -> 1.6441976e+08
